Workbook
Name ВстроеннаяВременнаяШкала_Дата_начала: #N/A
Name Срез_Скважина: #N/A
Name Срез_Этап: #N/A

Sheet Планы работ
L17: План работ по скважине №851 (к.п. №26) – стандартная форма
L18: Скважина | M18: ОК | N18: Этап | O18: Контекст простоя | P18: Событие | Q18: Категория работ | R18: Вид работ | S18: Категория объектов | T18: Объект работ | U18: Рейс | V18: Описание (кратко) | W18: Часы (план)
L19: 851 | N19: ДПМ | O19: Штатно | Q19: ПР | R19: Передвижка | S19: Оборудование | T19: УПА | V19: Переезд бригады на скв. №851, расстановка оборудования | W19: 3.5
L20: 851 | N20: ПР | O20: Штатно | Q20: Вспом_работы | R20: Завоз | S20: Объекты_промывка_СО | T20: Тех. вода | V20: Набор тех. воды со скв. №858 (V=66,2 м³), обработка ПАВ 0,03% | W20: 10
L21: 851 | N21: ПР | O21: Штатно | Q21: Контроль_замер | R21: Опрессовка | S21: Объекты_устье | T21: Фонтанная арматура | V21: Опрессовка лифта НКТП на 6 МПа и обратного клапана ФА на 4 МПа (негерметично). Демонтаж оборудования КИПа, метанольных линий | W21: 0.77
L22: 851 | N22: ПР | O22: Штатно | Q22: Циркуляция | R22: Обратная промывка | S22: Скважина_ствол | T22: Скважина | V22: Глушение скважины обратной промывкой 1,01 г/см³, Q=7 л/с, V=21 м³ (продолжение) | W22: 5
L23: 851 | N23: ПР | O23: Штатно | Q23: Циркуляция | R23: Обратная промывка | S23: Скважина_ствол | T23: Скважина | V23: Глушение обратной промывкой 1,01 г/см³, V=35 м³ (общ. 56,2 м³), рост давления до 10 МПа. Техотстой 3 ч, разрядка с 4 до 0 МПа, выход конденсата+газ | W23: 8
L24: 851 | N24: ПР | O24: Штатно | Q24: Монтаж_демонтаж_установка | R24: Монтаж | S24: Оборудование | T24: УПА | V24: Монтаж УПРС-80 (30%). Подвоз грунта, отсыпка под приёмный мост и 3 стеллажа | W24: 6
L25: 851 | N25: ПР | O25: Штатно | Q25: Монтаж_демонтаж_установка | R25: Монтаж | S25: Оборудование | T25: УПА | V25: Монтаж УПРС-80 (90%). Долив скважины V=0,5 м³ (общий долив 3 м³) | W25: 2.1
L26: 851 | N26: ПР | O26: Штатно | Q26: Монтаж_демонтаж_установка | R26: Демонтаж | S26: Объекты_устье | T26: Фонтанная арматура | V26: Получение разрешения на демонтаж ФА, монтаж ПВО. Подрыв ПШ (G=43 тн). Демонтаж КВ, протаскивание кабеля, демонтаж ФА | W26: 2.29
L27: 851 | N27: КРС | O27: Штатно | Q27: Монтаж_демонтаж_установка | R27: Монтаж | S27: Объекты_устье | T27: ПВО | V27: Монтаж 2 отбойных щитов, штурвалов, подключение СУП, монтаж выносного пульта, монтаж ПВО (100%) | W27: 1.35
L28: 851 | N28: КРС | O28: Штатно | Q28: СПО | R28: Спуск | S28: Технологический_инструмент | T28: Пакер | V28: Спуск пакера на глубину 30 м. Подготовка к опрессовке ПВО | W28: 0.97
L29: 851 | N29: КРС | O29: Орг_простой | Q29: Простой | R29: Ожидание | S29: Орг_логист_объекты | T29: Техника | V29: Ожидание спецтехники (ЦА-320) для опрессовки | W29: 4
L30: 851 | N30: КРС | O30: Штатно | Q30: Контроль_замер | R30: Опрессовка | S30: Объекты_устье | T30: ПВО | V30: Опрессовка трубных плашек 73 мм с представителем ВСВЧ на 23 МПа (+). Получение разрешения на дальнейшие работы | W30: 6
... L32: 851 | N32: КРС | O32: Штатно | Q32: Циркуляция | R32: Обратная промывка | S32: Скважина_ствол | T32: Скважина | V32: Подготовка к промывке. Обратная промывка раствором 1,01 г/см³ V=37,5 м³, Р=0→10→50 МПа, Q=7 л/с, циркуляция (+). Разрядка (+). Подготовка к подъёму ЭЦН | W32: 0.77
L33: 851 | N33: КРС | O33: Штатно | Q33: СПО | R33: Подъем | S33: Технологический_инструмент | T33: УЭЦН | U33: 1 | V33: Подъём ЭЦН с 2859,88 м до 2600 м (20 шт НКТП-73 мм). Долив 3 м³ | W33: 4
L34: 851 | N34: КРС | O34: Штатно | Q34: СПО | R34: Подъем | S34: Технологический_инструмент | T34: УЭЦН | U34: 1 | V34: Подъём ЭЦН с 2600 м до 1819 м (106 шт, всего 80 шт? уточнение: общее количество поднятых 80 шт – возможно опечатка, оставим как есть). Долив 2 м³ | W34: 8
L35: 851 | N35: КРС | O35: Штатно | Q35: СПО | R35: Подъем | S35: Технологический_инструмент | T35: УЭЦН | U35: 1 | V35: Подъём ЭЦН с 1819 м до 1365 м, ВИК первого ряда. Поднято 156 шт НКТП-73 мм. Долив 30 м³ | W35: 7
L36: 851 | N36: КРС | O36: Штатно | Q36: СПО | R36: Подъем | S36: Технологический_инструмент | T36: УЭЦН | U36: 1 | V36: Подъём ЭЦН с 1365 м до 672,31 м, ВИК 228-229, опрессовка лифта 6 МПа (+), замер изоляции (отсутствует), сброс спецштанги Ø25 мм L=1,2 м (+). Подъём до 0 м | W36: 4.44
L37: 851 | N37: КРС | O37: Штатно | Q37: Сборка_разборка_оснащение | R37: Разборка | S37: Технологический_инструмент | T37: УЭЦН | V37: Комиссионный демонтаж ЭЦН | W37: 2.5
L38: 851 | N38: КРС | O38: Штатно | Q38: Вспом_работы | R38: Подготовка | S38: Технологический_инструмент | T38: УЭЦН | V38: Центровка мачты, разгрузка оборудования ЭЦН, подготовка к опрессовке подклапанных НКТП-73 (6 шт.) | W38: 0.9
L39: 851 | N39: КРС | O39: Штатно | Q39: Контроль_замер | R39: Опрессовка | S39: Технологический_инструмент | T39: УЭЦН | V39: Опрессовка подклапанных НКТ-73 (6 шт.) на 25 МПа (+). Монтаж доп. оборудования + ЭЦН (ЭЦНМТ5-80/2260/8ЭДРТ-56-117) | W39: 6
L40: 851 | N40: КРС | O40: Штатно | Q40: СПО | R40: Спуск | S40: Технологический_инструмент | T40: УЭЦН | U40: 1 | V40: Спуск ЭЦН до глубины 877,66 м (92 шт НКТП-73 мм). Долив 38,3 м³ | W40: 14.5
L41: 851 | N41: КРС | O41: Штатно | Q41: СПО | R41: Спуск | S41: Технологический_инструмент | T41: УЭЦН | U41: 1 | V41: Спуск ЭЦН до 1532,37 м (всего 160 шт). Опрессовка лифта через 600 м (6 МПа). Долив 40 м³ | W41: 8
L42: 851 | N42: КРС | O42: Штатно | Q42: СПО | R42: Спуск | S42: Технологический_инструмент | T42: УЭЦН | U42: 1 | V42: Спуск ЭЦН до 1933,38 м (всего 202 шт). Долив 59 м³ | W42: 4
L43: 851 | N43: КРС | O43: Штатно | Q43: СПО | R43: Спуск | S43: Технологический_инструмент | T43: УЭЦН | U43: 1 | V43: Спуск ЭЦН до 2226 м (всего 232 шт). Долив 62 м³ | W43: 0.5
L44: 851 | N44: КРС | O44: Штатно | Q44: Ремонт | R44: Ремонт | S44: Оборудование | T44: УПА | V44: Ремонт УБРСП-80 (замена ремня компрессора) | W44: 0
L45: 851 | N45: Заканчивание | O45: Штатно | Q45: Монтаж_демонтаж_установка | R45: Перемонтаж | S45: Объекты_устье | T45: Фонтанная арматура | V45: Демонтаж ГКШ-1500, СУ-80, отбойных щитов, штурвалов, линии долива. Демонтаж ПВО с протаскиванием кабеля (35 м). Монтаж ФА и кабельного ввода, опрессовка КВ на 11 МПа. Монтаж обвязки ФА. Укладка кабеля (35 м). Контрольный замер изоляции | W45: 4.5
L46: 851 | N46: ДПМ | O46: Штатно | Q46: Монтаж_демонтаж_установка | R46: Демонтаж | S46: Оборудование | T46: УПА | V46: Демонтаж РП, ИВЭ-50 | W46: 1.5
L47: 851 | N47: Заканчивание | O47: Штатно | Q47: Контроль_замер | R47: Опрессовка | S47: Объекты_устье | T47: Фонтанная арматура | V47: Опрессовка ОК ФА и обвязки на 4 МПа (герметично), опрессовка лифта НКТП на 6 МПа (герметично) | W47: 0.9
L48: 851 | N48: Заканчивание | O48: Штатно | Q48: Испытания | R48: Запуск в работу | S48: Технологический_инструмент | T48: УЭЦН | V48: Замер изоляции перед запуском (200 МОм). Запуск ЭЦНМТ5-80/2260/8ЭДРТ-56-117, параметры: Iпуск=19,8А, Iраб=18,2А, 40Гц, загрузка 41%, Рпр=181 атм, Tпр=75°С, дебит 115 м³/сут | W48: 0.5
L49: 851 | N49: ДПМ | O49: Штатно | Q49: Монтаж_демонтаж_установка | R49: Демонтаж | S49: Оборудование | T49: УПА | V49: Демонтаж УБРСП-80, пригрузов, якорей, приёмного моста, стеллажей. Монтаж дублирующей ЗД №2, опрессовка фланца | W49: 3
L50: 851 | N50: ДПМ | O50: Штатно | Q50: Монтаж_демонтаж_установка | R50: Демонтаж | S50: Оборудование | T50: БО | V50: Демонтаж 1 защитного колпака, монтаж 2 лубрикаторных площадок | W50: 2
L51: 851 | N51: ДПМ | O51: Штатно | Q51: Монтаж_демонтаж_установка | R51: Демонтаж | S51: Оборудование | T51: БО | V51: Демонтаж заземлений (9 шт.), отключение оборудования (4 шт.), демонтаж подставок под кабель (5 шт.), уборка территории | W51: 0.84
L63: План работ по скважине №851 (к.п. №26 КНГКМ) – стандартная форма
L64: ОК | M64: Этап | N64: Контекст простоя | O64: Событие | P64: Категория работ | Q64: Вид работ | R64: Категория объектов | S64: Объект работ | T64: Рейс | U64: Описание | V64: Часы
M65: ДПМ | N65: Штатно | P65: ПР | Q65: Передвижка | R65: Оборудование | S65: УПА | U65: Переезд бригады на скв. №851 (9 рейсов, L=0,015 км) | V65: 0.87
M66: ДПМ | N66: Штатно | P66: Монтаж_демонтаж_установка | Q66: Монтаж | R66: Оборудование | S66: БО | U66: Расстановка оборудования (9 шт.), установка заземлений (9 шт.), подключение (4 шт.), установка подставок под кабель (5 шт.), демонтаж 2‑х лубрикаторных площадок, монтаж 1 защитного колпака | V66: 2.92
M67: ПР | N67: Штатно | P67: Вспом_работы | Q67: Завоз | R67: Объекты_промывка_СО | S67: Тех. вода | U67: Монтаж линии набора воды, набор тех. воды 66,2 м³ (ρ=1,01), обработка ПАВ, отбор пробы. Параллельный завоз жидкости глушения 82 м³ | V67: 10.22
M68: ПР | N68: Штатно | P68: Контроль_замер | Q68: Опрессовка | R68: Объекты_устье | S68: ПВО | U68: Опрессовка превентора с трубными плашками 73 мм до установки на устье (рабочее давление) | V68: 0.36
M69: ПР | N69: Штатно | P69: Контроль_замер | Q69: Опрессовка | R69: Объекты_устье | S69: Фонтанная арматура | U69: Опрессовка лифта НКТП на 6 МПа и обратного клапана ФА на 4 МПа | V69: 0.71
M70: ПР | N70: Штатно | P70: Циркуляция | Q70: Обратная промывка | R70: Скважина_ствол | S70: Скважина | U70: Глушение скважины обратной промывкой раствором 1,01 г/см³ V=56,2 м³, технологическая стоянка 2 ч, разрядка, долив | V70: 8.55
M71: ПР | N71: Штатно | P71: Монтаж_демонтаж_установка | Q71: Монтаж | R71: Оборудование | S71: УПА | U71: Монтаж подъемника УБРСП-80, устройство 2 якорей, установка пригрузов (2 компл.), монтаж приёмного моста, 3 стеллажей, рабочей площадки, спайдера СУ-80, гидроключа ГКШ-1500, ИВЭ-50, испытание якорей | V71: 8.11
M72: ПР | N72: Штатно | P72: Циркуляция | Q72: Промывка | R72: Скважина_ствол | S72: Скважина | U72: Промывка скважины с целью дегазации (35 м³, ρ=1,01 г/см³) | V72: 2.2
M73: КРС | N73: Штатно | P73: Монтаж_демонтаж_установка | Q73: Демонтаж | R73: Объекты_устье | S73: Фонтанная арматура | U73: Снятие кабеля с эстакады, демонтаж ёлки АФ и кабельного ввода, подготовка ФА к ревизии (пропарка) | V73: 2.29
M74: КРС | N74: Штатно | P74: Сборка_разборка_оснащение | Q74: Расхаживание | R74: Технологический_инструмент | S74: УЭЦН | U74: Расхаживание подвески с УЭЦН со ступенчатым увеличением веса до 47 тн | V74: 2
M75: КРС | N75: Штатно | P75: Монтаж_демонтаж_установка | Q75: Монтаж | R75: Объекты_устье | S75: ПВО | U75: Монтаж превентора, 2 отбойных щитов, 4 дистанционных штурвалов | V75: 1.35
M76: КРС | N76: Штатно | P76: СПО | Q76: Спуск | R76: Технологический_инструмент | S76: Пакер | U76: Монтаж, спуск и посадка пакера на глубину 30 м, опрессовка ПВО с пакером на 23 МПа (видеорегистрация) | V76: 0.97
... M80: КРС | N80: Штатно | P80: Циркуляция | Q80: Обратная промывка | R80: Скважина_ствол | S80: Скважина | U80: Обратная промывка скважины раствором глушения V=37,5 м³ (перед подъёмом УЭЦН) | V80: 1.78
M81: КРС | N81: Штатно | P81: СПО | Q81: Подъем | R81: Технологический_инструмент | S81: УЭЦН | T81: 1 | U81: Комиссионный подъём УЭЦН с глубины 2859,88 м до «зеркала», опрессовка лифта, замер изоляции, ВИК. При необходимости – сбив СК и полный подъём | V81: 23.45
M82: КРС | N82: Штатно | P82: Контроль_замер | Q82: Опрессовка | R82: Технологический_инструмент | S82: НКТ | U82: Опрессовка на стеллажах НКТП (4 шт. выше зеркала, 2 шт. ниже) на 25 МПа | V82: 0.3
M83: КРС | N83: Штатно | P83: Сборка_разборка_оснащение | Q83: Разборка | R83: Технологический_инструмент | S83: УЭЦН | U83: Комиссионный демонтаж УЭЦН (3 секции насоса, газосепаратор, 1 секция ПЭД) | V83: 5.05
M84: КРС | N84: Штатно | P84: Вспом_работы | Q84: Подготовка | R84: Технологический_инструмент | S84: УЭЦН | U84: Установка барабана на автовымотку, разгрузка УЭЦН, опрессовка подклапанных НКТП (4 шт.) на 25 МПа, сверка номеров, ВИК резьб, протаскивание кабеля 50 м | V84: 0.98
M85: КРС | N85: Штатно | P85: Сборка_разборка_оснащение | Q85: Сборка | R85: Технологический_инструмент | S85: УЭЦН | U85: Центровка мачты, монтаж УЭЦН (ЭЦНМТ5-80-2200: ПЭД, гидрозащита, газосепаратор, 2 секции ЭЦН) | V85: 7.78
M86: КРС | N86: Штатно | P86: СПО | Q86: Спуск | R86: Технологический_инструмент | S86: УЭЦН | T86: 1 | U86: Настройка ГКШ-1200МТ, сборка и опрессовка компоновки на 20 МПа. Спуск УЭЦН на 2860 м с поинтервальной опрессовкой НКТ через 600 м (6 МПа), замером изоляции через 300 м, установкой противополётного кольца на 800 м | V86: 27.2
M87: Заканчивание | N87: Штатно | P87: Монтаж_демонтаж_установка | Q87: Перемонтаж | R87: Объекты_устье | S87: Фонтанная арматура | U87: Демонтаж ГКШ-1500, СУ-80, превентора с протаскиванием кабеля 50 м, демонтаж отбойных щитов и штурвалов. Монтаж ёлки АФ и кабельного ввода, опрессовка КВ на 11 МПа, укладка кабеля 50 м | V87: 4.53
M88: Заканчивание | N88: Штатно | P88: Контроль_замер | Q88: Опрессовка | R88: Объекты_устье | S88: Фонтанная арматура | U88: Опрессовка НКТП-73 на 6 МПа и ФА с обвязкой на 4 МПа | V88: 0.9
M89: Заканчивание | N89: Штатно | P89: Испытания | Q89: Запуск в работу | R89: Технологический_инструмент | S89: УЭЦН | U89: Запуск скважины в коллектор | V89: 0.6
M90: ДПМ | N90: Штатно | P90: Монтаж_демонтаж_установка | Q90: Демонтаж | R90: Оборудование | S90: УПА | U90: Демонтаж ИВЭ-50, рабочей площадки, УПА 60/80, пригрузов, якорей, приёмного моста, 3 стеллажей, линии долива | V90: 4.58
M91: ДПМ | N91: Штатно | P91: Монтаж_демонтаж_установка | Q91: Демонтаж | R91: Оборудование | S91: БО | U91: Демонтаж 1 защитного колпака, монтаж 2 лубрикаторных площадок, демонтаж заземлений (9 ед.), отключение оборудования (4 ед.), демонтаж подставок под кабель (5 шт.), уборка территории | V91: 2.84
L92: Примечания:
L93: Операции с нулевой длительностью (согласования, заявки, акты готовности, разрешения, ВИК, фотофиксация и т.п.) исключены.
L94: Рейс проставлен только для подъёма и спуска УЭЦН (рейс 1), чт
M97: Фактическая хронология работ по скважине №851 – стандартная форма (по плану)
M98: ОК | N98: Этап | O98: Контекст простоя | P98: Событие | Q98: Категория работ | R98: Вид работ | S98: Категория объектов | T98: Объект работ | U98: Рейс | V98: Описание работ | W98: Часы
N99: ДПМ | O99: Штатно | Q99: ПР | R99: Передвижка | S99: Оборудование | T99: УПА | V99: Переезд бригады на скв. №851 (9 рейсов, L=0,015 км). Расстановка оборудования (9 шт.), установка заземлений (9 шт.), подключение (4 шт.), установка подставок под кабель (5 шт.), демонтаж 2‑х лубрикаторных площадок, монтаж 1 защитного колпака | W99: 3.5
N100: ПР | O100: Штатно | Q100: Вспом_работы | R100: Завоз | S100: Объекты_промывка_СО | T100: Тех. вода | V100: Монтаж линии набора воды, набор тех. воды 66,2 м³ (ρ=1,01), обработка ПАВ СНПХ-ПКД 0,03%, отбор пробы | W100: 10
N101: ПР | O101: Штатно | Q101: Контроль_замер | R101: Опрессовка | S101: Объекты_устье | T101: Фонтанная арматура | V101: Опрессовка лифта НКТП на 6 МПа (негерметично), опрессовка обратного клапана ФА на 4 МПа (негерметично). Демонтаж оборудования КИПа, метанольных линий | W101: 1
N102: ПР | O102: Штатно | Q102: Циркуляция | R102: Обратная промывка | S102: Скважина_ствол | T102: Скважина | V102: Глушение скважины обратной промывкой раствором 1,01 г/см³, V=21 м³ (продолжение) | W102: 5
N103: ПР | O103: Штатно | Q103: Циркуляция | R103: Обратная промывка | S103: Скважина_ствол | T103: Скважина | V103: Глушение скважины обратной промывкой раствором 1,01 г/см³, V=35 м³ (общ. 56,2 м³), рост давления до 10 МПа. Технологическая стоянка 3 ч, разрядка с 4 до 0 МПа, выход конденсата+газ | W103: 8
N104: ПР | O104: Штатно | Q104: Монтаж_демонтаж_установка | R104: Монтаж | S104: Оборудование | T104: УПА | V104: Монтаж УПРС-80 (30%), подвоз грунта и отсыпка территории под приёмный мост и 3 стеллажа | W104: 6
N105: ПР | O105: Орг_простой | Q105: Простой | R105: Ожидание | S105: Орг_логист_объекты | T105: Персонал | V105: Приостановка работ в связи с проведением ингибиторной обработки ПЗП на скв.188 кп 3 бис | W105: 5.5
N106: ПР | O106: Штатно | Q106: Монтаж_демонтаж_установка | R106: Монтаж | S106: Оборудование | T106: УПА | V106: Монтаж УПРС-80 (90%), долив скважины V=0,5 м³ (общий долив 3 м³) | W106: 4.5
N107: ПР | O107: Штатно | Q107: ПР | R107: Рабочая комиссия | S107: Орг_логист_объекты | T107: Разрешительная документация | V107: Устранение пунктов, выписанных пусковой комиссией | W107: 8
N108: ПР | O108: Орг_простой | Q108: Простой | R108: Ожидание | S108: Орг_логист_объекты | T108: МТР | V108: Запрет на рубку кабеля, ожидание завоза НКТ-73 (5 шт.), получение разрешения на демонтаж ФА и монтаж ПВО | W108: 10
N109: КРС | O109: Штатно | Q109: Монтаж_демонтаж_установка | R109: Демонтаж | S109: Объекты_устье | T109: Фонтанная арматура | V109: Получение разрешения на демонтаж ФА, монтаж ПВО. Подрыв ПШ (G=43 тн). Демонтаж КВ, протаскивание кабеля, демонтаж ФА | W109: 2.5
N110: КРС | O110: Штатно | Q110: Монтаж_демонтаж_установка | R110: Монтаж | S110: Объекты_устье | T110: ПВО | V110: Монтаж 2 отбойных щитов, штурвалов, подключение СУП, монтаж выносного пульта, монтаж ПВО (100%) | W110: 1.5
... N115: КРС | O115: Штатно | Q115: Циркуляция | R115: Обратная промывка | S115: Скважина_ствол | T115: Скважина | V115: Подготовка к промывке. Обратная промывка скважины раствором 1,01 г/см³ V=37,5 м³, циркуляция (+). Разрядка (+). Подготовка к подъёму ЭЦН | W115: 4
N116: КРС | O116: Штатно | Q116: СПО | R116: Подъем | S116: Технологический_инструмент | T116: УЭЦН | U116: 1 | V116: Подъём ЭЦН с 2859,88 м до 2600 м (20 шт НКТП-73 мм). Долив 3 м³ | W116: 4
N117: КРС | O117: Штатно | Q117: СПО | R117: Подъем | S117: Технологический_инструмент | T117: УЭЦН | U117: 1 | V117: Подъём ЭЦН с 2600 м до 1819 м (106 шт). Долив 2 м³ | W117: 8
N118: КРС | O118: Орг_простой | Q118: Простой | R118: Ожидание | S118: Орг_логист_объекты | T118: Персонал | V118: Остановка работ по неполному составу вахты | W118: 9
N119: КРС | O119: Штатно | Q119: СПО | R119: Подъем | S119: Технологический_инструмент | T119: УЭЦН | U119: 1 | V119: Подъём ЭЦН с 1819 м до 1365 м, ВИК первого ряда. Долив 30 м³ | W119: 7
N120: КРС | O120: Штатно | Q120: СПО | R120: Подъем | S120: Технологический_инструмент | T120: УЭЦН | U120: 1 | V120: Подъём ЭЦН с 1365 м до 672,31 м (устойчивый уровень – «зеркало»), ВИК, опрессовка лифта 6 МПа (+), замер изоляции (отсутствует), сброс спецштанги Ø25 мм L=1,2 м (+). Подъём до 0 м | W120: 20
N121: КРС | O121: Штатно | Q121: Сборка_разборка_оснащение | R121: Разборка | S121: Технологический_инструмент | T121: УЭЦН | V121: Комиссионный демонтаж ЭЦН | W121: 2.5
N122: КРС | O122: Штатно | Q122: Вспом_работы | R122: Подготовка | S122: Технологический_инструмент | T122: УЭЦН | V122: Центровка мачты, разгрузка оборудования ЭЦН, подготовка к опрессовке подклапанных НКТП-73 (6 шт.) | W122: 1.5
N123: КРС | O123: Штатно | Q123: Сборка_разборка_оснащение | R123: Сборка | S123: Технологический_инструмент | T123: УЭЦН | V123: Опрессовка подклапанных НКТ-73 (6 шт.) на 25 МПа (+). Монтаж дополнительного оборудования + ЭЦН (ЭЦНМТ5-80/2260/8ЭДРТ-56-117) | W123: 6
N124: КРС | O124: Орг_простой | Q124: Простой | R124: Ожидание | S124: Орг_логист_объекты | T124: МТР | V124: Ожидание завоза клямсевателя | W124: 3.5
N125: КРС | O125: Штатно | Q125: СПО | R125: Спуск | S125: Технологический_инструмент | T125: УЭЦН | U125: 1 | V125: Спуск ЭЦН до глубины 877,66 м (92 шт НКТП-73 мм). Долив 38,3 м³ | W125: 14.5
N126: КРС | O126: Штатно | Q126: СПО | R126: Спуск | S126: Технологический_инструмент | T126: УЭЦН | U126: 1 | V126: Спуск ЭЦН до 1532,37 м (всего 160 шт). Опрессовка лифта через 600 м (6 МПа). Долив 40 м³ | W126: 8
N127: КРС | O127: Орг_простой | Q127: Простой | R127: Ожидание | S127: Орг_логист_объекты | T127: Персонал | V127: Перевахтовка, оформление и получение наряда-допуска. Долив 55 м³ | W127: 12
N128: КРС | O128: Штатно | Q128: СПО | R128: Спуск | S128: Технологический_инструмент | T128: УЭЦН | U128: 1 | V128: Спуск ЭЦН до 1933,38 м (всего 202 шт). Долив 59 м³ | W128: 4
N129: КРС | O129: Штатно | Q129: СПО | R129: Спуск | S129: Технологический_инструмент | T129: УЭЦН | U129: 1 | V129: Спуск ЭЦН до 2226 м (всего 232 шт). Долив 62 м³ | W129: 3
N130: КРС | O130: Штатно | Q130: Ремонт | R130: Ремонт | S130: Оборудование | T130: УПА | V130: Ремонт УБРСП-80 (замена ремня компрессора) | W130: 1.5
N131: КРС | O131: Штатно | Q131: СПО | R131: Спуск | S131: Технологический_инструмент | T131: УЭЦН | U131: 1 | V131: Спуск ЭЦН до 2859,73 м (всего 296 шт). Установка стоп-кольца Ø35 мм на 203-й трубе (гл. 799,3 м). Замер изоляции через 300 м (200 МОм), опрессовка лифта через 600 м (6 МПа). Долив 68 м³ | W131: 5.5
N132: Заканчивание | O132: Штатно | Q132: Монтаж_демонтаж_установка | R132: Перемонтаж | S132: Объекты_устье | T132: Фонтанная арматура | V132: Демонтаж ГКШ-1500, СУ-80, отбойных щитов и штурвалов, линии долива, демонтаж ПВО с протаскиванием кабеля (≈35 м). Монтаж ФА и кабельного ввода, опрессовка КВ на 11 МПа (герметично). Монтаж обвязки ФА, укладка кабеля (≈35 м). Контрольный замер изоляции | W132: 6
N133: ДПМ | O133: Штатно | Q133: Монтаж_демонтаж_установка | R133: Демонтаж | S133: Оборудование | T133: УПА | V133: Демонтаж РП, ИВЭ-50 | W133: 1.5
N134: Заканчивание | O134: Штатно | Q134: Контроль_замер | R134: Опрессовка | S134: Объекты_устье | T134: Фонтанная арматура | V134: Опрессовка ОК ФА и обвязки на 4 МПа (герметично), опрессовка лифта НКТП на 6 МПа (герметично) | W134: 1
N135: Заканчивание | O135: Штатно | Q135: Испытания | R135: Запуск в работу | S135: Технологический_инструмент | T135: УЭЦН | V135: Замер изоляции перед запуском (200 МОм). Запуск ЭЦНМТ5-80/2260/8ЭДРТ-56-117. Iпуск=19,8А, Iраб=18,2А, частота 40 Гц, загрузка 41%, Рпр=181 атм, Tпр=75°С, дебит 115 м³/сут | W135: 0.5
N136: ДПМ | O136: Штатно | Q136: Монтаж_демонтаж_установка | R136: Демонтаж | S136: Оборудование | T136: УПА | V136: Демонтаж УБРСП-80, пригрузов, якорей, приёмного моста, 3 стеллажей. Монтаж дублирующей ЗД №2, опрессовка фланцевого соединения | W136: 3
N137: ДПМ | O137: Штатно | Q137: Монтаж_демонтаж_установка | R137: Демонтаж | S137: Оборудование | T137: БО | V137: Демонтаж 1 защитного колпака, монтаж 2 лубрикаторных площадок | W137: 2
...

Sheet 0. Лист для печати
E3: Суточный отчет по бурению № | I3: ='2. Для заполнения'!F1 -> 2 | P3: Дата: | Q3: ='2. Для заполнения'!I1 -> 46202
A5: 1. Данные по скважине | J5: 2. Подробная сводка
A6: Месторождение: | C6: ='2. Для заполнения'!D5 -> Казанское | E6: Составил: | F6: ='2. Для заполнения'!G5 -> Воронков Вадим Анатольевич | J6: ="Работы, проводимые в период с 00:00 до 24:00 " & TEXT(Q3-1, "ДД.ММ.ГГГГ") -> Работы, проводимые в период с 00:00 до 24:00 28.06.2026
A7: Куст: | C7: ='2. Для заполнения'!D6 -> 26 | E7: Почта: | F7: ='2. Для заполнения'!G6 -> kazanskoe.project@pobeditholding.com | J7: № п/п | K7: Забой, м | L7: Начало | M7: Конец | N7: Время, ч | O7: Фактические работы
A8: Скважина №: | C8: ='2. Для заполнения'!D7 -> 330 | E8: ОК | F8: Проект, м | G8: Факт, м | H8: Цементаж | J8: =IF('2. Для заполнения'!B36<>" ", '2. Для заполнения'!H36, " ") | K8: ='2. Для заполнения'!B36 | L8: ='2. Для заполнения'!C36 | M8: ='2. Для заполнения'!D36 | N8: ='2. Для заполнения'!E36 | O8: ='2. Для заполнения'!F36
A9: Назначение: | C9: ='2. Для заполнения'!D8 -> Добывающая | E9: 324 | F9: ='2. Для заполнения'!G9 -> 50 | G9: ='2. Для заполнения'!H9 -> 0 | H9: ='2. Для заполнения'!I9
A10: Заказчик: | C10: ='2. Для заполнения'!D9 -> ООО "Газпром Добыча Томск" | E10: 245 | F10: ='2. Для заполнения'!G10 -> 1150.51 | G10: ='2. Для заполнения'!H10 -> 0 | H10: ='2. Для заполнения'!I10 | J10: =IF('2. Для заполнения'!B37<>" ", '2. Для заполнения'!H37, " ") | K10: ='2. Для заполнения'!B37 | L10: ='2. Для заполнения'!C37 | M10: ='2. Для заполнения'!D37 | N10: ='2. Для заполнения'!E37 | O10: ='2. Для заполнения'!F37
A11: Тип БУ: | C11: ='2. Для заполнения'!D10 -> МБУ ZJ-30 | E11: 146 | F11: ='2. Для заполнения'!G11 -> 2491 | G11: ='2. Для заполнения'!H11 -> 0 | H11: ='2. Для заполнения'!I11
A12: Начало бурения: | C12: ='2. Для заполнения'!D14 -> 46145.099 | E12: 102 | F12: ='2. Для заполнения'!G12 -> 3591 | G12: ='2. Для заполнения'!H12 -> 0 | H12: ='2. Для заполнения'!I12 | J12: =IF('2. Для заполнения'!B38<>" ", '2. Для заполнения'!H38, " ") | K12: ='2. Для заполнения'!B38 | L12: ='2. Для заполнения'!C38 | M12: ='2. Для заполнения'!D38 | N12: ='2. Для заполнения'!E38 | O12: ='2. Для заполнения'!F38
A13: Длительность по плану: | C13: ='2. Для заполнения'!D15 -> 7.49625 | D13: Проектная глубина по стволу, м: | G13: ='2. Для заполнения'!G14 -> 3591
A14: Фактически дней: | C14: ='2. Для заполнения'!D16 -> 50.666667 | D14: Проектная глубина (верт), м: | G14: ='2. Для заполнения'!G15 -> 2475 | J14: =IF('2. Для заполнения'!B39<>" ", '2. Для заполнения'!H39, " ") | K14: ='2. Для заполнения'!B39 | L14: ='2. Для заполнения'!C39 | M14: ='2. Для заполнения'!D39 | N14: ='2. Для заполнения'!E39 | O14: ='2. Для заполнения'!F39
A15: Отставание от ГГД: | C15: ='2. Для заполнения'!D17 -> #REF! | D15: Кровля пласта (верт), м: | G15: ='2. Для заполнения'!G16 -> 2469.3
A16: Диаметр ствола: | C16: ='2. Для заполнения'!D19 -> 126 | D16: Тип профиля: | G16: ='2. Для заполнения'!G17 -> Наклонно-направленный | J16: =IF('2. Для заполнения'!B40<>" ", '2. Для заполнения'!H40, " ") | K16: ='2. Для заполнения'!B40 | L16: ='2. Для заполнения'!C40 | M16: ='2. Для заполнения'!D40 | N16: ='2. Для заполнения'!E40 | O16: ='2. Для заполнения'!F40
A17: MD, м: | C17: ='2. Для заполнения'!D20 -> 3538 | D17: Макс. зенитный угол, град: | G17: ='2. Для заполнения'!G18 -> 88,98
A18: TVD, м: | C18: ='2. Для заполнения'!D21 -> 2476.26 | D18: Макс. интенсивность, град/10м: | G18: ='2. Для заполнения'!G19 -> 1,5 | J18: =IF('2. Для заполнения'!B41<>" ", '2. Для заполнения'!H41, " ") | K18: ='2. Для заполнения'!B41 | L18: ='2. Для заполнения'!C41 | M18: ='2. Для заполнения'!D41 | N18: ='2. Для заполнения'!E41 | O18: ='2. Для заполнения'!F41
A19: Суточная проходка: | C19: ='2. Для заполнения'!D22 -> 128 | D19: Смещение от устья, м: | G19: ='2. Для заполнения'!G20 -> 2241.61
A20: Суммарная проходка: | C20: =SUM(Хронология[Проходка, м]) -> 2758.16 | D20: Температура воздуха, °С: | G20: ='2. Для заполнения'!G24 -> -27 | J20: =IF('2. Для заполнения'!B42<>" ", '2. Для заполнения'!H42, " ") | K20: ='2. Для заполнения'!B42 | L20: ='2. Для заполнения'!C42 | M20: ='2. Для заполнения'!D42 | N20: ='2. Для заполнения'!E42 | O20: ='2. Для заполнения'!F42
D21: ПВО испытано (Дата/Давление): | G21: ='2. Для заполнения'!G25 -> 06.02.26г / 35 МПа
D22: ПВО: | G22: ='2. Для заполнения'!G26 -> ОП-5 230х35 | J22: =IF('2. Для заполнения'!B43<>" ", '2. Для заполнения'!H43, " ") | K22: ='2. Для заполнения'!B43 | L22: ='2. Для заполнения'!C43 | M22: ='2. Для заполнения'!D43 | N22: ='2. Для заполнения'!E43 | O22: ='2. Для заполнения'!F43
D23: Наработка тал.каната, т/км: | G23: ='2. Для заполнения'!G27 -> 264,7\264,7
A24: Генеральный подрядчик: | C24: ='2. Для заполнения'!D24 -> ООО "Победит Холдинг" | E24: Долота: | G24: ='2. Для заполнения'!D28 -> ООО "Интер-Сервис" | J24: =IF('2. Для заполнения'!B44<>" ", '2. Для заполнения'!H44, " ") | K24: ='2. Для заполнения'!B44 | L24: ='2. Для заполнения'!C44 | M24: ='2. Для заполнения'!D44 | N24: ='2. Для заполнения'!E44 | O24: ='2. Для заполнения'!F44
A25: Подрядчик по бурению: | C25: ='2. Для заполнения'!D25 -> ООО "Победит Холдинг" | E25: Спуск ОК: | G25: ='2. Для заполнения'!D29 -> ООО "Нефтесервисная компания" "Буран"
A26: Растворы: | C26: ='2. Для заполнения'!D26 -> ООО "НСК Эшелон" | E26: ГИС и ГТК: | G26: ='2. Для заполнения'!D30 -> ПФ «Востокгазгеофизика» | J26: =IF('2. Для заполнения'!B45<>" ", '2. Для заполнения'!H45, " ") | K26: ='2. Для заполнения'!B45 | L26: ='2. Для заполнения'!C45 | M26: ='2. Для заполнения'!D45 | N26: ='2. Для заполнения'!E45 | O26: ='2. Для заполнения'!F45
A27: ННБ: | C27: ='2. Для заполнения'!D27 -> ООО "Интер-Сервис" | E27: Цементирование: | G27: ='2. Для заполнения'!D31 -> ООО "ЦЦС"
J28: =IF('2. Для заполнения'!B46<>" ", '2. Для заполнения'!H46, " ") | K28: ='2. Для заполнения'!B46 | L28: ='2. Для заполнения'!C46 | M28: ='2. Для заполнения'!D46 | N28: ='2. Для заполнения'!E46 | O28: ='2. Для заполнения'!F46
A29: 3. Данные по КНБК (последняя СПО)
A30: Оборудование | B30: Наружный Ø,мм | C30: Внутр. Ø,мм | D30: Длина, м | E30: Σ Длина,м | F30: Серийный номер | G30: Тип и размер соединения | H30: Примечание | J30: =IF('2. Для заполнения'!B47<>" ", '2. Для заполнения'!H47, " ") | K30: ='2. Для заполнения'!B47 | L30: ='2. Для заполнения'!C47 | M30: ='2. Для заполнения'!D47 | N30: ='2. Для заполнения'!E47 | O30: ='2. Для заполнения'!F47
A32: =IF('2. Для заполнения'!B71=0, " ", '2. Для заполнения'!B71) -> PDC TD-126,0 SVD 513-T1 S233 (4х7,9мм; 2х8,2мм) Технодрил | B32: =IF('2. Для заполнения'!D71=0, " ", '2. Для заполнения'!D71) -> 126 | C32: =IF('2. Для заполнения'!E71=0, " ", '2. Для заполнения'!E71) -> 4х7,9мм; 2х8,2мм | D32: =IF('2. Для заполнения'!F71=0, " ", '2. Для заполнения'!F71) -> 0.18 | E32: =IF('2. Для заполнения'!G71=0, " ", '2. Для заполнения'!G71) -> 0.18 | F32: =IF('2. Для заполнения'!H71=0, " ", '2. Для заполнения'!H71) -> 190425 | G32: =IF('2. Для заполнения'!I71=0, " ", '2. Для заполнения'!I71) -> Нз76 | J32: =IF('2. Для заполнения'!B48<>" ", '2. Для заполнения'!H48, " ") | K32: ='2. Для заполнения'!B48 | L32: ='2. Для заполнения'!C48 | M32: ='2. Для заполнения'!D48 | N32: ='2. Для заполнения'!E48 | O32: ='2. Для заполнения'!F48
A33: =IF('2. Для заполнения'!B72=0, " ", '2. Для заполнения'!B72) -> ДВ 106.7.531-Р 7/8 +КОБ (1º51´) ООО "СОКОL" | B33: =IF('2. Для заполнения'!D72=0, " ", '2. Для заполнения'!D72) -> 108 | C33: =IF('2. Для заполнения'!E72=0, " ", '2. Для заполнения'!E72) -> .- | D33: =IF('2. Для заполнения'!F72=0, " ", '2. Для заполнения'!F72) -> 7.61 | E33: =IF('2. Для заполнения'!G72=0, " ", '2. Для заполнения'!G72) -> 7.79 | F33: =IF('2. Для заполнения'!H72=0, " ", '2. Для заполнения'!H72) -> 4249 | G33: =IF('2. Для заполнения'!I72=0, " ", '2. Для заполнения'!I72) -> Мз 86 х Мз 76
A34: =IF('2. Для заполнения'!B73=0, " ", '2. Для заполнения'!B73) -> Переводник Мз 73 х Нз 86 | B34: =IF('2. Для заполнения'!D73=0, " ", '2. Для заполнения'!D73) -> 108 | C34: =IF('2. Для заполнения'!E73=0, " ", '2. Для заполнения'!E73) -> 45 | D34: =IF('2. Для заполнения'!F73=0, " ", '2. Для заполнения'!F73) -> 0.18 | E34: =IF('2. Для заполнения'!G73=0, " ", '2. Для заполнения'!G73) -> 7.97 | F34: =IF('2. Для заполнения'!H73=0, " ", '2. Для заполнения'!H73) -> 67 | G34: =IF('2. Для заполнения'!I73=0, " ", '2. Для заполнения'!I73) -> Мз 73 х Нз 86 | J34: =IF('2. Для заполнения'!B49<>" ", '2. Для заполнения'!H49, " ") | K34: ='2. Для заполнения'!B49 | L34: ='2. Для заполнения'!C49 | M34: ='2. Для заполнения'!D49 | N34: ='2. Для заполнения'!E49 | O34: ='2. Для заполнения'!F49
A35: =IF('2. Для заполнения'!B74=0, " ", '2. Для заполнения'!B74) -> Резистивиметр (пульсатор №723, батареи 1,2,3№1541;1638;1551,ТМС верхняя №129, ТМС нижняя №191, гамма №544, инклинометр №852) | B35: =IF('2. Для заполнения'!D74=0, " ", '2. Для заполнения'!D74) -> 95.2 | C35: =IF('2. Для заполнения'!E74=0, " ", '2. Для заполнения'!E74) -> 31 | D35: =IF('2. Для заполнения'!F74=0, " ", '2. Для заполнения'!F74) -> 9.45 | E35: =IF('2. Для заполнения'!G74=0, " ", '2. Для заполнения'!G74) -> 17.42 | F35: =IF('2. Для заполнения'!H74=0, " ", '2. Для заполнения'!H74) -> 537 | G35: =IF('2. Для заполнения'!I74=0, " ", '2. Для заполнения'!I74) -> Мз 80 х Нз 73
A36: =IF('2. Для заполнения'!B75=0, " ", '2. Для заполнения'!B75) -> УБТН-95 | B36: =IF('2. Для заполнения'!D75=0, " ", '2. Для заполнения'!D75) -> 95 | C36: =IF('2. Для заполнения'!E75=0, " ", '2. Для заполнения'!E75) -> 55.8 | D36: =IF('2. Для заполнения'!F75=0, " ", '2. Для заполнения'!F75) -> 9.25 | E36: =IF('2. Для заполнения'!G75=0, " ", '2. Для заполнения'!G75) -> 26.67 | F36: =IF('2. Для заполнения'!H75=0, " ", '2. Для заполнения'!H75) -> 80362/36598-2 | G36: =IF('2. Для заполнения'!I75=0, " ", '2. Для заполнения'!I75) -> Мз 80 х Нз 80
A37: =IF('2. Для заполнения'!B76=0, " ", '2. Для заполнения'!B76) -> Переводник Мз 86 х Нз 80 | B37: =IF('2. Для заполнения'!D76=0, " ", '2. Для заполнения'!D76) -> 106 | C37: =IF('2. Для заполнения'!E76=0, " ", '2. Для заполнения'!E76) -> 57.6 | D37: =IF('2. Для заполнения'!F76=0, " ", '2. Для заполнения'!F76) -> 0.46 | E37: =IF('2. Для заполнения'!G76=0, " ", '2. Для заполнения'!G76) -> 27.13 | F37: =IF('2. Для заполнения'!H76=0, " ", '2. Для заполнения'!H76) -> 12025*30 | G37: =IF('2. Для заполнения'!I76=0, " ", '2. Для заполнения'!I76) -> Мз 86 х Нз 80 | J37: ="Работы, проводимые в период с 00:00 до 8:00" & " " & TEXT(Q3, "ДД.ММ.ГГГГ") -> Работы, проводимые в период с 00:00 до 8:00 29.06.2026
A38: =IF('2. Для заполнения'!B77=0, " ", '2. Для заполнения'!B77) -> Ф106-С4 | B38: =IF('2. Для заполнения'!D77=0, " ", '2. Для заполнения'!D77) -> 106 | C38: =IF('2. Для заполнения'!E77=0, " ", '2. Для заполнения'!E77) -> .- | D38: =IF('2. Для заполнения'!F77=0, " ", '2. Для заполнения'!F77) -> 0.51 | E38: =IF('2. Для заполнения'!G77=0, " ", '2. Для заполнения'!G77) -> 27.64 | F38: =IF('2. Для заполнения'!H77=0, " ", '2. Для заполнения'!H77) -> 277 | G38: =IF('2. Для заполнения'!I77=0, " ", '2. Для заполнения'!I77) -> Мз 86 х Нз 86 | J38: Начало | K38: Конец | L38: Время, ч | M38: Забой, м | N38: Фактические работы
A39: =IF('2. Для заполнения'!B78=0, " ", '2. Для заполнения'!B78) -> СБТ-88,9х9,35мм (43 свечи) | B39: =IF('2. Для заполнения'!D78=0, " ", '2. Для заполнения'!D78) -> 88.9 | C39: =IF('2. Для заполнения'!E78=0, " ", '2. Для заполнения'!E78) -> 50.8 | D39: =IF('2. Для заполнения'!F78=0, " ", '2. Для заполнения'!F78) -> 788.46 | E39: =IF('2. Для заполнения'!G78=0, " ", '2. Для заполнения'!G78) -> 816.1 | F39: =IF('2. Для заполнения'!H78=0, " ", '2. Для заполнения'!H78) -> 4 | G39: =IF('2. Для заполнения'!I78=0, " ", '2. Для заполнения'!I78) -> Мз 86 х Нз 86 | J39: =IF('2. Для заполнения'!C58="", " ", '2. Для заполнения'!C58) | K39: =IF('2. Для заполнения'!D58="", " ", '2. Для заполнения'!D58) | L39: =IF('2. Для заполнения'!E58="", " ", '2. Для заполнения'!E58) | M39: =IF('2. Для заполнения'!B58=0, " ", '2. Для заполнения'!B58) | N39: =IF('2. Для заполнения'!F58=0, " ", '2. Для заполнения'!F58)
A40: =IF('2. Для заполнения'!B79=0, " ", '2. Для заполнения'!B79) -> ТБТ-К1-108-89-51 (3 свечи) | B40: =IF('2. Для заполнения'!D79=0, " ", '2. Для заполнения'!D79) -> 88.9 | C40: =IF('2. Для заполнения'!E79=0, " ", '2. Для заполнения'!E79) -> 53 | D40: =IF('2. Для заполнения'!F79=0, " ", '2. Для заполнения'!F79) -> 55.18 | E40: =IF('2. Для заполнения'!G79=0, " ", '2. Для заполнения'!G79) -> 871.28 | F40: =IF('2. Для заполнения'!H79=0, " ", '2. Для заполнения'!H79) -> 19 | G40: =IF('2. Для заполнения'!I79=0, " ", '2. Для заполнения'!I79) -> Мз 86 х Нз 86 | J40: =IF('2. Для заполнения'!C59="", " ", '2. Для заполнения'!C59) | K40: =IF('2. Для заполнения'!D59="", " ", '2. Для заполнения'!D59) | L40: =IF('2. Для заполнения'!E59="", " ", '2. Для заполнения'!E59) | M40: =IF('2. Для заполнения'!B59=0, " ", '2. Для заполнения'!B59) | N40: =IF('2. Для заполнения'!F59=0, " ", '2. Для заполнения'!F59)
A41: =IF('2. Для заполнения'!B80=0, " ", '2. Для заполнения'!B80) -> ЯС-106 ГМ | B41: =IF('2. Для заполнения'!D80=0, " ", '2. Для заполнения'!D80) -> 108 | C41: =IF('2. Для заполнения'!E80=0, " ", '2. Для заполнения'!E80) -> 50.8 | D41: =IF('2. Для заполнения'!F80=0, " ", '2. Для заполнения'!F80) -> 5.74 | E41: =IF('2. Для заполнения'!F80=0, " ", '2. Для заполнения'!F80) -> 5.74 | F41: =IF('2. Для заполнения'!H80=0, " ", '2. Для заполнения'!H80) -> 146 | G41: =IF('2. Для заполнения'!I80=0, " ", '2. Для заполнения'!I80) -> Мз 86 х Нз 86 | J41: =IF('2. Для заполнения'!C60="", " ", '2. Для заполнения'!C60) | K41: =IF('2. Для заполнения'!D60="", " ", '2. Для заполнения'!D60) | L41: =IF('2. Для заполнения'!E60="", " ", '2. Для заполнения'!E60) | M41: =IF('2. Для заполнения'!B60=0, " ", '2. Для заполнения'!B60) | N41: =IF('2. Для заполнения'!F60=0, " ", '2. Для заполнения'!F60)
A42: =IF('2. Для заполнения'!B81=0, " ", '2. Для заполнения'!B81) -> ТБТ-К1-108-89-51 (3 свечи) | B42: =IF('2. Для заполнения'!C81=0, " ", '2. Для заполнения'!C81) | C42: =IF('2. Для заполнения'!D81=0, " ", '2. Для заполнения'!D81) -> 88.9 | D42: =IF('2. Для заполнения'!E81=0, " ", '2. Для заполнения'!E81) -> 53 | E42: =IF('2. Для заполнения'!F81=0, " ", '2. Для заполнения'!F81) -> 55.28 | F42: =IF('2. Для заполнения'!G81=0, " ", '2. Для заполнения'!G81) -> 932.3 | G42: =IF('2. Для заполнения'!H81=0, " ", '2. Для заполнения'!H81) -> 19 | H42: =IF('2. Для заполнения'!I81=0, " ", '2. Для заполнения'!I81) -> Мз 86 х Нз 86
A43: =IF('2. Для заполнения'!B82=0, " ", '2. Для заполнения'!B82) -> СБТ-88,9х9,35мм (ост) | B43: =IF('2. Для заполнения'!C82=0, " ", '2. Для заполнения'!C82) | C43: =IF('2. Для заполнения'!D82=0, " ", '2. Для заполнения'!D82) -> 88.9 | D43: =IF('2. Для заполнения'!E82=0, " ", '2. Для заполнения'!E82) -> 50.8 | E43: =IF('2. Для заполнения'!F82=0, " ", '2. Для заполнения'!F82) -> 2658.7 | F43: =IF('2. Для заполнения'!G82=0, " ", '2. Для заполнения'!G82) -> 3591 | G43: =IF('2. Для заполнения'!H82=0, " ", '2. Для заполнения'!H82) -> 4 | H43: =IF('2. Для заполнения'!I82=0, " ", '2. Для заполнения'!I82) -> Мз 86 х Нз 86 | J43: 4. Заявки
A44: =IF('2. Для заполнения'!B83=0, " ", '2. Для заполнения'!B83) | B44: =IF('2. Для заполнения'!C83=0, " ", '2. Для заполнения'!C83) | C44: =IF('2. Для заполнения'!D83=0, " ", '2. Для заполнения'!D83) | D44: =IF('2. Для заполнения'!E83=0, " ", '2. Для заполнения'!E83) | E44: =IF('2. Для заполнения'!F83=0, " ", '2. Для заполнения'!F83) | F44: =IF('2. Для заполнения'!G83=0, " ", '2. Для заполнения'!G83) | G44: =IF('2. Для заполнения'!H83=0, " ", '2. Для заполнения'!H83) | H44: =IF('2. Для заполнения'!I83=0, " ", '2. Для заполнения'!I83) | J44: № п/п | K44: Потребность | P44: Кол-во | Q44: Примечание
A45: =IF('2. Для заполнения'!B84=0, " ", '2. Для заполнения'!B84) | B45: =IF('2. Для заполнения'!C84=0, " ", '2. Для заполнения'!C84) | C45: =IF('2. Для заполнения'!D84=0, " ", '2. Для заполнения'!D84) | D45: =IF('2. Для заполнения'!E84=0, " ", '2. Для заполнения'!E84) | E45: =IF('2. Для заполнения'!F84=0, " ", '2. Для заполнения'!F84) | F45: =IF('2. Для заполнения'!G84=0, " ", '2. Для заполнения'!G84) | G45: =IF('2. Для заполнения'!H84=0, " ", '2. Для заполнения'!H84) | H45: =IF('2. Для заполнения'!I84=0, " ", '2. Для заполнения'!I84) | J45: ='2. Для заполнения'!B100 -> 1 | K45: =IF('2. Для заполнения'!C100="", " ", '2. Для заполнения'!C100) | P45: =IF('2. Для заполнения'!H100="", " ", '2. Для заполнения'!H100) | Q45: =IF('2. Для заполнения'!I100="", " ", '2. Для заполнения'!I100)
J46: ='2. Для заполнения'!B101 | K46: =IF('2. Для заполнения'!C101="", " ", '2. Для заполнения'!C101) | P46: =IF('2. Для заполнения'!H101="", " ", '2. Для заполнения'!H101) | Q46: =IF('2. Для заполнения'!I101="", " ", '2. Для заполнения'!I101)
A47: 5. Параметры долот | E47: 6. Буровой раствор | J47: ='2. Для заполнения'!B102 | K47: =IF('2. Для заполнения'!C102="", " ", '2. Для заполнения'!C102) | P47: =IF('2. Для заполнения'!H102="", " ", '2. Для заполнения'!H102) | Q47: =IF('2. Для заполнения'!I102="", " ", '2. Для заполнения'!I102)
A48: № рейса: | C48: =IF('2. Для заполнения'!D117<>0, '2. Для заполнения'!D117, " ") -> 4 | D48: Общ. проходка, м: | E48: Параметр | G48: План | H48: Факт | J48: ='2. Для заполнения'!B103 | K48: =IF('2. Для заполнения'!C103="", " ", '2. Для заполнения'!C103) | P48: =IF('2. Для заполнения'!H103="", " ", '2. Для заполнения'!H103) | Q48: =IF('2. Для заполнения'!I103="", " ", '2. Для заполнения'!I103)
A49: Диаметр, мм: | C49: =IF('2. Для заполнения'!D118<>0, '2. Для заполнения'!D118, " ") -> 126 | E49: Тип | G49: =IF('2. Для заполнения'!D137<>0, '2. Для заполнения'!D137, " ") -> Ингибирующий хлоркалиевый | H49: =IF('2. Для заполнения'!E137<>0, '2. Для заполнения'!E137, " ") -> Ингибирующий хлоркалиевый | J49: ='2. Для заполнения'!B104 | K49: =IF('2. Для заполнения'!C104="", " ", '2. Для заполнения'!C104) | P49: =IF('2. Для заполнения'!H104="", " ", '2. Для заполнения'!H104) | Q49: =IF('2. Для заполнения'!I104="", " ", '2. Для заполнения'!I104)
A50: Модель: | C50: =IF('2. Для заполнения'!D119<>0, '2. Для заполнения'!D119, " ") -> PDC TD-126,0 SVD 513-T1 S233 Технодрил | D50: ='2. Для заполнения'!G121 -> 1042 | E50: Плотность, г/см3 | G50: =IF('2. Для заполнения'!D138<>0, '2. Для заполнения'!D138, " ") -> 1.12 | H50: =IF('2. Для заполнения'!E138<>0, '2. Для заполнения'!E138, " ") -> 1.11 | J50: ='2. Для заполнения'!B105 | K50: =IF('2. Для заполнения'!C105="", " ", '2. Для заполнения'!C105) | P50: =IF('2. Для заполнения'!H105="", " ", '2. Для заполнения'!H105) | Q50: =IF('2. Для заполнения'!I105="", " ", '2. Для заполнения'!I105)
A51: № долота: | C51: =IF('2. Для заполнения'!D120<>0, '2. Для заполнения'!D120, " ") -> 190425 | E51: Усл.вязкость, сек | G51: =IF('2. Для заполнения'!D139<>0, '2. Для заполнения'!D139, " ") -> 30-60 | H51: =IF('2. Для заполнения'!E139<>0, '2. Для заполнения'!E139, " ") -> 42 | J51: ='2. Для заполнения'!B106 | K51: =IF('2. Для заполнения'!C106="", " ", '2. Для заполнения'!C106) | P51: =IF('2. Для заполнения'!H106="", " ", '2. Для заполнения'!H106) | Q51: =IF('2. Для заполнения'!I106="", " ", '2. Для заполнения'!I106)
A52: Обороты, об/мин: | C52: =IF('2. Для заполнения'!D121<>0, '2. Для заполнения'!D121, " ") -> до 300 | D52: Т бур.(общ.), час: | E52: Вязкость пласт., сПз | G52: =IF('2. Для заполнения'!D140<>0, '2. Для заполнения'!D140, " ") -> 10-20 | H52: =IF('2. Для заполнения'!E140<>0, '2. Для заполнения'!E140, " ") -> 11 | J52: ='2. Для заполнения'!B107 | K52: =IF('2. Для заполнения'!C107="", " ", '2. Для заполнения'!C107) | P52: =IF('2. Для заполнения'!H107="", " ", '2. Для заполнения'!H107) | Q52: =IF('2. Для заполнения'!I107="", " ", '2. Для заполнения'!I107)
A53: Нагрузка, т: | C53: =IF('2. Для заполнения'!D122<>0, '2. Для заполнения'!D122, " ") -> до 10 | E53: ДНС, мг/см2 | G53: =IF('2. Для заполнения'!D141<>0, '2. Для заполнения'!D141, " ") -> 15-25 | H53: =IF('2. Для заполнения'!E141<>0, '2. Для заполнения'!E141, " ") -> 19 | J53: ='2. Для заполнения'!B108 | K53: =IF('2. Для заполнения'!C108="", " ", '2. Для заполнения'!C108) | P53: =IF('2. Для заполнения'!H108="", " ", '2. Для заполнения'!H108) | Q53: =IF('2. Для заполнения'!I108="", " ", '2. Для заполнения'!I108)
A54: Насадки, мм: | C54: =IF('2. Для заполнения'!D123<>0, '2. Для заполнения'!D123, " ") -> 4х7,9мм; 2х8,2мм | D54: ='2. Для заполнения'!G124 -> 16.4 | E54: СНС, мг/см2 | G54: =IF('2. Для заполнения'!D142<>0, '2. Для заполнения'!D142, " ") -> 6-15/8-20 | H54: =IF('2. Для заполнения'!E142<>0, '2. Для заполнения'!E142, " ") -> 7/12 | J54: ='2. Для заполнения'!B109 | K54: =IF('2. Для заполнения'!C109="", " ", '2. Для заполнения'!C109) | P54: =IF('2. Для заполнения'!H109="", " ", '2. Для заполнения'!H109) | Q54: =IF('2. Для заполнения'!I109="", " ", '2. Для заполнения'!I109)
A55: Интервал, м | B55: От: | C55: =IF('2. Для заполнения'!D124<>0, '2. Для заполнения'!D124, " ") -> 2496 | E55: Толщина корки, % | G55: =IF('2. Для заполнения'!D143<>0, '2. Для заполнения'!D143, " ") -> <0,5/ не менее 3 | H55: =IF('2. Для заполнения'!E143<>0, '2. Для заполнения'!E143, " ") -> 0,2/4
B56: До: | C56: =IF('2. Для заполнения'!D125<>0, '2. Для заполнения'!D125, " ") -> 3538 | D56: Т цирк.(общ.), час: | E56: Песок, % | G56: =IF('2. Для заполнения'!D144<>0, '2. Для заполнения'!D144, " ") -> <0,5 | H56: =IF('2. Для заполнения'!E144<>0, '2. Для заполнения'!E144, " ") -> 0,1 | J56: 8. Инклинометрия
A57: Проходка (сут), м: | C57: =IF('2. Для заполнения'!D126<>0, '2. Для заполнения'!D126, " ") -> 128 | E57: Содержание хлоридов | G57: =IF('2. Для заполнения'!D145<>0, '2. Для заполнения'!D145, " ") -> 20000-30000 | H57: =IF('2. Для заполнения'!E145<>0, '2. Для заполнения'!E145, " ") -> 25000 | J57: План
A58: T бурения, час: | C58: =IF('2. Для заполнения'!D127<>0, '2. Для заполнения'!D127, " ") -> 8.82 | D58: ='2. Для заполнения'!G127 -> 59.63 | E58: Фильтрация см3/30 мин | G58: =IF('2. Для заполнения'!D146<>0, '2. Для заполнения'!D146, " ") -> 4-6 | H58: =IF('2. Для заполнения'!E146<>0, '2. Для заполнения'!E146, " ") -> 5,4 | J58: Параметр | L58: Зачение
A59: Мех. cкорость, м/час: | C59: =IF('2. Для заполнения'!D128<>0, '2. Для заполнения'!D128, " ") -> 14.512472 | E59: рН | G59: =IF('2. Для заполнения'!D147<>0, '2. Для заполнения'!D147, " ") -> 9-10 | H59: =IF('2. Для заполнения'!E147<>0, '2. Для заполнения'!E147, " ") -> 9 | J59: MD, глубина (ствол), м: | L59: =IF('2. Для заполнения'!D178<>0, '2. Для заполнения'!D178, " ") | M59: =IF('2. Для заполнения'!E178<>0, '2. Для заполнения'!E178, " ") | N59: =IF('2. Для заполнения'!F178<>0, '2. Для заполнения'!F178, " ") -> 3538 | O59: =IF('2. Для заполнения'!G178<>0, '2. Для заполнения'!G178, " ") | P59: =IF('2. Для заполнения'!H178<>0, '2. Для заполнения'!H178, " ") | Q59: =IF('2. Для заполнения'!I178<>0, '2. Для заполнения'!I178, " ")
A60: Проходка на долото за рейс, м: | C60: =IF('2. Для заполнения'!D129<>0, '2. Для заполнения'!D129, " ") -> 1042 | D60: Отработка долота (AНИ): | E60: МВТ | G60: =IF('2. Для заполнения'!D148<>0, '2. Для заполнения'!D148, " ") -> <25 | H60: =IF('2. Для заполнения'!E148<>0, '2. Для заполнения'!E148, " ") -> 14,25 | J60: Зенитный угол, град: | L60: =IF('2. Для заполнения'!D179<>0, '2. Для заполнения'!D179, " ") | M60: =IF('2. Для заполнения'!E179<>0, '2. Для заполнения'!E179, " ") | N60: =IF('2. Для заполнения'!F179<>0, '2. Для заполнения'!F179, " ") -> 90.19 | O60: =IF('2. Для заполнения'!G179<>0, '2. Для заполнения'!G179, " ") | P60: =IF('2. Для заполнения'!H179<>0, '2. Для заполнения'!H179, " ") | Q60: =IF('2. Для заполнения'!I179<>0, '2. Для заполнения'!I179, " ")
A61: T бур. за рейс, час: | C61: =IF('2. Для заполнения'!D130<>0, '2. Для заполнения'!D130, " ") -> 16.4 | E61: Общая жесткость | G61: =IF('2. Для заполнения'!D149<>0, '2. Для заполнения'!D149, " ") | H61: =IF('2. Для заполнения'!E149<>0, '2. Для заполнения'!E149, " ") | J61: AZ, азимут, град: | L61: =IF('2. Для заполнения'!D180<>0, '2. Для заполнения'!D180, " ") | M61: =IF('2. Для заполнения'!E180<>0, '2. Для заполнения'!E180, " ") | N61: =IF('2. Для заполнения'!F180<>0, '2. Для заполнения'!F180, " ") -> 257 | O61: =IF('2. Для заполнения'!G180<>0, '2. Для заполнения'!G180, " ") | P61: =IF('2. Для заполнения'!H180<>0, '2. Для заполнения'!H180, " ") | Q61: =IF('2. Для заполнения'!I180<>0, '2. Для заполнения'!I180, " ")
A62: T цирк. за рейс, час: | C62: =IF('2. Для заполнения'!D131<>0, '2. Для заполнения'!D131, " ") -> 59.63 | D62: ='2. Для заполнения'!G130 -> 0 | E62: Содержание CaCO3 | G62: =IF('2. Для заполнения'!D150<>0, '2. Для заполнения'!D150, " ") -> >80 | H62: =IF('2. Для заполнения'!E150<>0, '2. Для заполнения'!E150, " ") -> 80 | J62: TVD, глубина (верт), м: | L62: =IF('2. Для заполнения'!D181<>0, '2. Для заполнения'!D181, " ") | M62: =IF('2. Для заполнения'!E181<>0, '2. Для заполнения'!E181, " ") | N62: =IF('2. Для заполнения'!F181<>0, '2. Для заполнения'!F181, " ") -> 2475.25 | O62: =IF('2. Для заполнения'!G181<>0, '2. Для заполнения'!G181, " ") | P62: =IF('2. Для заполнения'!H181<>0, '2. Для заполнения'!H181, " ") | Q62: =IF('2. Для заполнения'!I181<>0, '2. Для заполнения'!I181, " ")
A63: Состояние: | C63: =IF('2. Для заполнения'!D132<>0, '2. Для заполнения'!D132, " ") -> New | E63: V скв. с БИ, м3: | G63: =IF('2. Для заполнения'!D151<>0, '2. Для заполнения'!D151, " ") | H63: =IF('2. Для заполнения'!E151<>0, '2. Для заполнения'!E151, " ") -> 34 | J63: Closure, отход, м: | L63: =IF('2. Для заполнения'!D182<>0, '2. Для заполнения'!D182, " ") | M63: =IF('2. Для заполнения'!E182<>0, '2. Для заполнения'!E182, " ") | N63: =IF('2. Для заполнения'!F182<>0, '2. Для заполнения'!F182, " ") -> 2164.94 | O63: =IF('2. Для заполнения'!G182<>0, '2. Для заполнения'!G182, " ") | P63: =IF('2. Для заполнения'!H182<>0, '2. Для заполнения'!H182, " ") | Q63: =IF('2. Для заполнения'!I182<>0, '2. Для заполнения'!I182, " ")
E64: V емкости, м3: | G64: =IF('2. Для заполнения'!D152<>0, '2. Для заполнения'!D152, " ") | H64: =IF('2. Для заполнения'!E152<>0, '2. Для заполнения'!E152, " ") -> 31 | J64: DLS, интенсивн. ° / 10м: | L64: =IF('2. Для заполнения'!D183<>0, '2. Для заполнения'!D183, " ") | M64: =IF('2. Для заполнения'!E183<>0, '2. Для заполнения'!E183, " ") | N64: =IF('2. Для заполнения'!F183<>0, '2. Для заполнения'!F183, " ") | O64: =IF('2. Для заполнения'!G183<>0, '2. Для заполнения'!G183, " ") | P64: =IF('2. Для заполнения'!H183<>0, '2. Для заполнения'!H183, " ") | Q64: =IF('2. Для заполнения'!I183<>0, '2. Для заполнения'!I183, " ")
E65: V циркуляции, м3: | G65: =IF('2. Для заполнения'!D153<>0, '2. Для заполнения'!D153, " ") | H65: =IF('2. Для заполнения'!E153<>0, '2. Для заполнения'!E153, " ") -> 65
E66: V скв. без БИ, м3: | G66: =IF('2. Для заполнения'!D154<>0, '2. Для заполнения'!D154, " ") | H66: =IF('2. Для заполнения'!E154<>0, '2. Для заполнения'!E154, " ") -> 48 | J66: Факт
J67: Параметр | L67: Зачение
J68: MD, глубина (ствол), м: | L68: =IF('2. Для заполнения'!D187<>0, '2. Для заполнения'!D187, " ") | M68: =IF('2. Для заполнения'!E187<>0, '2. Для заполнения'!E187, " ") | N68: =IF('2. Для заполнения'!F187<>0, '2. Для заполнения'!F187, " ") -> 3538 | O68: =IF('2. Для заполнения'!G187<>0, '2. Для заполнения'!G187, " ") | P68: =IF('2. Для заполнения'!H187<>0, '2. Для заполнения'!H187, " ") | Q68: =IF('2. Для заполнения'!I187<>0, '2. Для заполнения'!I187, " ")
A69: 7. Забойный двигатель | J69: Зенитный угол, град: | L69: =IF('2. Для заполнения'!D188<>0, '2. Для заполнения'!D188, " ") | M69: =IF('2. Для заполнения'!E188<>0, '2. Для заполнения'!E188, " ") | N69: =IF('2. Для заполнения'!F188<>0, '2. Для заполнения'!F188, " ") -> 87.9 | O69: =IF('2. Для заполнения'!G188<>0, '2. Для заполнения'!G188, " ") | P69: =IF('2. Для заполнения'!H188<>0, '2. Для заполнения'!H188, " ") | Q69: =IF('2. Для заполнения'!I188<>0, '2. Для заполнения'!I188, " ")
A70: № рейса | B70: Модель | C70: Диаметр, мм | D70: Длина, м | E70: Вес, кг | F70: Ресурс, час | G70: Наработка, час/сут/всего | J70: AZ, азимут, град: | L70: =IF('2. Для заполнения'!D189<>0, '2. Для заполнения'!D189, " ") | M70: =IF('2. Для заполнения'!E189<>0, '2. Для заполнения'!E189, " ") | N70: =IF('2. Для заполнения'!F189<>0, '2. Для заполнения'!F189, " ") -> 258.99 | O70: =IF('2. Для заполнения'!G189<>0, '2. Для заполнения'!G189, " ") | P70: =IF('2. Для заполнения'!H189<>0, '2. Для заполнения'!H189, " ") | Q70: =IF('2. Для заполнения'!I189<>0, '2. Для заполнения'!I189, " ")
A71: =IF('2. Для заполнения'!B171<>0, '2. Для заполнения'!B171, " ") -> 4 | B71: =IF('2. Для заполнения'!C171<>0, '2. Для заполнения'!C171, " ") -> ДВ-106.Р.7/8_(1°51') ООО "СОКОL" | C71: =IF('2. Для заполнения'!D171<>0, '2. Для заполнения'!D171, " ") -> 108 | D71: =IF('2. Для заполнения'!E171<>0, '2. Для заполнения'!E171, " ") -> 7.61 | E71: =IF('2. Для заполнения'!F171<>0, '2. Для заполнения'!F171, " ") -> 350.06 | F71: =IF('2. Для заполнения'!G171<>0, '2. Для заполнения'!G171, " ") -> 150 | G71: =IF('2. Для заполнения'!H171<>0, '2. Для заполнения'!H171, " ") -> 20.58 | H71: =IF('2. Для заполнения'!I171<>0, '2. Для заполнения'!I171, " ") -> 59.63 | J71: TVD, глубина (верт), м: | L71: =IF('2. Для заполнения'!D190<>0, '2. Для заполнения'!D190, " ") | M71: =IF('2. Для заполнения'!E190<>0, '2. Для заполнения'!E190, " ") | N71: =IF('2. Для заполнения'!F190<>0, '2. Для заполнения'!F190, " ") -> 2476.26 | O71: =IF('2. Для заполнения'!G190<>0, '2. Для заполнения'!G190, " ") | P71: =IF('2. Для заполнения'!H190<>0, '2. Для заполнения'!H190, " ") | Q71: =IF('2. Для заполнения'!I190<>0, '2. Для заполнения'!I190, " ")
A72: =IF('2. Для заполнения'!B172<>0, '2. Для заполнения'!B172, " ") | B72: =IF('2. Для заполнения'!C172<>0, '2. Для заполнения'!C172, " ") | C72: =IF('2. Для заполнения'!D172<>0, '2. Для заполнения'!D172, " ") | D72: =IF('2. Для заполнения'!E172<>0, '2. Для заполнения'!E172, " ") | E72: =IF('2. Для заполнения'!F172<>0, '2. Для заполнения'!F172, " ") | F72: =IF('2. Для заполнения'!G172<>0, '2. Для заполнения'!G172, " ") | G72: =IF('2. Для заполнения'!H172<>0, '2. Для заполнения'!H172, " ") | H72: =IF('2. Для заполнения'!I172<>0, '2. Для заполнения'!I172, " ") | J72: Closure, отход, м: | L72: =IF('2. Для заполнения'!D191<>0, '2. Для заполнения'!D191, " ") | M72: =IF('2. Для заполнения'!E191<>0, '2. Для заполнения'!E191, " ") | N72: =IF('2. Для заполнения'!F191<>0, '2. Для заполнения'!F191, " ") -> 2166.72 | O72: =IF('2. Для заполнения'!G191<>0, '2. Для заполнения'!G191, " ") | P72: =IF('2. Для заполнения'!H191<>0, '2. Для заполнения'!H191, " ") | Q72: =IF('2. Для заполнения'!I191<>0, '2. Для заполнения'!I191, " ")
A73: =IF('2. Для заполнения'!B173<>0, '2. Для заполнения'!B173, " ") | B73: =IF('2. Для заполнения'!C173<>0, '2. Для заполнения'!C173, " ") | C73: =IF('2. Для заполнения'!D173<>0, '2. Для заполнения'!D173, " ") | D73: =IF('2. Для заполнения'!E173<>0, '2. Для заполнения'!E173, " ") | E73: =IF('2. Для заполнения'!F173<>0, '2. Для заполнения'!F173, " ") | F73: =IF('2. Для заполнения'!G173<>0, '2. Для заполнения'!G173, " ") | G73: =IF('2. Для заполнения'!H173<>0, '2. Для заполнения'!H173, " ") | H73: =IF('2. Для заполнения'!I173<>0, '2. Для заполнения'!I173, " ") | J73: DLS, интенсивн. ° / 10м: | L73: =IF('2. Для заполнения'!D192<>0, '2. Для заполнения'!D192, " ") | M73: =IF('2. Для заполнения'!E192<>0, '2. Для заполнения'!E192, " ") | N73: =IF('2. Для заполнения'!F192<>0, '2. Для заполнения'!F192, " ") -> 0.32 | O73: =IF('2. Для заполнения'!G192<>0, '2. Для заполнения'!G192, " ") | P73: =IF('2. Для заполнения'!H192<>0, '2. Для заполнения'!H192, " ") | Q73: =IF('2. Для заполнения'!I192<>0, '2. Для заполнения'!I192, " ")
A75: Параметры гидравлики | J75: Отклонение
A76: Р насоса, атм | B76: Ø втулок насоса, мм | C76: Ход насоса, кол./мин | D76: Т подъема затрубье, мин | E76: Подача БН, л/сек | F76: Т цикла цирк., мин | G76: v истек. в насадках, м/с | H76: Гидр. Р на долоте, кВт/см2 | J76: Параметр | L76: Зачение
J77: MD, глубина (ствол), м: | L77: =IF('2. Для заполнения'!D196 <>0, '2. Для заполнения'!D196, " ") | M77: =IF('2. Для заполнения'!E196 <>0, '2. Для заполнения'!E196, " ") | N77: =IF('2. Для заполнения'!F196 <>0, '2. Для заполнения'!F196, " ") | O77: =IF('2. Для заполнения'!G196 <>0, '2. Для заполнения'!G196, " ") | P77: =IF('2. Для заполнения'!H196 <>0, '2. Для заполнения'!H196, " ") | Q77: =IF('2. Для заполнения'!I196 <>0, '2. Для заполнения'!I196, " ")
A78: =IF('2. Для заполнения'!B158<>0, '2. Для заполнения'!B158, " ") -> 195 | B78: =IF('2. Для заполнения'!C158<>0, '2. Для заполнения'!C158, " ") -> 110 | C78: =IF('2. Для заполнения'!D158<>0, '2. Для заполнения'!D158, " ") -> 114 | D78: =IF('2. Для заполнения'!E158<>0, '2. Для заполнения'!E158, " ") -> 36 | E78: =IF('2. Для заполнения'!F158<>0, '2. Для заполнения'!F158, " ") -> 12 | F78: =IF('2. Для заполнения'!G158<>0, '2. Для заполнения'!G158, " ") -> 47 | G78: =IF('2. Для заполнения'!H158<>0, '2. Для заполнения'!H158, " ") | H78: =IF('2. Для заполнения'!I158<>0, '2. Для заполнения'!I158, " ") | J78: Зенитный угол, град: | L78: =IF('2. Для заполнения'!D197 <>0, '2. Для заполнения'!D197, " ") | M78: =IF('2. Для заполнения'!E197 <>0, '2. Для заполнения'!E197, " ") | N78: =IF('2. Для заполнения'!F197 <>0, '2. Для заполнения'!F197, " ") -> 2.29 | O78: =IF('2. Для заполнения'!G197 <>0, '2. Для заполнения'!G197, " ") | P78: =IF('2. Для заполнения'!H197 <>0, '2. Для заполнения'!H197, " ") | Q78: =IF('2. Для заполнения'!I197 <>0, '2. Для заполнения'!I197, " ")
A79: =IF('2. Для заполнения'!B159<>0, '2. Для заполнения'!B159, " ") | B79: =IF('2. Для заполнения'!C159<>0, '2. Для заполнения'!C159, " ") | C79: =IF('2. Для заполнения'!D159<>0, '2. Для заполнения'!D159, " ") | D79: =IF('2. Для заполнения'!E159<>0, '2. Для заполнения'!E159, " ") | E79: =IF('2. Для заполнения'!F159<>0, '2. Для заполнения'!F159, " ") | F79: =IF('2. Для заполнения'!G159<>0, '2. Для заполнения'!G159, " ") | G79: =IF('2. Для заполнения'!H159<>0, '2. Для заполнения'!H159, " ") | H79: =IF('2. Для заполнения'!I159<>0, '2. Для заполнения'!I159, " ") | J79: AZ, азимут, град: | L79: =IF('2. Для заполнения'!D198 <>0, '2. Для заполнения'!D198, " ") | M79: =IF('2. Для заполнения'!E198 <>0, '2. Для заполнения'!E198, " ") | N79: =IF('2. Для заполнения'!F198 <>0, '2. Для заполнения'!F198, " ") -> -1.99 | O79: =IF('2. Для заполнения'!G198 <>0, '2. Для заполнения'!G198, " ") | P79: =IF('2. Для заполнения'!H198 <>0, '2. Для заполнения'!H198, " ") | Q79: =IF('2. Для заполнения'!I198 <>0, '2. Для заполнения'!I198, " ")
J80: TVD, глубина (верт), м: | L80: =IF('2. Для заполнения'!D199 <>0, '2. Для заполнения'!D199, " ") | M80: =IF('2. Для заполнения'!E199 <>0, '2. Для заполнения'!E199, " ") | N80: =IF('2. Для заполнения'!F199 <>0, '2. Для заполнения'!F199, " ") -> -1.01 | O80: =IF('2. Для заполнения'!G199 <>0, '2. Для заполнения'!G199, " ") | P80: =IF('2. Для заполнения'!H199 <>0, '2. Для заполнения'!H199, " ") | Q80: =IF('2. Для заполнения'!I199 <>0, '2. Для заполнения'!I199, " ")
A81: Система очистки | J81: Closure, отход, м: | L81: =IF('2. Для заполнения'!D200 <>0, '2. Для заполнения'!D200, " ") | M81: =IF('2. Для заполнения'!E200 <>0, '2. Для заполнения'!E200, " ") | N81: =IF('2. Для заполнения'!F200 <>0, '2. Для заполнения'!F200, " ") -> -1.78 | O81: =IF('2. Для заполнения'!G200 <>0, '2. Для заполнения'!G200, " ") | P81: =IF('2. Для заполнения'!H200 <>0, '2. Для заполнения'!H200, " ") | Q81: =IF('2. Для заполнения'!I200 <>0, '2. Для заполнения'!I200, " ")
A82: Видросито | E82: Сито №1 | F82: Сито №2 | G82: Сито №3 | H82: Сито №4 | J82: DLS, интенсивн. ° / 10м: | L82: =IF('2. Для заполнения'!D201 <>0, '2. Для заполнения'!D201, " ") | M82: =IF('2. Для заполнения'!E201 <>0, '2. Для заполнения'!E201, " ") | N82: =IF('2. Для заполнения'!F201 <>0, '2. Для заполнения'!F201, " ") -> -0.32 | O82: =IF('2. Для заполнения'!G201 <>0, '2. Для заполнения'!G201, " ") | P82: =IF('2. Для заполнения'!H201 <>0, '2. Для заполнения'!H201, " ") | Q82: =IF('2. Для заполнения'!I201 <>0, '2. Для заполнения'!I201, " ")
A83: Размер сеток на ВС | E83: =IF('2. Для заполнения'!C164 <>0, '2. Для заполнения'!C164, " ") -> 270/270/200/200 | F83: =IF('2. Для заполнения'!D164 <>0, '2. Для заполнения'!D164, " ") -> 270/270/270/200 | G83: =IF('2. Для заполнения'!E164 <>0, '2. Для заполнения'!E164, " ") -> 325/325/325/325 | H83: =IF('2. Для заполнения'!F164 <>0, '2. Для заполнения'!F164, " ") | J83: Комментарии подрядчика по телеметрии:
A84: Центрифуга, вход/выход, г/см3 | E84: =IF('2. Для заполнения'!C165 <>0, '2. Для заполнения'!C165, " ") -> 1,12/1,05 (1,71)
A85: Пульпа пескоотд-ля/илоотд-ля, г/м3 | E85: =IF('2. Для заполнения'!C166 <>0, '2. Для заполнения'!C166, " ") -> 1,22/1,37 | J85: 9. Транспорт, расход ГСМ
A86: Потери на пов-ности./в скважине | E86: =IF('2. Для заполнения'!C167 <>0, '2. Для заполнения'!C167, " ") -> 12/2 | J86: Наличие техники на кустовой площадке | M86: Наличие агрегатов на кустовой площадке
J87: № п/п | K87: Позиция | L87: Кол-во | M87: Агрегат | O87: Т работы, ч | P87: Расход д/т, м3/ч | Q87: Расход за сутки
A88: 10. Персонал | J88: ='2. Для заполнения'!B208 -> 1 | K88: =IF('2. Для заполнения'!C208<>0, '2. Для заполнения'!C208, " ") -> Вакуумник УРАЛ С 613 РВ 70 | L88: =IF('2. Для заполнения'!D208<>0, '2. Для заполнения'!D208, " ") -> 1 | M88: ='2. Для заполнения'!F208 -> 0 | O88: =IF('2. Для заполнения'!G208<>0, '2. Для заполнения'!G208, " ") -> 24 | Q88: ='2. Для заполнения'!I208 -> 1284
A89: ИТР "Победит" | B89: Бурильщики | C89: Пом. бур. | D89: Ост. персонал ББ | E89: Служба заказчика | F89: Подрядчики | G89: Сторонние орг. | H89: Итог | J89: ='2. Для заполнения'!B209 -> 2 | K89: =IF('2. Для заполнения'!C209<>0, '2. Для заполнения'!C209, " ") -> Площадка УРАЛ Н 748 ТО 174 | L89: =IF('2. Для заполнения'!D209<>0, '2. Для заполнения'!D209, " ") -> 1 | M89: ='2. Для заполнения'!F209 -> 0 | O89: =IF('2. Для заполнения'!G209<>0, '2. Для заполнения'!G209, " ") | Q89: ='2. Для заполнения'!I209 -> 0
J90: ='2. Для заполнения'!B210 -> 3 | K90: =IF('2. Для заполнения'!C210<>0, '2. Для заполнения'!C210, " ") -> Погрузчик LONKIN 7719 ММ 77 | L90: =IF('2. Для заполнения'!D210<>0, '2. Для заполнения'!D210, " ") -> 1 | M90: ='2. Для заполнения'!F210 -> 0 | O90: =IF('2. Для заполнения'!G210<>0, '2. Для заполнения'!G210, " ") -> 24 | Q90: ='2. Для заполнения'!I210 -> 1157
A91: ='2. Для заполнения'!B225 -> 5 | B91: ='2. Для заполнения'!C225 -> 3 | C91: 6 | D91: ='2. Для заполнения'!E225 -> 9 | E91: ='2. Для заполнения'!F225 -> 1 | F91: 18 | G91: ='2. Для заполнения'!H225 -> 4 | H91: =SUM(A91:G91) -> 46 | J91: ='2. Для заполнения'!B211 -> 4 | K91: =IF('2. Для заполнения'!C211<>0, '2. Для заполнения'!C211, " ") -> Водовоза УРАЛ 10м³ Т 455 АС 797 | L91: =IF('2. Для заполнения'!D211<>0, '2. Для заполнения'!D211, " ") -> 1 | M91: ='2. Для заполнения'!F211 -> 0 | O91: =IF('2. Для заполнения'!G211<>0, '2. Для заполнения'!G211, " ") | Q91: ='2. Для заполнения'!I211 -> 0
A92: ИТР ООО "Победит Холдинг" | E92: Подписи | J92: ='2. Для заполнения'!B212 -> 5 | K92: =IF('2. Для заполнения'!C212<>0, '2. Для заполнения'!C212, " ") -> Водовоза УРАЛ 20м³ В 312 КВ 70 | L92: =IF('2. Для заполнения'!D212<>0, '2. Для заполнения'!D212, " ") -> 1 | M92: ='2. Для заполнения'!F212 -> 0 | O92: =IF('2. Для заполнения'!G212<>0, '2. Для заполнения'!G212, " ") -> 24 | Q92: ='2. Для заполнения'!I212 -> 407
A93: Должность | B93: ФИО | E93: Должность | G93: ФИО | J93: ='2. Для заполнения'!B213 -> 6 | K93: =IF('2. Для заполнения'!#REF!<>0, '2. Для заполнения'!#REF!, " ") -> #REF! | L93: =IF('2. Для заполнения'!D213<>0, '2. Для заполнения'!D213, " ") | M93: ='2. Для заполнения'!F213 -> 0 | O93: =IF('2. Для заполнения'!G213<>0, '2. Для заполнения'!G213, " ") -> 16 | Q93: ='2. Для заполнения'!I213 -> 0
A94: Инженер по бурению: | B94: =IF('2. Для заполнения'!D229 <>0, '2. Для заполнения'!D229, " ") | E94: Представитель: | G94: =IF('2. Для заполнения'!H229 <>0, '2. Для заполнения'!H229, " ") -> Грот Дмитрий Александрович | J94: ='2. Для заполнения'!B214 -> 7 | K94: =IF('2. Для заполнения'!C213<>0, '2. Для заполнения'!C213, " ") | L94: =IF('2. Для заполнения'!D214<>0, '2. Для заполнения'!D214, " ") | M94: ='2. Для заполнения'!F214 -> 0 | O94: =IF('2. Для заполнения'!G214<>0, '2. Для заполнения'!G214, " ") -> 11 | Q94: ='2. Для заполнения'!I214 -> 376
A95: Ведущий инженер механик | B95: =IF('2. Для заполнения'!D230 <>0, '2. Для заполнения'!D230, " ") -> Ведущий инженер-механик | E95: Мастер буровой: | G95: =IF('2. Для заполнения'!H230 <>0, '2. Для заполнения'!H230, " ") -> Коротков Денис Сергеевич | J95: ='2. Для заполнения'!B215 -> 8 | K95: =IF('2. Для заполнения'!C215<>0, '2. Для заполнения'!C215, " ") -> Голова УРАЛ Х 226 АН 797 | L95: =IF('2. Для заполнения'!D215<>0, '2. Для заполнения'!D215, " ") | M95: ='2. Для заполнения'!F215 -> 0 | O95: =IF('2. Для заполнения'!G215<>0, '2. Для заполнения'!G215, " ") -> 16 | Q95: ='2. Для заполнения'!I215 -> 0
A96: И. по ТБ: | B96: =IF('2. Для заполнения'!D231 <>0, '2. Для заполнения'!D231, " ") -> Черноиванов Павел Вячеславович | E96: Мастер по сложным работам | G96: =IF('2. Для заполнения'!H231 <>0, '2. Для заполнения'!H231, " ") -> Воронков Вадим Анатольевич | J96: ='2. Для заполнения'!B216 -> 9 | K96: =IF('2. Для заполнения'!C216<>0, '2. Для заполнения'!C216, " ") | L96: =IF('2. Для заполнения'!D216<>0, '2. Для заполнения'!D216, " ") | M96: ='2. Для заполнения'!F216 -> 0 | O96: =IF('2. Для заполнения'!G216<>0, '2. Для заполнения'!G216, " ") -> 16 | P96: =IF('2. Для заполнения'!H216<>0, '2. Для заполнения'!H216, " ") | Q96: ='2. Для заполнения'!I216 -> 0
A97: Ведущий инженер энергетик | B97: =IF('2. Для заполнения'!D232 <>0, '2. Для заполнения'!D232, " ") -> Горшков Александр Владимирович | K97: =IF('2. Для заполнения'!C217<>0, '2. Для заполнения'!C217, " ") | L97: =IF('2. Для заполнения'!D217<>0, '2. Для заполнения'!D217, " ") | M97: ='2. Для заполнения'!F217 -> 0 | O97: =IF('2. Для заполнения'!G217<>0, '2. Для заполнения'!G217, " ") -> 13 | P97: =IF('2. Для заполнения'!H217<>0, '2. Для заполнения'!H217, " ") | Q97: ='2. Для заполнения'!I217 -> 0
M98: ='2. Для заполнения'!F218 -> 0 | O98: =IF('2. Для заполнения'!G218<>0, '2. Для заполнения'!G218, " ") | Q98: ='2. Для заполнения'!I218 -> 0
M99: ='2. Для заполнения'!F220 -> 0 | O99: =IF('2. Для заполнения'!G220<>0, '2. Для заполнения'!G220, " ") | Q99: ='2. Для заполнения'!I220 -> 0
M100: Итого: | O100: =SUM(O88:O99) -> 144 | P100: =SUM(P88:P99) -> 0 | Q100: =SUM(Q88:Q99) -> 3224
J102: 11. Персонал подрядных организаций
J103: Сервис | K103: ='2. Для заполнения'!C236 -> Растворы | L103: ='2. Для заполнения'!D236 -> ННБ | M103: ='2. Для заполнения'!E236 -> ГТИ | N103: ='2. Для заполнения'!F236 -> Спуск ОК | O103: ='2. Для заполнения'!G236 -> ГИС | P103: ='2. Для заполнения'!H236 -> Цементаж | Q103: ='2. Для заполнения'!I236 -> Прочий сервис
K104: ='2. Для заполнения'!C237 -> ООО "НСК Эшелон" | L104: ='2. Для заполнения'!D237 -> ООО "Интер-Сервис" | M104: ='2. Для заполнения'!E237 -> ПФ «Востокгазгеофизика» | N104: ='2. Для заполнения'!F237 -> ООО "Нефтесервисная компания" "Буран" | O104: ='2. Для заполнения'!G237 -> ПФ «Востокгазгеофизика» | P104: ='2. Для заполнения'!H237 -> ООО "ЦЦС" | Q104: ='2. Для заполнения'!I237 -> ООО «ЭТТЦ»
J105: Персонал, чел | K105: ='2. Для заполнения'!C238 -> 2 | L105: ='2. Для заполнения'!D238 -> 3 | M105: ='2. Для заполнения'!E238 -> 4 | N105: ='2. Для заполнения'!F238 -> 1 | O105: ='2. Для заполнения'!G238 -> 0 | P105: ='2. Для заполнения'!H238 -> 0 | Q105: ='2. Для заполнения'!I238 -> 2
A109: Представитель заказчика: | E109: =G94 -> Грот Дмитрий Александрович | H109: Буровой мастер: | K109: =G95 -> Коротков Денис Сергеевич | N109: Руководитель объекта:

Sheet 1. Хронология работ
A1: Проект | B1: Основные работы | C1: Месторождение | D1: Куст | E1: Скважина | F1: Мастер | G1: Помощник мастера | H1: Бурильщик | I1: № рапорта | J1: № п/п | K1: ОК | L1: Этап | M1: Контекст простоя | N1: Событие | O1: Категория работ | P1: Вид работ | Q1: Категория объектов | R1: Объект работ | S1: Рейс | T1: Описание работ | U1: Часы | V1: Забой, м | W1: Статус | X1: Ответственный за НПВ | Y1: Слайд/ротор | Z1: G, т | AA1: Q, л/с | AB1: P, атм | AC1: N, об/мин | AD1: M, кН*м | AE1: Проходка, м | AF1: Начало | AG1: Окончание | AH1: Сутки | AI1: Нараст. сутки | AJ1: Результат | AK1: ПВ | AL1: ПНВ | AM1: НПВ | AN1: Накопительное НПВ | AO1: Накопительное ПНВ | AP1: Дата начала | AQ1: Время начала | AR1: Дата окончания | AS1: Время окончания | AT1: Бригада | AU1: Ключ | AV1: Результат, вид, объект | AW1: Подытог за операцию | AX1: Вид, объект
A2: ГДТ | B2: КРС | C2: Казанское | D2: 1 | E2: 6 бис | F2: Вдовин И.О. | H2: Жангазиев С.К. | I2: 1 | J2: 0.1 | L2: ДПМ | M2: Штатно | O2: ПР | P2: Передвижка | Q2: Оборудование | R2: УПА | T2: Переезд бригады на скв. № 6 бис к.п. № 1 бис КНГКМ с к.п. № 7 КНГКМ 9 рейсов L= 7,696км. | U2: 4 | W2: Работы окончены | X2: Победит Холдинг | AE2: =IFERROR(IF(Хронология[[#This Row],[Забой, м]]-V1<0, 0, Хронология[[#This Row],[Забой, м]]-V1), 0) -> 0 | AF2: 46144.833 | AG2: =Хронология[[#This Row],[Начало]]+Хронология[[#This Row],[Сутки]] -> 46145 | AH2: =Хронология[[#This Row],[Часы]]/24 -> 0.16666667 | AI2: =IFERROR(Хронология[[#This Row],[Сутки]]+AI1, Хронология[[#This Row],[Сутки]]) -> 0.16666667 | AJ2: =IF(Хронология[[#This Row],[Этап]]="Доп. работы", "ПВ", IFERROR( IF(AND( MATCH(Хронология[[#This Row],[Ключ]], Планирование[Ключ], 0), Хронология[[#This Row],[Подытог за операцию]] <= INDEX(Планирование[Сутки (план)], MATCH(Хронология[[#This Row],[Ключ]], Планирование[Ключ], 0)) ), "ПВ", "ПНВ"), "НПВ")) -> ПВ | AK2: =IF( OR(Хронология[[#This Row],[Результат]]="ПВ", Хронология[[#This Row],[Результат]]="ПНВ"), Хронология[[#This Row],[Часы]] - IF( Хронология[[#This Row],[Результат]]="ПНВ", MAX(0, MAX(0, SUMIFS(Хронология[Часы], Хронология[Ключ], Хронология[[#This Row],[Ключ]], Хронология[Начало], "<=" & Хронология[[#This Row],[Начало]]) - IFERROR(INDEX(Планирование[Часы (план)], MATCH(Хронология[[#This Row],[Ключ]], Планирование[Ключ], 0)), 0)) - MAX(0, SUMIFS(Хронология[Часы], Хронология[Ключ], Хронология[[#This Row],[Ключ]], Хронология[Начало], "<" & Хронология[[#This Row],[Начало]]) - IFERROR(INDEX(Планирование[Часы (план)], MATCH(Хронология[[#This Row],[Ключ]], Планирование[Ключ], 0)), 0)) ), 0 ), 0 ) -> 4 | AL2: =IF( Хронология[[#This Row],[Результат]]="ПНВ", MAX(0, MAX(0, SUMIFS(Хронология[Часы], Хронология[Ключ], Хронология[[#This Row],[Ключ]], Хронология[Начало], "<=" & Хронология[[#This Row],[Начало]]) - IFERROR(INDEX(Планирование[Часы (план)], MATCH(Хронология[[#This Row],[Ключ]], Планирование[Ключ], 0)), 0)) - MAX(0, SUMIFS(Хронология[Часы], Хронология[Ключ], Хронология[[#This Row],[Ключ]], Хронология[Начало], "<" & Хронология[[#This Row],[Начало]]) - IFERROR(INDEX(Планирование[Часы (план)], MATCH(Хронология[[#This Row],[Ключ]], Планирование[Ключ], 0)), 0)) ), 0 ) -> 0 | AM2: =IF(Хронология[[#This Row],[Результат]]="НПВ", Хронология[[#This Row],[Часы]], 0) -> 0 | AN2: =SUMIFS(Хронология[НПВ], Хронология[Скважина], Хронология[[#This Row],[Скважина]], Хронология[Начало], "<=" & Хронология[[#This Row],[Начало]]) -> 0 | AO2: =SUMIFS(Хронология[ПНВ], Хронология[Скважина], Хронология[[#This Row],[Скважина]], Хронология[Начало], "<=" & Хронология[[#This Row],[Начало]]) -> 0 | AP2: =INT(ROUND(Хронология[[#This Row],[Начало]], 3)) -> 46144 | AQ2: =Хронология[[#This Row],[Начало]]-INT(Хронология[[#This Row],[Начало]]) -> 0.83333333 | AR2: =INT(ROUND(Хронология[[#This Row],[Окончание]], 3)) -> 46145 | AS2: =Хронология[[#This Row],[Окончание]]-INT(Хронология[[#This Row],[Окончание]]) -> 0 | AT2: =Хронология[[#This Row],[Мастер]] & CHAR(10) & Хронология[[#This Row],[Помощник мастера]] & CHAR(10) & Хронология[[#This Row],[Бурильщик]] -> Вдовин И.О. Жангазиев С.К. | AU2: =IF(Хронология[[#This Row],[Контекст простоя]]="Штатно", Хронология[[#This Row],[Скважина]] & " " & "ОК–" &Хронология[[#This Row],[ОК]] & " " & Хронология[[#This Row],[Этап]] & " " & Хронология[[#This Row],[Вид работ]] & " " & Хронология[[#This Row],[Объект работ]] & " " & Хронология[[#This Row],[Рейс]], Хронология[[#This Row],[Скважина]] & " " & "ОК–" &Хронология[[#This Row],[ОК]] & " " & Хронология[[#This Row],[Этап]] & " " & Хронология[[#This Row],[Контекст простоя]] & " " & Хронология[[#This Row],[Событие]] & " " & Хронология[[#This Row],[Вид работ]] & " " & Хронология[[#This Row],[Объект работ]] & " " & Хронология[[#This Row],[Рейс]]) -> 6 бис ОК– ДПМ Передвижка УПА | AV2: =Хронология[[#This Row],[Результат]]&": "&Хронология[[#This Row],[Событие]]& CHAR(10) &Хронология[[#This Row],[Вид работ]]&" "&Хронология[[#This Row],[Объект работ]] -> ПВ: Передвижка УПА | AW2: =SUMIF($AU$2:AU2, Хронология[[#This Row],[Ключ]], $AH$2:AH2) -> 0.16666667 | AX2: =Хронология[[#This Row],[Вид работ]] & " " & Хронология[[#This Row],[Объект работ]] -> Передвижка УПА
A3: ГДТ | B3: КРС | C3: Казанское | D3: 1 | E3: 6 бис | F3: Жабин П.П. | H3: Керимов Н.К. | L3: ДПМ | M3: Штатно | O3: ПР | P3: Передвижка | Q3: Оборудование | R3: УПА | U3: 2.5 | AE3: =IFERROR(IF(Хронология[[#This Row],[Забой, м]]-V2<0, 0, Хронология[[#This Row],[Забой, м]]-V2), 0) -> 0 | AF3: =AG2 -> 46145 | AG3: =Хронология[[#This Row],[Начало]]+Хронология[[#This Row],[Сутки]] -> 46145.104 | AH3: =Хронология[[#This Row],[Часы]]/24 -> 0.10416667 | AI3: =IFERROR(Хронология[[#This Row],[Сутки]]+AI2, Хронология[[#This Row],[Сутки]]) -> 0.27083333 | AJ3: =IF(Хронология[[#This Row],[Этап]]="Доп. работы", "ПВ", IFERROR( IF(AND( MATCH(Хронология[[#This Row],[Ключ]], Планирование[Ключ], 0), Хронология[[#This Row],[Подытог за операцию]] <= INDEX(Планирование[Сутки (план)], MATCH(Хронология[[#This Row],[Ключ]], Планирование[Ключ], 0)) ), "ПВ", "ПНВ"), "НПВ")) -> ПНВ | AK3: =IF( OR(Хронология[[#This Row],[Результат]]="ПВ", Хронология[[#This Row],[Результат]]="ПНВ"), Хронология[[#This Row],[Часы]] - IF( Хронология[[#This Row],[Результат]]="ПНВ", MAX(0, MAX(0, SUMIFS(Хронология[Часы], Хронология[Ключ], Хронология[[#This Row],[Ключ]], Хронология[Начало], "<=" & Хронология[[#This Row],[Начало]]) - IFERROR(INDEX(Планирование[Часы (план)], MATCH(Хронология[[#This Row],[Ключ]], Планирование[Ключ], 0)), 0)) - MAX(0, SUMIFS(Хронология[Часы], Хронология[Ключ], Хронология[[#This Row],[Ключ]], Хронология[Начало], "<" & Хронология[[#This Row],[Начало]]) - IFERROR(INDEX(Планирование[Часы (план)], MATCH(Хронология[[#This Row],[Ключ]], Планирование[Ключ], 0)), 0)) ), 0 ), 0 ) -> 2.37 | AL3: =IF( Хронология[[#This Row],[Результат]]="ПНВ", MAX(0, MAX(0, SUMIFS(Хронология[Часы], Хронология[Ключ], Хронология[[#This Row],[Ключ]], Хронология[Начало], "<=" & Хронология[[#This Row],[Начало]]) - IFERROR(INDEX(Планирование[Часы (план)], MATCH(Хронология[[#This Row],[Ключ]], Планирование[Ключ], 0)), 0)) - MAX(0, SUMIFS(Хронология[Часы], Хронология[Ключ], Хронология[[#This Row],[Ключ]], Хронология[Начало], "<" & Хронология[[#This Row],[Начало]]) - IFERROR(INDEX(Планирование[Часы (план)], MATCH(Хронология[[#This Row],[Ключ]], Планирование[Ключ], 0)), 0)) ), 0 ) -> 0.13 | AM3: =IF(Хронология[[#This Row],[Результат]]="НПВ", Хронология[[#This Row],[Часы]], 0) -> 0 | AN3: =SUMIFS(Хронология[НПВ], Хронология[Скважина], Хронология[[#This Row],[Скважина]], Хронология[Начало], "<=" & Хронология[[#This Row],[Начало]]) -> 0 | AO3: =SUMIFS(Хронология[ПНВ], Хронология[Скважина], Хронология[[#This Row],[Скважина]], Хронология[Начало], "<=" & Хронология[[#This Row],[Начало]]) -> 0.13 | AP3: =INT(ROUND(Хронология[[#This Row],[Начало]], 3)) -> 46145 | AQ3: =Хронология[[#This Row],[Начало]]-INT(Хронология[[#This Row],[Начало]]) -> 0 | AR3: =INT(ROUND(Хронология[[#This Row],[Окончание]], 3)) -> 46145 | AS3: =Хронология[[#This Row],[Окончание]]-INT(Хронология[[#This Row],[Окончание]]) -> 0.10416667 | AT3: =Хронология[[#This Row],[Мастер]] & CHAR(10) & Хронология[[#This Row],[Помощник мастера]] & CHAR(10) & Хронология[[#This Row],[Бурильщик]] -> Жабин П.П. Керимов Н.К. | AU3: =IF(Хронология[[#This Row],[Контекст простоя]]="Штатно", Хронология[[#This Row],[Скважина]] & " " & "ОК–" &Хронология[[#This Row],[ОК]] & " " & Хронология[[#This Row],[Этап]] & " " & Хронология[[#This Row],[Вид работ]] & " " & Хронология[[#This Row],[Объект работ]] & " " & Хронология[[#This Row],[Рейс]], Хронология[[#This Row],[Скважина]] & " " & "ОК–" &Хронология[[#This Row],[ОК]] & " " & Хронология[[#This Row],[Этап]] & " " & Хронология[[#This Row],[Контекст простоя]] & " " & Хронология[[#This Row],[Событие]] & " " & Хронология[[#This Row],[Вид работ]] & " " & Хронология[[#This Row],[Объект работ]] & " " & Хронология[[#This Row],[Рейс]]) -> 6 бис ОК– ДПМ Передвижка УПА | AV3: =Хронология[[#This Row],[Результат]]&": "&Хронология[[#This Row],[Событие]]& CHAR(10) &Хронология[[#This Row],[Вид работ]]&" "&Хронология[[#This Row],[Объект работ]] -> ПНВ: Передвижка УПА | AW3: =SUMIF($AU$2:AU3, Хронология[[#This Row],[Ключ]], $AH$2:AH3) -> 0.27083333 | AX3: =Хронология[[#This Row],[Вид работ]] & " " & Хронология[[#This Row],[Объект работ]] -> Передвижка УПА
A4: ГДТ | B4: КРС | C4: Казанское | D4: 1 | E4: 6 бис | F4: Жабин П.П. | H4: Керимов Н.К. | I4: 1 | J4: 0.2 | L4: ДПМ | M4: Штатно | O4: Монтаж_демонтаж_установка | P4: Монтаж | Q4: Оборудование | R4: БО | T4: Расстановка оборудования- 9шт. Установка заземления - 9шт. Монтаж подставок под кабель-25шт. Подключение оборудования-8шт. Монтаж Экр.колпаков - 1 шт. | U4: 4.25 | W4: Работы окончены | X4: Победит Холдинг | AE4: =IFERROR(IF(Хронология[[#This Row],[Забой, м]]-V3<0, 0, Хронология[[#This Row],[Забой, м]]-V3), 0) -> 0 | AF4: =AG3 -> 46145.104 | AG4: =Хронология[[#This Row],[Начало]]+Хронология[[#This Row],[Сутки]] -> 46145.281 | AH4: =Хронология[[#This Row],[Часы]]/24 -> 0.17708333 | AI4: =IFERROR(Хронология[[#This Row],[Сутки]]+AI3, Хронология[[#This Row],[Сутки]]) -> 0.44791667 | AJ4: =IF(Хронология[[#This Row],[Этап]]="Доп. работы", "ПВ", IFERROR( IF(AND( MATCH(Хронология[[#This Row],[Ключ]], Планирование[Ключ], 0), Хронология[[#This Row],[Подытог за операцию]] <= INDEX(Планирование[Сутки (план)], MATCH(Хронология[[#This Row],[Ключ]], Планирование[Ключ], 0)) ), "ПВ", "ПНВ"), "НПВ")) -> ПНВ | AK4: =IF( OR(Хронология[[#This Row],[Результат]]="ПВ", Хронология[[#This Row],[Результат]]="ПНВ"), Хронология[[#This Row],[Часы]] - IF( Хронология[[#This Row],[Результат]]="ПНВ", MAX(0, MAX(0, SUMIFS(Хронология[Часы], Хронология[Ключ], Хронология[[#This Row],[Ключ]], Хронология[Начало], "<=" & Хронология[[#This Row],[Начало]]) - IFERROR(INDEX(Планирование[Часы (план)], MATCH(Хронология[[#This Row],[Ключ]], Планирование[Ключ], 0)), 0)) - MAX(0, SUMIFS(Хронология[Часы], Хронология[Ключ], Хронология[[#This Row],[Ключ]], Хронология[Начало], "<" & Хронология[[#This Row],[Начало]]) - IFERROR(INDEX(Планирование[Часы (план)], MATCH(Хронология[[#This Row],[Ключ]], Планирование[Ключ], 0)), 0)) ), 0 ), 0 ) -> 4.04 | AL4: =IF( Хронология[[#This Row],[Результат]]="ПНВ", MAX(0, MAX(0, SUMIFS(Хронология[Часы], Хронология[Ключ], Хронология[[#This Row],[Ключ]], Хронология[Начало], "<=" & Хронология[[#This Row],[Начало]]) - IFERROR(INDEX(Планирование[Часы (план)], MATCH(Хронология[[#This Row],[Ключ]], Планирование[Ключ], 0)), 0)) - MAX(0, SUMIFS(Хронология[Часы], Хронология[Ключ], Хронология[[#This Row],[Ключ]], Хронология[Начало], "<" & Хронология[[#This Row],[Начало]]) - IFERROR(INDEX(Планирование[Часы (план)], MATCH(Хронология[[#This Row],[Ключ]], Планирование[Ключ], 0)), 0)) ), 0 ) -> 0.21 | AM4: =IF(Хронология[[#This Row],[Результат]]="НПВ", Хронология[[#This Row],[Часы]], 0) -> 0 | AN4: =SUMIFS(Хронология[НПВ], Хронология[Скважина], Хронология[[#This Row],[Скважина]], Хронология[Начало], "<=" & Хронология[[#This Row],[Начало]]) -> 0 | AO4: =SUMIFS(Хронология[ПНВ], Хронология[Скважина], Хронология[[#This Row],[Скважина]], Хронология[Начало], "<=" & Хронология[[#This Row],[Начало]]) -> 0.34 | AP4: =INT(ROUND(Хронология[[#This Row],[Начало]], 3)) -> 46145 | AQ4: =Хронология[[#This Row],[Начало]]-INT(Хронология[[#This Row],[Начало]]) -> 0.10416667 | AR4: =INT(ROUND(Хронология[[#This Row],[Окончание]], 3)) -> 46145 | AS4: =Хронология[[#This Row],[Окончание]]-INT(Хронология[[#This Row],[Окончание]]) -> 0.28125 | AT4: =Хронология[[#This Row],[Мастер]] & CHAR(10) & Хронология[[#This Row],[Помощник мастера]] & CHAR(10) & Хронология[[#This Row],[Бурильщик]] -> Жабин П.П. Керимов Н.К. | AU4: =IF(Хронология[[#This Row],[Контекст простоя]]="Штатно", Хронология[[#This Row],[Скважина]] & " " & "ОК–" &Хронология[[#This Row],[ОК]] & " " & Хронология[[#This Row],[Этап]] & " " & Хронология[[#This Row],[Вид работ]] & " " & Хронология[[#This Row],[Объект работ]] & " " & Хронология[[#This Row],[Рейс]], Хронология[[#This Row],[Скважина]] & " " & "ОК–" &Хронология[[#This Row],[ОК]] & " " & Хронология[[#This Row],[Этап]] & " " & Хронология[[#This Row],[Контекст простоя]] & " " & Хронология[[#This Row],[Событие]] & " " & Хронология[[#This Row],[Вид работ]] & " " & Хронология[[#This Row],[Объект работ]] & " " & Хронология[[#This Row],[Рейс]]) -> 6 бис ОК– ДПМ Монтаж БО | AV4: =Хронология[[#This Row],[Результат]]&": "&Хронология[[#This Row],[Событие]]& CHAR(10) &Хронология[[#This Row],[Вид работ]]&" "&Хронология[[#This Row],[Объект работ]] -> ПНВ: Монтаж БО | AW4: =SUMIF($AU$2:AU4, Хронология[[#This Row],[Ключ]], $AH$2:AH4) -> 0.17708333 | AX4: =Хронология[[#This Row],[Вид работ]] & " " & Хронология[[#This Row],[Объект работ]] -> Монтаж БО
A5: ГДТ | B5: КРС | C5: Казанское | D5: 1 | E5: 6 бис | F5: Вдовин И.О. | H5: Жангазиев С.К. | I5: 1 | J5: 0.3 | L5: ПР | M5: Штатно | O5: Монтаж_демонтаж_установка | P5: Монтаж | Q5: Оборудование | R5: УПА | T5: Монтаж подъемного агрегата А-60/80 согласно ТУ и правил ПБ - 100%, РП, спайдера СУ-80, гидроключа ГКШ-1200, ИВЭ-50. Монтаж системы видеонаблюдения. Устройство 2-х якорей. Установка пригрузов 2-х комплектов. Монтаж ПМ и трёх облегченных стеллажей. | U5: 11.25 | W5: Работы окончены | X5: Победит Холдинг | AE5: =IFERROR(IF(Хронология[[#This Row],[Забой, м]]-V4<0, 0, Хронология[[#This Row],[Забой, м]]-V4), 0) -> 0 | AF5: =AG4 -> 46145.281 | AG5: =Хронология[[#This Row],[Начало]]+Хронология[[#This Row],[Сутки]] -> 46145.75 | AH5: =Хронология[[#This Row],[Часы]]/24 -> 0.46875 | AI5: =IFERROR(Хронология[[#This Row],[Сутки]]+AI4, Хронология[[#This Row],[Сутки]]) -> 0.91666667 | AJ5: =IF(Хронология[[#This Row],[Этап]]="Доп. работы", "ПВ", IFERROR( IF(AND( MATCH(Хронология[[#This Row],[Ключ]], Планирование[Ключ], 0), Хронология[[#This Row],[Подытог за операцию]] <= INDEX(Планирование[Сутки (план)], MATCH(Хронология[[#This Row],[Ключ]], Планирование[Ключ], 0)) ), "ПВ", "ПНВ"), "НПВ")) -> ПНВ | AK5: =IF( OR(Хронология[[#This Row],[Результат]]="ПВ", Хронология[[#This Row],[Результат]]="ПНВ"), Хронология[[#This Row],[Часы]] - IF( Хронология[[#This Row],[Результат]]="ПНВ", MAX(0, MAX(0, SUMIFS(Хронология[Часы], Хронология[Ключ], Хронология[[#This Row],[Ключ]], Хронология[Начало], "<=" & Хронология[[#This Row],[Начало]]) - IFERROR(INDEX(Планирование[Часы (план)], MATCH(Хронология[[#This Row],[Ключ]], Планирование[Ключ], 0)), 0)) - MAX(0, SUMIFS(Хронология[Часы], Хронология[Ключ], Хронология[[#This Row],[Ключ]], Хронология[Начало], "<" & Хронология[[#This Row],[Начало]]) - IFERROR(INDEX(Планирование[Часы (план)], MATCH(Хронология[[#This Row],[Ключ]], Планирование[Ключ], 0)), 0)) ), 0 ), 0 ) -> 8.09 | AL5: =IF( Хронология[[#This Row],[Результат]]="ПНВ", MAX(0, MAX(0, SUMIFS(Хронология[Часы], Хронология[Ключ], Хронология[[#This Row],[Ключ]], Хронология[Начало], "<=" & Хронология[[#This Row],[Начало]]) - IFERROR(INDEX(Планирование[Часы (план)], MATCH(Хронология[[#This Row],[Ключ]], Планирование[Ключ], 0)), 0)) - MAX(0, SUMIFS(Хронология[Часы], Хронология[Ключ], Хронология[[#This Row],[Ключ]], Хронология[Начало], "<" & Хронология[[#This Row],[Начало]]) - IFERROR(INDEX(Планирование[Часы (план)], MATCH(Хронология[[#This Row],[Ключ]], Планирование[Ключ], 0)), 0)) ), 0 ) -> 3.16 | AM5: =IF(Хронология[[#This Row],[Результат]]="НПВ", Хронология[[#This Row],[Часы]], 0) -> 0 | AN5: =SUMIFS(Хронология[НПВ], Хронология[Скважина], Хронология[[#This Row],[Скважина]], Хронология[Начало], "<=" & Хронология[[#This Row],[Начало]]) -> 0 | AO5: =SUMIFS(Хронология[ПНВ], Хронология[Скважина], Хронология[[#This Row],[Скважина]], Хронология[Начало], "<=" & Хронология[[#This Row],[Начало]]) -> 3.5 | AP5: =INT(ROUND(Хронология[[#This Row],[Начало]], 3)) -> 46145 | AQ5: =Хронология[[#This Row],[Начало]]-INT(Хронология[[#This Row],[Начало]]) -> 0.28125 | AR5: =INT(ROUND(Хронология[[#This Row],[Окончание]], 3)) -> 46145 | AS5: =Хронология[[#This Row],[Окончание]]-INT(Хронология[[#This Row],[Окончание]]) -> 0.75 | AT5: =Хронология[[#This Row],[Мастер]] & CHAR(10) & Хронология[[#This Row],[Помощник мастера]] & CHAR(10) & Хронология[[#This Row],[Бурильщик]] -> Вдовин И.О. Жангазиев С.К. | AU5: =IF(Хронология[[#This Row],[Контекст простоя]]="Штатно", Хронология[[#This Row],[Скважина]] & " " & "ОК–" &Хронология[[#This Row],[ОК]] & " " & Хронология[[#This Row],[Этап]] & " " & Хронология[[#This Row],[Вид работ]] & " " & Хронология[[#This Row],[Объект работ]] & " " & Хронология[[#This Row],[Рейс]], Хронология[[#This Row],[Скважина]] & " " & "ОК–" &Хронология[[#This Row],[ОК]] & " " & Хронология[[#This Row],[Этап]] & " " & Хронология[[#This Row],[Контекст простоя]] & " " & Хронология[[#This Row],[Событие]] & " " & Хронология[[#This Row],[Вид работ]] & " " & Хронология[[#This Row],[Объект работ]] & " " & Хронология[[#This Row],[Рейс]]) -> 6 бис ОК– ПР Монтаж УПА | AV5: =Хронология[[#This Row],[Результат]]&": "&Хронология[[#This Row],[Событие]]& CHAR(10) &Хронология[[#This Row],[Вид работ]]&" "&Хронология[[#This Row],[Объект работ]] -> ПНВ: Монтаж УПА | AW5: =SUMIF($AU$2:AU5, Хронология[[#This Row],[Ключ]], $AH$2:AH5) -> 0.46875 | AX5: =Хронология[[#This Row],[Вид работ]] & " " & Хронология[[#This Row],[Объект работ]] -> Монтаж УПА
A6: ГДТ | B6: КРС | C6: Казанское | D6: 1 | E6: 6 бис | F6: Вдовин И.О. | H6: Жангазиев С.К. | I6: 1 | J6: 0.4 | L6: ПР | M6: Орг_простой | N6: Ожидание разрешения | O6: Вспом_работы | P6: Устранение | Q6: Орг_логист_объекты | R6: Предписания | T6: Запуск бригады КРС пусковой комиссией. | U6: 6 | W6: Работы окончены | X6: Организационные | AE6: =IFERROR(IF(Хронология[[#This Row],[Забой, м]]-V5<0, 0, Хронология[[#This Row],[Забой, м]]-V5), 0) -> 0 | AF6: =AG5 -> 46145.75 | AG6: =Хронология[[#This Row],[Начало]]+Хронология[[#This Row],[Сутки]] -> 46146 | AH6: =Хронология[[#This Row],[Часы]]/24 -> 0.25 | AI6: =IFERROR(Хронология[[#This Row],[Сутки]]+AI5, Хронология[[#This Row],[Сутки]]) -> 1.1666667 | AJ6: =IF(Хронология[[#This Row],[Этап]]="Доп. работы", "ПВ", IFERROR( IF(AND( MATCH(Хронология[[#This Row],[Ключ]], Планирование[Ключ], 0), Хронология[[#This Row],[Подытог за операцию]] <= INDEX(Планирование[Сутки (план)], MATCH(Хронология[[#This Row],[Ключ]], Планирование[Ключ], 0)) ), "ПВ", "ПНВ"), "НПВ")) -> НПВ | AK6: =IF( OR(Хронология[[#This Row],[Результат]]="ПВ", Хронология[[#This Row],[Результат]]="ПНВ"), Хронология[[#This Row],[Часы]] - IF( Хронология[[#This Row],[Результат]]="ПНВ", MAX(0, MAX(0, SUMIFS(Хронология[Часы], Хронология[Ключ], Хронология[[#This Row],[Ключ]], Хронология[Начало], "<=" & Хронология[[#This Row],[Начало]]) - IFERROR(INDEX(Планирование[Часы (план)], MATCH(Хронология[[#This Row],[Ключ]], Планирование[Ключ], 0)), 0)) - MAX(0, SUMIFS(Хронология[Часы], Хронология[Ключ], Хронология[[#This Row],[Ключ]], Хронология[Начало], "<" & Хронология[[#This Row],[Начало]]) - IFERROR(INDEX(Планирование[Часы (план)], MATCH(Хронология[[#This Row],[Ключ]], Планирование[Ключ], 0)), 0)) ), 0 ), 0 ) -> 0 | AL6: =IF( Хронология[[#This Row],[Результат]]="ПНВ", MAX(0, MAX(0, SUMIFS(Хронология[Часы], Хронология[Ключ], Хронология[[#This Row],[Ключ]], Хронология[Начало], "<=" & Хронология[[#This Row],[Начало]]) - IFERROR(INDEX(Планирование[Часы (план)], MATCH(Хронология[[#This Row],[Ключ]], Планирование[Ключ], 0)), 0)) - MAX(0, SUMIFS(Хронология[Часы], Хронология[Ключ], Хронология[[#This Row],[Ключ]], Хронология[Начало], "<" & Хронология[[#This Row],[Начало]]) - IFERROR(INDEX(Планирование[Часы (план)], MATCH(Хронология[[#This Row],[Ключ]], Планирование[Ключ], 0)), 0)) ), 0 ) -> 0 | AM6: =IF(Хронология[[#This Row],[Результат]]="НПВ", Хронология[[#This Row],[Часы]], 0) -> 6 | AN6: =SUMIFS(Хронология[НПВ], Хронология[Скважина], Хронология[[#This Row],[Скважина]], Хронология[Начало], "<=" & Хронология[[#This Row],[Начало]]) -> 6 | AO6: =SUMIFS(Хронология[ПНВ], Хронология[Скважина], Хронология[[#This Row],[Скважина]], Хронология[Начало], "<=" & Хронология[[#This Row],[Начало]]) -> 3.5 | AP6: =INT(ROUND(Хронология[[#This Row],[Начало]], 3)) -> 46145 | AQ6: =Хронология[[#This Row],[Начало]]-INT(Хронология[[#This Row],[Начало]]) -> 0.75 | AR6: =INT(ROUND(Хронология[[#This Row],[Окончание]], 3)) -> 46146 | AS6: =Хронология[[#This Row],[Окончание]]-INT(Хронология[[#This Row],[Окончание]]) -> 0 | AT6: =Хронология[[#This Row],[Мастер]] & CHAR(10) & Хронология[[#This Row],[Помощник мастера]] & CHAR(10) & Хронология[[#This Row],[Бурильщик]] -> Вдовин И.О. Жангазиев С.К. | AU6: =IF(Хронология[[#This Row],[Контекст простоя]]="Штатно", Хронология[[#This Row],[Скважина]] & " " & "ОК–" &Хронология[[#This Row],[ОК]] & " " & Хронология[[#This Row],[Этап]] & " " & Хронология[[#This Row],[Вид работ]] & " " & Хронология[[#This Row],[Объект работ]] & " " & Хронология[[#This Row],[Рейс]], Хронология[[#This Row],[Скважина]] & " " & "ОК–" &Хронология[[#This Row],[ОК]] & " " & Хронология[[#This Row],[Этап]] & " " & Хронология[[#This Row],[Контекст простоя]] & " " & Хронология[[#This Row],[Событие]] & " " & Хронология[[#This Row],[Вид работ]] & " " & Хронология[[#This Row],[Объект работ]] & " " & Хронология[[#This Row],[Рейс]]) -> 6 бис ОК– ПР Орг_простой Ожидание разрешения Устранение Предписания | AV6: =Хронология[[#This Row],[Результат]]&": "&Хронология[[#This Row],[Событие]]& CHAR(10) &Хронология[[#This Row],[Вид работ]]&" "&Хронология[[#This Row],[Объект работ]] -> НПВ: Ожидание разрешения Устранение Предписания | AW6: =SUMIF($AU$2:AU6, Хронология[[#This Row],[Ключ]], $AH$2:AH6) -> 0.25 | AX6: =Хронология[[#This Row],[Вид работ]] & " " & Хронология[[#This Row],[Объект работ]] -> Устранение Предписания
A7: ГДТ | B7: КРС | C7: Казанское | D7: 1 | E7: 6 бис | F7: Жабин П.П. | H7: Керимов Н.К. | L7: ПР | M7: Орг_простой | N7: Ожидание разрешения | O7: Вспом_работы | P7: Устранение | Q7: Орг_логист_объекты | R7: Предписания | U7: 3 | W7: Работы окончены | X7: Организационные | AE7: =IFERROR(IF(Хронология[[#This Row],[Забой, м]]-V6<0, 0, Хронология[[#This Row],[Забой, м]]-V6), 0) -> 0 | AF7: =AG6 -> 46146 | AG7: =Хронология[[#This Row],[Начало]]+Хронология[[#This Row],[Сутки]] -> 46146.125 | AH7: =Хронология[[#This Row],[Часы]]/24 -> 0.125 | AI7: =IFERROR(Хронология[[#This Row],[Сутки]]+AI6, Хронология[[#This Row],[Сутки]]) -> 1.2916667 | AJ7: =IF(Хронология[[#This Row],[Этап]]="Доп. работы", "ПВ", IFERROR( IF(AND( MATCH(Хронология[[#This Row],[Ключ]], Планирование[Ключ], 0), Хронология[[#This Row],[Подытог за операцию]] <= INDEX(Планирование[Сутки (план)], MATCH(Хронология[[#This Row],[Ключ]], Планирование[Ключ], 0)) ), "ПВ", "ПНВ"), "НПВ")) -> НПВ | AK7: =IF( OR(Хронология[[#This Row],[Результат]]="ПВ", Хронология[[#This Row],[Результат]]="ПНВ"), Хронология[[#This Row],[Часы]] - IF( Хронология[[#This Row],[Результат]]="ПНВ", MAX(0, MAX(0, SUMIFS(Хронология[Часы], Хронология[Ключ], Хронология[[#This Row],[Ключ]], Хронология[Начало], "<=" & Хронология[[#This Row],[Начало]]) - IFERROR(INDEX(Планирование[Часы (план)], MATCH(Хронология[[#This Row],[Ключ]], Планирование[Ключ], 0)), 0)) - MAX(0, SUMIFS(Хронология[Часы], Хронология[Ключ], Хронология[[#This Row],[Ключ]], Хронология[Начало], "<" & Хронология[[#This Row],[Начало]]) - IFERROR(INDEX(Планирование[Часы (план)], MATCH(Хронология[[#This Row],[Ключ]], Планирование[Ключ], 0)), 0)) ), 0 ), 0 ) -> 0 | AL7: =IF( Хронология[[#This Row],[Результат]]="ПНВ", MAX(0, MAX(0, SUMIFS(Хронология[Часы], Хронология[Ключ], Хронология[[#This Row],[Ключ]], Хронология[Начало], "<=" & Хронология[[#This Row],[Начало]]) - IFERROR(INDEX(Планирование[Часы (план)], MATCH(Хронология[[#This Row],[Ключ]], Планирование[Ключ], 0)), 0)) - MAX(0, SUMIFS(Хронология[Часы], Хронология[Ключ], Хронология[[#This Row],[Ключ]], Хронология[Начало], "<" & Хронология[[#This Row],[Начало]]) - IFERROR(INDEX(Планирование[Часы (план)], MATCH(Хронология[[#This Row],[Ключ]], Планирование[Ключ], 0)), 0)) ), 0 ) -> 0 | AM7: =IF(Хронология[[#This Row],[Результат]]="НПВ", Хронология[[#This Row],[Часы]], 0) -> 3 | AN7: =SUMIFS(Хронология[НПВ], Хронология[Скважина], Хронология[[#This Row],[Скважина]], Хронология[Начало], "<=" & Хронология[[#This Row],[Начало]]) -> 9 | AO7: =SUMIFS(Хронология[ПНВ], Хронология[Скважина], Хронология[[#This Row],[Скважина]], Хронология[Начало], "<=" & Хронология[[#This Row],[Начало]]) -> 3.5 | AP7: =INT(ROUND(Хронология[[#This Row],[Начало]], 3)) -> 46146 | AQ7: =Хронология[[#This Row],[Начало]]-INT(Хронология[[#This Row],[Начало]]) -> 0 | AR7: =INT(ROUND(Хронология[[#This Row],[Окончание]], 3)) -> 46146 | AS7: =Хронология[[#This Row],[Окончание]]-INT(Хронология[[#This Row],[Окончание]]) -> 0.125 | AT7: =Хронология[[#This Row],[Мастер]] & CHAR(10) & Хронология[[#This Row],[Помощник мастера]] & CHAR(10) & Хронология[[#This Row],[Бурильщик]] -> Жабин П.П. Керимов Н.К. | AU7: =IF(Хронология[[#This Row],[Контекст простоя]]="Штатно", Хронология[[#This Row],[Скважина]] & " " & "ОК–" &Хронология[[#This Row],[ОК]] & " " & Хронология[[#This Row],[Этап]] & " " & Хронология[[#This Row],[Вид работ]] & " " & Хронология[[#This Row],[Объект работ]] & " " & Хронология[[#This Row],[Рейс]], Хронология[[#This Row],[Скважина]] & " " & "ОК–" &Хронология[[#This Row],[ОК]] & " " & Хронология[[#This Row],[Этап]] & " " & Хронология[[#This Row],[Контекст простоя]] & " " & Хронология[[#This Row],[Событие]] & " " & Хронология[[#This Row],[Вид работ]] & " " & Хронология[[#This Row],[Объект работ]] & " " & Хронология[[#This Row],[Рейс]]) -> 6 бис ОК– ПР Орг_простой Ожидание разрешения Устранение Предписания | AV7: =Хронология[[#This Row],[Результат]]&": "&Хронология[[#This Row],[Событие]]& CHAR(10) &Хронология[[#This Row],[Вид работ]]&" "&Хронология[[#This Row],[Объект работ]] -> НПВ: Ожидание разрешения Устранение Предписания | AW7: =SUMIF($AU$2:AU7, Хронология[[#This Row],[Ключ]], $AH$2:AH7) -> 0.375 | AX7: =Хронология[[#This Row],[Вид работ]] & " " & Хронология[[#This Row],[Объект работ]] -> Устранение Предписания
A8: ГДТ | B8: КРС | C8: Казанское | D8: 1 | E8: 6 бис | F8: Жабин П.П. | H8: Керимов Н.К. | I8: 1 | J8: 0.5 | L8: КРС | M8: Штатно | O8: Монтаж_демонтаж_установка | P8: Срыв | Q8: Объекты_устье | R8: Планшайба | T8: Подрыв ПШ (вес при подрыве ПШ 8,9тн). Разделка кабельного ввода. Протаскивание кабеля через КВ (L≈50м). Демонтаж КВ, ПШ. | U8: 5 | W8: Работы окончены | X8: Победит Холдинг | AE8: =IFERROR(IF(Хронология[[#This Row],[Забой, м]]-V7<0, 0, Хронология[[#This Row],[Забой, м]]-V7), 0) -> 0 | AF8: =AG7 -> 46146.125 | AG8: =Хронология[[#This Row],[Начало]]+Хронология[[#This Row],[Сутки]] -> 46146.333 | AH8: =Хронология[[#This Row],[Часы]]/24 -> 0.20833333 | AI8: =IFERROR(Хронология[[#This Row],[Сутки]]+AI7, Хронология[[#This Row],[Сутки]]) -> 1.5 | AJ8: =IF(Хронология[[#This Row],[Этап]]="Доп. работы", "ПВ", IFERROR( IF(AND( MATCH(Хронология[[#This Row],[Ключ]], Планирование[Ключ], 0), Хронология[[#This Row],[Подытог за операцию]] <= INDEX(Планирование[Сутки (план)], MATCH(Хронология[[#This Row],[Ключ]], Планирование[Ключ], 0)) ), "ПВ", "ПНВ"), "НПВ")) -> ПНВ | AK8: =IF( OR(Хронология[[#This Row],[Результат]]="ПВ", Хронология[[#This Row],[Результат]]="ПНВ"), Хронология[[#This Row],[Часы]] - IF( Хронология[[#This Row],[Результат]]="ПНВ", MAX(0, MAX(0, SUMIFS(Хронология[Часы], Хронология[Ключ], Хронология[[#This Row],[Ключ]], Хронология[Начало], "<=" & Хронология[[#This Row],[Начало]]) - IFERROR(INDEX(Планирование[Часы (план)], MATCH(Хронология[[#This Row],[Ключ]], Планирование[Ключ], 0)), 0)) - MAX(0, SUMIFS(Хронология[Часы], Хронология[Ключ], Хронология[[#This Row],[Ключ]], Хронология[Начало], "<" & Хронология[[#This Row],[Начало]]) - IFERROR(INDEX(Планирование[Часы (план)], MATCH(Хронология[[#This Row],[Ключ]], Планирование[Ключ], 0)), 0)) ), 0 ), 0 ) -> 1.48 | AL8: =IF( Хронология[[#This Row],[Результат]]="ПНВ", MAX(0, MAX(0, SUMIFS(Хронология[Часы], Хронология[Ключ], Хронология[[#This Row],[Ключ]], Хронология[Начало], "<=" & Хронология[[#This Row],[Начало]]) - IFERROR(INDEX(Планирование[Часы (план)], MATCH(Хронология[[#This Row],[Ключ]], Планирование[Ключ], 0)), 0)) - MAX(0, SUMIFS(Хронология[Часы], Хронология[Ключ], Хронология[[#This Row],[Ключ]], Хронология[Начало], "<" & Хронология[[#This Row],[Начало]]) - IFERROR(INDEX(Планирование[Часы (план)], MATCH(Хронология[[#This Row],[Ключ]], Планирование[Ключ], 0)), 0)) ), 0 ) -> 3.52 | AM8: =IF(Хронология[[#This Row],[Результат]]="НПВ", Хронология[[#This Row],[Часы]], 0) -> 0 | AN8: =SUMIFS(Хронология[НПВ], Хронология[Скважина], Хронология[[#This Row],[Скважина]], Хронология[Начало], "<=" & Хронология[[#This Row],[Начало]]) -> 9 | AO8: =SUMIFS(Хронология[ПНВ], Хронология[Скважина], Хронология[[#This Row],[Скважина]], Хронология[Начало], "<=" & Хронология[[#This Row],[Начало]]) -> 7.02 | AP8: =INT(ROUND(Хронология[[#This Row],[Начало]], 3)) -> 46146 | AQ8: =Хронология[[#This Row],[Начало]]-INT(Хронология[[#This Row],[Начало]]) -> 0.125 | AR8: =INT(ROUND(Хронология[[#This Row],[Окончание]], 3)) -> 46146 | AS8: =Хронология[[#This Row],[Окончание]]-INT(Хронология[[#This Row],[Окончание]]) -> 0.33333333 | AT8: =Хронология[[#This Row],[Мастер]] & CHAR(10) & Хронология[[#This Row],[Помощник мастера]] & CHAR(10) & Хронология[[#This Row],[Бурильщик]] -> Жабин П.П. Керимов Н.К. | AU8: =IF(Хронология[[#This Row],[Контекст простоя]]="Штатно", Хронология[[#This Row],[Скважина]] & " " & "ОК–" &Хронология[[#This Row],[ОК]] & " " & Хронология[[#This Row],[Этап]] & " " & Хронология[[#This Row],[Вид работ]] & " " & Хронология[[#This Row],[Объект работ]] & " " & Хронология[[#This Row],[Рейс]], Хронология[[#This Row],[Скважина]] & " " & "ОК–" &Хронология[[#This Row],[ОК]] & " " & Хронология[[#This Row],[Этап]] & " " & Хронология[[#This Row],[Контекст простоя]] & " " & Хронология[[#This Row],[Событие]] & " " & Хронология[[#This Row],[Вид работ]] & " " & Хронология[[#This Row],[Объект работ]] & " " & Хронология[[#This Row],[Рейс]]) -> 6 бис ОК– КРС Срыв Планшайба | AV8: =Хронология[[#This Row],[Результат]]&": "&Хронология[[#This Row],[Событие]]& CHAR(10) &Хронология[[#This Row],[Вид работ]]&" "&Хронология[[#This Row],[Объект работ]] -> ПНВ: Срыв Планшайба | AW8: =SUMIF($AU$2:AU8, Хронология[[#This Row],[Ключ]], $AH$2:AH8) -> 0.20833333 | AX8: =Хронология[[#This Row],[Вид работ]] & " " & Хронология[[#This Row],[Объект работ]] -> Срыв Планшайба
A9: ГДТ | B9: КРС | C9: Казанское | D9: 1 | E9: 6 бис | F9: Вдовин И.О. | H9: Жангазиев С.К. | I9: 1 | J9: 0.6 | L9: КРС | M9: Штатно | O9: СПО | P9: Подъем | Q9: Технологический_инструмент | R9: УЭЦН | T9: Комиссионный подъём 10.1ЭЦНМИК8 - 2000-350 с глубины 400,69 м. (39шт) на НКТП-114мм.Подъём НКТП-114мм осуществлять в соответствии с регламентом «По учёту и эксплуатации иа со сно- комп рессорных труб в АО «Газпром добыча Томск». | U9: 7.5 | W9: Работы окончены | X9: Победит Холдинг | AE9: =IFERROR(IF(Хронология[[#This Row],[Забой, м]]-V8<0, 0, Хронология[[#This Row],[Забой, м]]-V8), 0) -> 0 | AF9: =AG8 -> 46146.333 | AG9: =Хронология[[#This Row],[Начало]]+Хронология[[#This Row],[Сутки]] -> 46146.646 | AH9: =Хронология[[#This Row],[Часы]]/24 -> 0.3125 | AI9: =IFERROR(Хронология[[#This Row],[Сутки]]+AI8, Хронология[[#This Row],[Сутки]]) -> 1.8125 | AJ9: =IF(Хронология[[#This Row],[Этап]]="Доп. работы", "ПВ", IFERROR( IF(AND( MATCH(Хронология[[#This Row],[Ключ]], Планирование[Ключ], 0), Хронология[[#This Row],[Подытог за операцию]] <= INDEX(Планирование[Сутки (план)], MATCH(Хронология[[#This Row],[Ключ]], Планирование[Ключ], 0)) ), "ПВ", "ПНВ"), "НПВ")) -> ПНВ | AK9: =IF( OR(Хронология[[#This Row],[Результат]]="ПВ", Хронология[[#This Row],[Результат]]="ПНВ"), Хронология[[#This Row],[Часы]] - IF( Хронология[[#This Row],[Результат]]="ПНВ", MAX(0, MAX(0, SUMIFS(Хронология[Часы], Хронология[Ключ], Хронология[[#This Row],[Ключ]], Хронология[Начало], "<=" & Хронология[[#This Row],[Начало]]) - IFERROR(INDEX(Планирование[Часы (план)], MATCH(Хронология[[#This Row],[Ключ]], Планирование[Ключ], 0)), 0)) - MAX(0, SUMIFS(Хронология[Часы], Хронология[Ключ], Хронология[[#This Row],[Ключ]], Хронология[Начало], "<" & Хронология[[#This Row],[Начало]]) - IFERROR(INDEX(Планирование[Часы (план)], MATCH(Хронология[[#This Row],[Ключ]], Планирование[Ключ], 0)), 0)) ), 0 ), 0 ) -> 3.46 | AL9: =IF( Хронология[[#This Row],[Результат]]="ПНВ", MAX(0, MAX(0, SUMIFS(Хронология[Часы], Хронология[Ключ], Хронология[[#This Row],[Ключ]], Хронология[Начало], "<=" & Хронология[[#This Row],[Начало]]) - IFERROR(INDEX(Планирование[Часы (план)], MATCH(Хронология[[#This Row],[Ключ]], Планирование[Ключ], 0)), 0)) - MAX(0, SUMIFS(Хронология[Часы], Хронология[Ключ], Хронология[[#This Row],[Ключ]], Хронология[Начало], "<" & Хронология[[#This Row],[Начало]]) - IFERROR(INDEX(Планирование[Часы (план)], MATCH(Хронология[[#This Row],[Ключ]], Планирование[Ключ], 0)), 0)) ), 0 ) -> 4.04 | AM9: =IF(Хронология[[#This Row],[Результат]]="НПВ", Хронология[[#This Row],[Часы]], 0) -> 0 | AN9: =SUMIFS(Хронология[НПВ], Хронология[Скважина], Хронология[[#This Row],[Скважина]], Хронология[Начало], "<=" & Хронология[[#This Row],[Начало]]) -> 9 | AO9: =SUMIFS(Хронология[ПНВ], Хронология[Скважина], Хронология[[#This Row],[Скважина]], Хронология[Начало], "<=" & Хронология[[#This Row],[Начало]]) -> 11.06 | AP9: =INT(ROUND(Хронология[[#This Row],[Начало]], 3)) -> 46146 | AQ9: =Хронология[[#This Row],[Начало]]-INT(Хронология[[#This Row],[Начало]]) -> 0.33333333 | AR9: =INT(ROUND(Хронология[[#This Row],[Окончание]], 3)) -> 46146 | AS9: =Хронология[[#This Row],[Окончание]]-INT(Хронология[[#This Row],[Окончание]]) -> 0.64583333 | AT9: =Хронология[[#This Row],[Мастер]] & CHAR(10) & Хронология[[#This Row],[Помощник мастера]] & CHAR(10) & Хронология[[#This Row],[Бурильщик]] -> Вдовин И.О. Жангазиев С.К. | AU9: =IF(Хронология[[#This Row],[Контекст простоя]]="Штатно", Хронология[[#This Row],[Скважина]] & " " & "ОК–" &Хронология[[#This Row],[ОК]] & " " & Хронология[[#This Row],[Этап]] & " " & Хронология[[#This Row],[Вид работ]] & " " & Хронология[[#This Row],[Объект работ]] & " " & Хронология[[#This Row],[Рейс]], Хронология[[#This Row],[Скважина]] & " " & "ОК–" &Хронология[[#This Row],[ОК]] & " " & Хронология[[#This Row],[Этап]] & " " & Хронология[[#This Row],[Контекст простоя]] & " " & Хронология[[#This Row],[Событие]] & " " & Хронология[[#This Row],[Вид работ]] & " " & Хронология[[#This Row],[Объект работ]] & " " & Хронология[[#This Row],[Рейс]]) -> 6 бис ОК– КРС Подъем УЭЦН | AV9: =Хронология[[#This Row],[Результат]]&": "&Хронология[[#This Row],[Событие]]& CHAR(10) &Хронология[[#This Row],[Вид работ]]&" "&Хронология[[#This Row],[Объект работ]] -> ПНВ: Подъем УЭЦН | AW9: =SUMIF($AU$2:AU9, Хронология[[#This Row],[Ключ]], $AH$2:AH9) -> 0.3125 | AX9: =Хронология[[#This Row],[Вид работ]] & " " & Хронология[[#This Row],[Объект работ]] -> Подъем УЭЦН
A10: ГДТ | B10: КРС | C10: Казанское | D10: 1 | E10: 6 бис | F10: Вдовин И.О. | H10: Жангазиев С.К. | L10: КРС | M10: Штатно | O10: Сборка_разборка_оснащение | P10: Разборка | Q10: Технологический_инструмент | R10: УЭЦН | T10: демонтаж 10.1ЭЦНМИК8 - 2000-350 (1 секция) согласно регламента "По взаимодействию структурных подразделений внутри АО "Газпром добыча Томск" и сервисных (подрядных) организаций при работе с электропогружным оборудованием. | U10: 2.5 | W10: Работы окончены | AE10: =IFERROR(IF(Хронология[[#This Row],[Забой, м]]-V9<0, 0, Хронология[[#This Row],[Забой, м]]-V9), 0) -> 0 | AF10: =AG9 -> 46146.646 | AG10: =Хронология[[#This Row],[Начало]]+Хронология[[#This Row],[Сутки]] -> 46146.75 | AH10: =Хронология[[#This Row],[Часы]]/24 -> 0.10416667 | AI10: =IFERROR(Хронология[[#This Row],[Сутки]]+AI9, Хронология[[#This Row],[Сутки]]) -> 1.9166667 | AJ10: =IF(Хронология[[#This Row],[Этап]]="Доп. работы", "ПВ", IFERROR( IF(AND( MATCH(Хронология[[#This Row],[Ключ]], Планирование[Ключ], 0), Хронология[[#This Row],[Подытог за операцию]] <= INDEX(Планирование[Сутки (план)], MATCH(Хронология[[#This Row],[Ключ]], Планирование[Ключ], 0)) ), "ПВ", "ПНВ"), "НПВ")) -> ПВ | AK10: =IF( OR(Хронология[[#This Row],[Результат]]="ПВ", Хронология[[#This Row],[Результат]]="ПНВ"), Хронология[[#This Row],[Часы]] - IF( Хронология[[#This Row],[Результат]]="ПНВ", MAX(0, MAX(0, SUMIFS(Хронология[Часы], Хронология[Ключ], Хронология[[#This Row],[Ключ]], Хронология[Начало], "<=" & Хронология[[#This Row],[Начало]]) - IFERROR(INDEX(Планирование[Часы (план)], MATCH(Хронология[[#This Row],[Ключ]], Планирование[Ключ], 0)), 0)) - MAX(0, SUMIFS(Хронология[Часы], Хронология[Ключ], Хронология[[#This Row],[Ключ]], Хронология[Начало], "<" & Хронология[[#This Row],[Начало]]) - IFERROR(INDEX(Планирование[Часы (план)], MATCH(Хронология[[#This Row],[Ключ]], Планирование[Ключ], 0)), 0)) ), 0 ), 0 ) -> 2.5 | AL10: =IF( Хронология[[#This Row],[Результат]]="ПНВ", MAX(0, MAX(0, SUMIFS(Хронология[Часы], Хронология[Ключ], Хронология[[#This Row],[Ключ]], Хронология[Начало], "<=" & Хронология[[#This Row],[Начало]]) - IFERROR(INDEX(Планирование[Часы (план)], MATCH(Хронология[[#This Row],[Ключ]], Планирование[Ключ], 0)), 0)) - MAX(0, SUMIFS(Хронология[Часы], Хронология[Ключ], Хронология[[#This Row],[Ключ]], Хронология[Начало], "<" & Хронология[[#This Row],[Начало]]) - IFERROR(INDEX(Планирование[Часы (план)], MATCH(Хронология[[#This Row],[Ключ]], Планирование[Ключ], 0)), 0)) ), 0 ) -> 0 | AM10: =IF(Хронология[[#This Row],[Результат]]="НПВ", Хронология[[#This Row],[Часы]], 0) -> 0 | AN10: =SUMIFS(Хронология[НПВ], Хронология[Скважина], Хронология[[#This Row],[Скважина]], Хронология[Начало], "<=" & Хронология[[#This Row],[Начало]]) -> 9 | AO10: =SUMIFS(Хронология[ПНВ], Хронология[Скважина], Хронология[[#This Row],[Скважина]], Хронология[Начало], "<=" & Хронология[[#This Row],[Начало]]) -> 11.06 | AP10: =INT(ROUND(Хронология[[#This Row],[Начало]], 3)) -> 46146 | AQ10: =Хронология[[#This Row],[Начало]]-INT(Хронология[[#This Row],[Начало]]) -> 0.64583333 | AR10: =INT(ROUND(Хронология[[#This Row],[Окончание]], 3)) -> 46146 | AS10: =Хронология[[#This Row],[Окончание]]-INT(Хронология[[#This Row],[Окончание]]) -> 0.75 | AT10: =Хронология[[#This Row],[Мастер]] & CHAR(10) & Хронология[[#This Row],[Помощник мастера]] & CHAR(10) & Хронология[[#This Row],[Бурильщик]] -> Вдовин И.О. Жангазиев С.К. | AU10: =IF(Хронология[[#This Row],[Контекст простоя]]="Штатно", Хронология[[#This Row],[Скважина]] & " " & "ОК–" &Хронология[[#This Row],[ОК]] & " " & Хронология[[#This Row],[Этап]] & " " & Хронология[[#This Row],[Вид работ]] & " " & Хронология[[#This Row],[Объект работ]] & " " & Хронология[[#This Row],[Рейс]], Хронология[[#This Row],[Скважина]] & " " & "ОК–" &Хронология[[#This Row],[ОК]] & " " & Хронология[[#This Row],[Этап]] & " " & Хронология[[#This Row],[Контекст простоя]] & " " & Хронология[[#This Row],[Событие]] & " " & Хронология[[#This Row],[Вид работ]] & " " & Хронология[[#This Row],[Объект работ]] & " " & Хронология[[#This Row],[Рейс]]) -> 6 бис ОК– КРС Разборка УЭЦН | AV10: =Хронология[[#This Row],[Результат]]&": "&Хронология[[#This Row],[Событие]]& CHAR(10) &Хронология[[#This Row],[Вид работ]]&" "&Хронология[[#This Row],[Объект работ]] -> ПВ: Разборка УЭЦН | AW10: =SUMIF($AU$2:AU10, Хронология[[#This Row],[Ключ]], $AH$2:AH10) -> 0.10416667 | AX10: =Хронология[[#This Row],[Вид работ]] & " " & Хронология[[#This Row],[Объект работ]] -> Разборка УЭЦН
A11: ГДТ | B11: КРС | C11: Казанское | D11: 1 | E11: 6 бис | F11: Вдовин И.О. | H11: Жангазиев С.К. | L11: ГИС | M11: Штатно | O11: ГИС | P11: ГИС | Q11: Объекты_ГИС | R11: АКЦ-прибор | T11: ГФР: спуск прибора для записи АКЦ, ГФР: спуск прибора для записи АКЦ Силами ООО "Газпром недра" ПФ "Красноярскгазгеофизика в интервале от устья до текущего забоя (1448,6м). | U11: 6 | W11: Работы окончены | AE11: =IFERROR(IF(Хронология[[#This Row],[Забой, м]]-V10<0, 0, Хронология[[#This Row],[Забой, м]]-V10), 0) -> 0 | AF11: =AG10 -> 46146.75 | AG11: =Хронология[[#This Row],[Начало]]+Хронология[[#This Row],[Сутки]] -> 46147 | AH11: =Хронология[[#This Row],[Часы]]/24 -> 0.25 | AI11: =IFERROR(Хронология[[#This Row],[Сутки]]+AI10, Хронология[[#This Row],[Сутки]]) -> 2.1666667 | AJ11: =IF(Хронология[[#This Row],[Этап]]="Доп. работы", "ПВ", IFERROR( IF(AND( MATCH(Хронология[[#This Row],[Ключ]], Планирование[Ключ], 0), Хронология[[#This Row],[Подытог за операцию]] <= INDEX(Планирование[Сутки (план)], MATCH(Хронология[[#This Row],[Ключ]], Планирование[Ключ], 0)) ), "ПВ", "ПНВ"), "НПВ")) -> ПВ | AK11: =IF( OR(Хронология[[#This Row],[Результат]]="ПВ", Хронология[[#This Row],[Результат]]="ПНВ"), Хронология[[#This Row],[Часы]] - IF( Хронология[[#This Row],[Результат]]="ПНВ", MAX(0, MAX(0, SUMIFS(Хронология[Часы], Хронология[Ключ], Хронология[[#This Row],[Ключ]], Хронология[Начало], "<=" & Хронология[[#This Row],[Начало]]) - IFERROR(INDEX(Планирование[Часы (план)], MATCH(Хронология[[#This Row],[Ключ]], Планирование[Ключ], 0)), 0)) - MAX(0, SUMIFS(Хронология[Часы], Хронология[Ключ], Хронология[[#This Row],[Ключ]], Хронология[Начало], "<" & Хронология[[#This Row],[Начало]]) - IFERROR(INDEX(Планирование[Часы (план)], MATCH(Хронология[[#This Row],[Ключ]], Планирование[Ключ], 0)), 0)) ), 0 ), 0 ) -> 6 | AL11: =IF( Хронология[[#This Row],[Результат]]="ПНВ", MAX(0, MAX(0, SUMIFS(Хронология[Часы], Хронология[Ключ], Хронология[[#This Row],[Ключ]], Хронология[Начало], "<=" & Хронология[[#This Row],[Начало]]) - IFERROR(INDEX(Планирование[Часы (план)], MATCH(Хронология[[#This Row],[Ключ]], Планирование[Ключ], 0)), 0)) - MAX(0, SUMIFS(Хронология[Часы], Хронология[Ключ], Хронология[[#This Row],[Ключ]], Хронология[Начало], "<" & Хронология[[#This Row],[Начало]]) - IFERROR(INDEX(Планирование[Часы (план)], MATCH(Хронология[[#This Row],[Ключ]], Планирование[Ключ], 0)), 0)) ), 0 ) -> 0 | AM11: =IF(Хронология[[#This Row],[Результат]]="НПВ", Хронология[[#This Row],[Часы]], 0) -> 0 | AN11: =SUMIFS(Хронология[НПВ], Хронология[Скважина], Хронология[[#This Row],[Скважина]], Хронология[Начало], "<=" & Хронология[[#This Row],[Начало]]) -> 9 | AO11: =SUMIFS(Хронология[ПНВ], Хронология[Скважина], Хронология[[#This Row],[Скважина]], Хронология[Начало], "<=" & Хронология[[#This Row],[Начало]]) -> 11.06 | AP11: =INT(ROUND(Хронология[[#This Row],[Начало]], 3)) -> 46146 | AQ11: =Хронология[[#This Row],[Начало]]-INT(Хронология[[#This Row],[Начало]]) -> 0.75 | AR11: =INT(ROUND(Хронология[[#This Row],[Окончание]], 3)) -> 46147 | AS11: =Хронология[[#This Row],[Окончание]]-INT(Хронология[[#This Row],[Окончание]]) -> 0 | AT11: =Хронология[[#This Row],[Мастер]] & CHAR(10) & Хронология[[#This Row],[Помощник мастера]] & CHAR(10) & Хронология[[#This Row],[Бурильщик]] -> Вдовин И.О. Жангазиев С.К. | AU11: =IF(Хронология[[#This Row],[Контекст простоя]]="Штатно", Хронология[[#This Row],[Скважина]] & " " & "ОК–" &Хронология[[#This Row],[ОК]] & " " & Хронология[[#This Row],[Этап]] & " " & Хронология[[#This Row],[Вид работ]] & " " & Хронология[[#This Row],[Объект работ]] & " " & Хронология[[#This Row],[Рейс]], Хронология[[#This Row],[Скважина]] & " " & "ОК–" &Хронология[[#This Row],[ОК]] & " " & Хронология[[#This Row],[Этап]] & " " & Хронология[[#This Row],[Контекст простоя]] & " " & Хронология[[#This Row],[Событие]] & " " & Хронология[[#This Row],[Вид работ]] & " " & Хронология[[#This Row],[Объект работ]] & " " & Хронология[[#This Row],[Рейс]]) -> 6 бис ОК– ГИС ГИС АКЦ-прибор | AV11: =Хронология[[#This Row],[Результат]]&": "&Хронология[[#This Row],[Событие]]& CHAR(10) &Хронология[[#This Row],[Вид работ]]&" "&Хронология[[#This Row],[Объект работ]] -> ПВ: ГИС АКЦ-прибор | AW11: =SUMIF($AU$2:AU11, Хронология[[#This Row],[Ключ]], $AH$2:AH11) -> 0.25 | AX11: =Хронология[[#This Row],[Вид работ]] & " " & Хронология[[#This Row],[Объект работ]] -> ГИС АКЦ-прибор
A12: ГДТ | B12: КРС | C12: Казанское | D12: 1 | E12: 6 бис | F12: Жабин П.П. | H12: Керимов Н.К. | L12: ГИС | M12: Штатно | O12: ГИС | P12: ГИС | Q12: Объекты_ГИС | R12: АКЦ-прибор | U12: 6 | AE12: =IFERROR(IF(Хронология[[#This Row],[Забой, м]]-V11<0, 0, Хронология[[#This Row],[Забой, м]]-V11), 0) -> 0 | AF12: =AG11 -> 46147 | AG12: =Хронология[[#This Row],[Начало]]+Хронология[[#This Row],[Сутки]] -> 46147.25 | AH12: =Хронология[[#This Row],[Часы]]/24 -> 0.25 | AI12: =IFERROR(Хронология[[#This Row],[Сутки]]+AI11, Хронология[[#This Row],[Сутки]]) -> 2.4166667 | AJ12: =IF(Хронология[[#This Row],[Этап]]="Доп. работы", "ПВ", IFERROR( IF(AND( MATCH(Хронология[[#This Row],[Ключ]], Планирование[Ключ], 0), Хронология[[#This Row],[Подытог за операцию]] <= INDEX(Планирование[Сутки (план)], MATCH(Хронология[[#This Row],[Ключ]], Планирование[Ключ], 0)) ), "ПВ", "ПНВ"), "НПВ")) -> ПВ | AK12: =IF( OR(Хронология[[#This Row],[Результат]]="ПВ", Хронология[[#This Row],[Результат]]="ПНВ"), Хронология[[#This Row],[Часы]] - IF( Хронология[[#This Row],[Результат]]="ПНВ", MAX(0, MAX(0, SUMIFS(Хронология[Часы], Хронология[Ключ], Хронология[[#This Row],[Ключ]], Хронология[Начало], "<=" & Хронология[[#This Row],[Начало]]) - IFERROR(INDEX(Планирование[Часы (план)], MATCH(Хронология[[#This Row],[Ключ]], Планирование[Ключ], 0)), 0)) - MAX(0, SUMIFS(Хронология[Часы], Хронология[Ключ], Хронология[[#This Row],[Ключ]], Хронология[Начало], "<" & Хронология[[#This Row],[Начало]]) - IFERROR(INDEX(Планирование[Часы (план)], MATCH(Хронология[[#This Row],[Ключ]], Планирование[Ключ], 0)), 0)) ), 0 ), 0 ) -> 6 | AL12: =IF( Хронология[[#This Row],[Результат]]="ПНВ", MAX(0, MAX(0, SUMIFS(Хронология[Часы], Хронология[Ключ], Хронология[[#This Row],[Ключ]], Хронология[Начало], "<=" & Хронология[[#This Row],[Начало]]) - IFERROR(INDEX(Планирование[Часы (план)], MATCH(Хронология[[#This Row],[Ключ]], Планирование[Ключ], 0)), 0)) - MAX(0, SUMIFS(Хронология[Часы], Хронология[Ключ], Хронология[[#This Row],[Ключ]], Хронология[Начало], "<" & Хронология[[#This Row],[Начало]]) - IFERROR(INDEX(Планирование[Часы (план)], MATCH(Хронология[[#This Row],[Ключ]], Планирование[Ключ], 0)), 0)) ), 0 ) -> 0 | AM12: =IF(Хронология[[#This Row],[Результат]]="НПВ", Хронология[[#This Row],[Часы]], 0) -> 0 | AN12: =SUMIFS(Хронология[НПВ], Хронология[Скважина], Хронология[[#This Row],[Скважина]], Хронология[Начало], "<=" & Хронология[[#This Row],[Начало]]) -> 9 | AO12: =SUMIFS(Хронология[ПНВ], Хронология[Скважина], Хронология[[#This Row],[Скважина]], Хронология[Начало], "<=" & Хронология[[#This Row],[Начало]]) -> 11.06 | AP12: =INT(ROUND(Хронология[[#This Row],[Начало]], 3)) -> 46147 | AQ12: =Хронология[[#This Row],[Начало]]-INT(Хронология[[#This Row],[Начало]]) -> 0 | AR12: =INT(ROUND(Хронология[[#This Row],[Окончание]], 3)) -> 46147 | AS12: =Хронология[[#This Row],[Окончание]]-INT(Хронология[[#This Row],[Окончание]]) -> 0.25 | AT12: =Хронология[[#This Row],[Мастер]] & CHAR(10) & Хронология[[#This Row],[Помощник мастера]] & CHAR(10) & Хронология[[#This Row],[Бурильщик]] -> Жабин П.П. Керимов Н.К. | AU12: =IF(Хронология[[#This Row],[Контекст простоя]]="Штатно", Хронология[[#This Row],[Скважина]] & " " & "ОК–" &Хронология[[#This Row],[ОК]] & " " & Хронология[[#This Row],[Этап]] & " " & Хронология[[#This Row],[Вид работ]] & " " & Хронология[[#This Row],[Объект работ]] & " " & Хронология[[#This Row],[Рейс]], Хронология[[#This Row],[Скважина]] & " " & "ОК–" &Хронология[[#This Row],[ОК]] & " " & Хронология[[#This Row],[Этап]] & " " & Хронология[[#This Row],[Контекст простоя]] & " " & Хронология[[#This Row],[Событие]] & " " & Хронология[[#This Row],[Вид работ]] & " " & Хронология[[#This Row],[Объект работ]] & " " & Хронология[[#This Row],[Рейс]]) -> 6 бис ОК– ГИС ГИС АКЦ-прибор | AV12: =Хронология[[#This Row],[Результат]]&": "&Хронология[[#This Row],[Событие]]& CHAR(10) &Хронология[[#This Row],[Вид работ]]&" "&Хронология[[#This Row],[Объект работ]] -> ПВ: ГИС АКЦ-прибор | AW12: =SUMIF($AU$2:AU12, Хронология[[#This Row],[Ключ]], $AH$2:AH12) -> 0.5 | AX12: =Хронология[[#This Row],[Вид работ]] & " " & Хронология[[#This Row],[Объект работ]] -> ГИС АКЦ-прибор
A13: ГДТ | B13: КРС | C13: Казанское | D13: 1 | E13: 6 бис | F13: Вдовин И.О. | H13: Жангазиев С.К. | L13: КРС | M13: Штатно | O13: Вспом_работы | P13: Подготовка | Q13: Технологический_инструмент | R13: УЭЦН | T13: Разгрузка на ПМ оборудования для монтажа УЭЦН. Монтаж катушки с кабелем на автонаматыватель. Настройка клапанов ГКШ-1200МТ. Сверка номерных узлов УЭЦН. Центровка мачты | U13: 1.5 | W13: Работы окончены | X13: Победит Холдинг | AE13: =IFERROR(IF(Хронология[[#This Row],[Забой, м]]-V12<0, 0, Хронология[[#This Row],[Забой, м]]-V12), 0) -> 0 | AF13: =AG12 -> 46147.25 | AG13: =Хронология[[#This Row],[Начало]]+Хронология[[#This Row],[Сутки]] -> 46147.313 | AH13: =Хронология[[#This Row],[Часы]]/24 -> 0.0625 | AI13: =IFERROR(Хронология[[#This Row],[Сутки]]+AI12, Хронология[[#This Row],[Сутки]]) -> 2.4791667 | AJ13: =IF(Хронология[[#This Row],[Этап]]="Доп. работы", "ПВ", IFERROR( IF(AND( MATCH(Хронология[[#This Row],[Ключ]], Планирование[Ключ], 0), Хронология[[#This Row],[Подытог за операцию]] <= INDEX(Планирование[Сутки (план)], MATCH(Хронология[[#This Row],[Ключ]], Планирование[Ключ], 0)) ), "ПВ", "ПНВ"), "НПВ")) -> ПНВ | AK13: =IF( OR(Хронология[[#This Row],[Результат]]="ПВ", Хронология[[#This Row],[Результат]]="ПНВ"), Хронология[[#This Row],[Часы]] - IF( Хронология[[#This Row],[Результат]]="ПНВ", MAX(0, MAX(0, SUMIFS(Хронология[Часы], Хронология[Ключ], Хронология[[#This Row],[Ключ]], Хронология[Начало], "<=" & Хронология[[#This Row],[Начало]]) - IFERROR(INDEX(Планирование[Часы (план)], MATCH(Хронология[[#This Row],[Ключ]], Планирование[Ключ], 0)), 0)) - MAX(0, SUMIFS(Хронология[Часы], Хронология[Ключ], Хронология[[#This Row],[Ключ]], Хронология[Начало], "<" & Хронология[[#This Row],[Начало]]) - IFERROR(INDEX(Планирование[Часы (план)], MATCH(Хронология[[#This Row],[Ключ]], Планирование[Ключ], 0)), 0)) ), 0 ), 0 ) -> 0.92 | AL13: =IF( Хронология[[#This Row],[Результат]]="ПНВ", MAX(0, MAX(0, SUMIFS(Хронология[Часы], Хронология[Ключ], Хронология[[#This Row],[Ключ]], Хронология[Начало], "<=" & Хронология[[#This Row],[Начало]]) - IFERROR(INDEX(Планирование[Часы (план)], MATCH(Хронология[[#This Row],[Ключ]], Планирование[Ключ], 0)), 0)) - MAX(0, SUMIFS(Хронология[Часы], Хронология[Ключ], Хронология[[#This Row],[Ключ]], Хронология[Начало], "<" & Хронология[[#This Row],[Начало]]) - IFERROR(INDEX(Планирование[Часы (план)], MATCH(Хронология[[#This Row],[Ключ]], Планирование[Ключ], 0)), 0)) ), 0 ) -> 0.58 | AM13: =IF(Хронология[[#This Row],[Результат]]="НПВ", Хронология[[#This Row],[Часы]], 0) -> 0 | AN13: =SUMIFS(Хронология[НПВ], Хронология[Скважина], Хронология[[#This Row],[Скважина]], Хронология[Начало], "<=" & Хронология[[#This Row],[Начало]]) -> 9 | AO13: =SUMIFS(Хронология[ПНВ], Хронология[Скважина], Хронология[[#This Row],[Скважина]], Хронология[Начало], "<=" & Хронология[[#This Row],[Начало]]) -> 11.64 | AP13: =INT(ROUND(Хронология[[#This Row],[Начало]], 3)) -> 46147 | AQ13: =Хронология[[#This Row],[Начало]]-INT(Хронология[[#This Row],[Начало]]) -> 0.25 | AR13: =INT(ROUND(Хронология[[#This Row],[Окончание]], 3)) -> 46147 | AS13: =Хронология[[#This Row],[Окончание]]-INT(Хронология[[#This Row],[Окончание]]) -> 0.3125 | AT13: =Хронология[[#This Row],[Мастер]] & CHAR(10) & Хронология[[#This Row],[Помощник мастера]] & CHAR(10) & Хронология[[#This Row],[Бурильщик]] -> Вдовин И.О. Жангазиев С.К. | AU13: =IF(Хронология[[#This Row],[Контекст простоя]]="Штатно", Хронология[[#This Row],[Скважина]] & " " & "ОК–" &Хронология[[#This Row],[ОК]] & " " & Хронология[[#This Row],[Этап]] & " " & Хронология[[#This Row],[Вид работ]] & " " & Хронология[[#This Row],[Объект работ]] & " " & Хронология[[#This Row],[Рейс]], Хронология[[#This Row],[Скважина]] & " " & "ОК–" &Хронология[[#This Row],[ОК]] & " " & Хронология[[#This Row],[Этап]] & " " & Хронология[[#This Row],[Контекст простоя]] & " " & Хронология[[#This Row],[Событие]] & " " & Хронология[[#This Row],[Вид работ]] & " " & Хронология[[#This Row],[Объект работ]] & " " & Хронология[[#This Row],[Рейс]]) -> 6 бис ОК– КРС Подготовка УЭЦН | AV13: =Хронология[[#This Row],[Результат]]&": "&Хронология[[#This Row],[Событие]]& CHAR(10) &Хронология[[#This Row],[Вид работ]]&" "&Хронология[[#This Row],[Объект работ]] -> ПНВ: Подготовка УЭЦН | AW13: =SUMIF($AU$2:AU13, Хронология[[#This Row],[Ключ]], $AH$2:AH13) -> 0.0625 | AX13: =Хронология[[#This Row],[Вид работ]] & " " & Хронология[[#This Row],[Объект работ]] -> Подготовка УЭЦН
A14: ГДТ | B14: КРС | C14: Казанское | D14: 1 | E14: 6 бис | F14: Вдовин И.О. | H14: Жангазиев С.К. | L14: КРС | M14: Штатно | O14: Сборка_разборка_оснащение | P14: Сборка | Q14: Технологический_инструмент | R14: УЭЦН | T14: монтаж 10.1ЭЦНМИК8-3000-300 (1 секция насоса, гидрозащита, ПЭД) согласно чек- листа по монтажу | U14: 10.67 | W14: Работы окончены | X14: Победит Холдинг | AE14: =IFERROR(IF(Хронология[[#This Row],[Забой, м]]-V13<0, 0, Хронология[[#This Row],[Забой, м]]-V13), 0) -> 0 | AF14: =AG13 -> 46147.313 | AG14: =Хронология[[#This Row],[Начало]]+Хронология[[#This Row],[Сутки]] -> 46147.757 | AH14: =Хронология[[#This Row],[Часы]]/24 -> 0.44458333 | AI14: =IFERROR(Хронология[[#This Row],[Сутки]]+AI13, Хронология[[#This Row],[Сутки]]) -> 2.92375 | AJ14: =IF(Хронология[[#This Row],[Этап]]="Доп. работы", "ПВ", IFERROR( IF(AND( MATCH(Хронология[[#This Row],[Ключ]], Планирование[Ключ], 0), Хронология[[#This Row],[Подытог за операцию]] <= INDEX(Планирование[Сутки (план)], MATCH(Хронология[[#This Row],[Ключ]], Планирование[Ключ], 0)) ), "ПВ", "ПНВ"), "НПВ")) -> ПНВ | AK14: =IF( OR(Хронология[[#This Row],[Результат]]="ПВ", Хронология[[#This Row],[Результат]]="ПНВ"), Хронология[[#This Row],[Часы]] - IF( Хронология[[#This Row],[Результат]]="ПНВ", MAX(0, MAX(0, SUMIFS(Хронология[Часы], Хронология[Ключ], Хронология[[#This Row],[Ключ]], Хронология[Начало], "<=" & Хронология[[#This Row],[Начало]]) - IFERROR(INDEX(Планирование[Часы (план)], MATCH(Хронология[[#This Row],[Ключ]], Планирование[Ключ], 0)), 0)) - MAX(0, SUMIFS(Хронология[Часы], Хронология[Ключ], Хронология[[#This Row],[Ключ]], Хронология[Начало], "<" & Хронология[[#This Row],[Начало]]) - IFERROR(INDEX(Планирование[Часы (план)], MATCH(Хронология[[#This Row],[Ключ]], Планирование[Ключ], 0)), 0)) ), 0 ), 0 ) -> 6.67 | AL14: =IF( Хронология[[#This Row],[Результат]]="ПНВ", MAX(0, MAX(0, SUMIFS(Хронология[Часы], Хронология[Ключ], Хронология[[#This Row],[Ключ]], Хронология[Начало], "<=" & Хронология[[#This Row],[Начало]]) - IFERROR(INDEX(Планирование[Часы (план)], MATCH(Хронология[[#This Row],[Ключ]], Планирование[Ключ], 0)), 0)) - MAX(0, SUMIFS(Хронология[Часы], Хронология[Ключ], Хронология[[#This Row],[Ключ]], Хронология[Начало], "<" & Хронология[[#This Row],[Начало]]) - IFERROR(INDEX(Планирование[Часы (план)], MATCH(Хронология[[#This Row],[Ключ]], Планирование[Ключ], 0)), 0)) ), 0 ) -> 4 | AM14: =IF(Хронология[[#This Row],[Результат]]="НПВ", Хронология[[#This Row],[Часы]], 0) -> 0 | AN14: =SUMIFS(Хронология[НПВ], Хронология[Скважина], Хронология[[#This Row],[Скважина]], Хронология[Начало], "<=" & Хронология[[#This Row],[Начало]]) -> 9 | AO14: =SUMIFS(Хронология[ПНВ], Хронология[Скважина], Хронология[[#This Row],[Скважина]], Хронология[Начало], "<=" & Хронология[[#This Row],[Начало]]) -> 15.64 | AP14: =INT(ROUND(Хронология[[#This Row],[Начало]], 3)) -> 46147 | AQ14: =Хронология[[#This Row],[Начало]]-INT(Хронология[[#This Row],[Начало]]) -> 0.3125 | AR14: =INT(ROUND(Хронология[[#This Row],[Окончание]], 3)) -> 46147 | AS14: =Хронология[[#This Row],[Окончание]]-INT(Хронология[[#This Row],[Окончание]]) -> 0.75708333 | AT14: =Хронология[[#This Row],[Мастер]] & CHAR(10) & Хронология[[#This Row],[Помощник мастера]] & CHAR(10) & Хронология[[#This Row],[Бурильщик]] -> Вдовин И.О. Жангазиев С.К. | AU14: =IF(Хронология[[#This Row],[Контекст простоя]]="Штатно", Хронология[[#This Row],[Скважина]] & " " & "ОК–" &Хронология[[#This Row],[ОК]] & " " & Хронология[[#This Row],[Этап]] & " " & Хронология[[#This Row],[Вид работ]] & " " & Хронология[[#This Row],[Объект работ]] & " " & Хронология[[#This Row],[Рейс]], Хронология[[#This Row],[Скважина]] & " " & "ОК–" &Хронология[[#This Row],[ОК]] & " " & Хронология[[#This Row],[Этап]] & " " & Хронология[[#This Row],[Контекст простоя]] & " " & Хронология[[#This Row],[Событие]] & " " & Хронология[[#This Row],[Вид работ]] & " " & Хронология[[#This Row],[Объект работ]] & " " & Хронология[[#This Row],[Рейс]]) -> 6 бис ОК– КРС Сборка УЭЦН | AV14: =Хронология[[#This Row],[Результат]]&": "&Хронология[[#This Row],[Событие]]& CHAR(10) &Хронология[[#This Row],[Вид работ]]&" "&Хронология[[#This Row],[Объект работ]] -> ПНВ: Сборка УЭЦН | AW14: =SUMIF($AU$2:AU14, Хронология[[#This Row],[Ключ]], $AH$2:AH14) -> 0.44458333 | AX14: =Хронология[[#This Row],[Вид работ]] & " " & Хронология[[#This Row],[Объект работ]] -> Сборка УЭЦН
A15: ГДТ | B15: КРС | C15: Казанское | D15: 1 | E15: 6 бис | F15: Вдовин И.О. | H15: Жангазиев С.К. | L15: КРС | M15: Штатно | O15: СПО | P15: Спуск | Q15: Технологический_инструмент | R15: УЭЦН | T15: спуск 10.1 ЭЦНМИК8-3000-300 на глубину 450 метров по мере НКТП в следующей компоновке: ЭЦН + НКТП-114 мм до устья. Скорость СПО установки не более 0,25 м/сек. | U15: 5 | W15: Работы окончены | X15: Победит Холдинг | AE15: =IFERROR(IF(Хронология[[#This Row],[Забой, м]]-V14<0, 0, Хронология[[#This Row],[Забой, м]]-V14), 0) -> 0 | AF15: =AG14 -> 46147.757 | AG15: =Хронология[[#This Row],[Начало]]+Хронология[[#This Row],[Сутки]] -> 46147.965 | AH15: =Хронология[[#This Row],[Часы]]/24 -> 0.20833333 | AI15: =IFERROR(Хронология[[#This Row],[Сутки]]+AI14, Хронология[[#This Row],[Сутки]]) -> 3.1320833 | AJ15: =IF(Хронология[[#This Row],[Этап]]="Доп. работы", "ПВ", IFERROR( IF(AND( MATCH(Хронология[[#This Row],[Ключ]], Планирование[Ключ], 0), Хронология[[#This Row],[Подытог за операцию]] <= INDEX(Планирование[Сутки (план)], MATCH(Хронология[[#This Row],[Ключ]], Планирование[Ключ], 0)) ), "ПВ", "ПНВ"), "НПВ")) -> ПНВ | AK15: =IF( OR(Хронология[[#This Row],[Результат]]="ПВ", Хронология[[#This Row],[Результат]]="ПНВ"), Хронология[[#This Row],[Часы]] - IF( Хронология[[#This Row],[Результат]]="ПНВ", MAX(0, MAX(0, SUMIFS(Хронология[Часы], Хронология[Ключ], Хронология[[#This Row],[Ключ]], Хронология[Начало], "<=" & Хронология[[#This Row],[Начало]]) - IFERROR(INDEX(Планирование[Часы (план)], MATCH(Хронология[[#This Row],[Ключ]], Планирование[Ключ], 0)), 0)) - MAX(0, SUMIFS(Хронология[Часы], Хронология[Ключ], Хронология[[#This Row],[Ключ]], Хронология[Начало], "<" & Хронология[[#This Row],[Начало]]) - IFERROR(INDEX(Планирование[Часы (план)], MATCH(Хронология[[#This Row],[Ключ]], Планирование[Ключ], 0)), 0)) ), 0 ), 0 ) -> 4.97 | AL15: =IF( Хронология[[#This Row],[Результат]]="ПНВ", MAX(0, MAX(0, SUMIFS(Хронология[Часы], Хронология[Ключ], Хронология[[#This Row],[Ключ]], Хронология[Начало], "<=" & Хронология[[#This Row],[Начало]]) - IFERROR(INDEX(Планирование[Часы (план)], MATCH(Хронология[[#This Row],[Ключ]], Планирование[Ключ], 0)), 0)) - MAX(0, SUMIFS(Хронология[Часы], Хронология[Ключ], Хронология[[#This Row],[Ключ]], Хронология[Начало], "<" & Хронология[[#This Row],[Начало]]) - IFERROR(INDEX(Планирование[Часы (план)], MATCH(Хронология[[#This Row],[Ключ]], Планирование[Ключ], 0)), 0)) ), 0 ) -> 0.03 | AM15: =IF(Хронология[[#This Row],[Результат]]="НПВ", Хронология[[#This Row],[Часы]], 0) -> 0 | AN15: =SUMIFS(Хронология[НПВ], Хронология[Скважина], Хронология[[#This Row],[Скважина]], Хронология[Начало], "<=" & Хронология[[#This Row],[Начало]]) -> 9 | AO15: =SUMIFS(Хронология[ПНВ], Хронология[Скважина], Хронология[[#This Row],[Скважина]], Хронология[Начало], "<=" & Хронология[[#This Row],[Начало]]) -> 15.67 | AP15: =INT(ROUND(Хронология[[#This Row],[Начало]], 3)) -> 46147 | AQ15: =Хронология[[#This Row],[Начало]]-INT(Хронология[[#This Row],[Начало]]) -> 0.75708333 | AR15: =INT(ROUND(Хронология[[#This Row],[Окончание]], 3)) -> 46147 | AS15: =Хронология[[#This Row],[Окончание]]-INT(Хронология[[#This Row],[Окончание]]) -> 0.96541667 | AT15: =Хронология[[#This Row],[Мастер]] & CHAR(10) & Хронология[[#This Row],[Помощник мастера]] & CHAR(10) & Хронология[[#This Row],[Бурильщик]] -> Вдовин И.О. Жангазиев С.К. | AU15: =IF(Хронология[[#This Row],[Контекст простоя]]="Штатно", Хронология[[#This Row],[Скважина]] & " " & "ОК–" &Хронология[[#This Row],[ОК]] & " " & Хронология[[#This Row],[Этап]] & " " & Хронология[[#This Row],[Вид работ]] & " " & Хронология[[#This Row],[Объект работ]] & " " & Хронология[[#This Row],[Рейс]], Хронология[[#This Row],[Скважина]] & " " & "ОК–" &Хронология[[#This Row],[ОК]] & " " & Хронология[[#This Row],[Этап]] & " " & Хронология[[#This Row],[Контекст простоя]] & " " & Хронология[[#This Row],[Событие]] & " " & Хронология[[#This Row],[Вид работ]] & " " & Хронология[[#This Row],[Объект работ]] & " " & Хронология[[#This Row],[Рейс]]) -> 6 бис ОК– КРС Спуск УЭЦН | AV15: =Хронология[[#This Row],[Результат]]&": "&Хронология[[#This Row],[Событие]]& CHAR(10) &Хронология[[#This Row],[Вид работ]]&" "&Хронология[[#This Row],[Объект работ]] -> ПНВ: Спуск УЭЦН | AW15: =SUMIF($AU$2:AU15, Хронология[[#This Row],[Ключ]], $AH$2:AH15) -> 0.20833333 | AX15: =Хронология[[#This Row],[Вид работ]] & " " & Хронология[[#This Row],[Объект работ]] -> Спуск УЭЦН
A16: ГДТ | B16: КРС | C16: Казанское | D16: 1 | E16: 6 бис | F16: Жабин П.П. | H16: Керимов Н.К. | L16: КРС | M16: Штатно | O16: Монтаж_демонтаж_установка | P16: Демонтаж | Q16: Оборудование | R16: ГКШ | T16: Демонтаж РП. Демонтаж ГКШ-1200, СУ-80, (вес перед посадкой ПШ: на ↑ 4,9тн, на ↓ 4,6тн). | U16: 0.83 | W16: Работы окончены | AE16: =IFERROR(IF(Хронология[[#This Row],[Забой, м]]-V15<0, 0, Хронология[[#This Row],[Забой, м]]-V15), 0) -> 0 | AF16: =AG15 -> 46147.965 | AG16: =Хронология[[#This Row],[Начало]]+Хронология[[#This Row],[Сутки]] -> 46148 | AH16: =Хронология[[#This Row],[Часы]]/24 -> 0.034583333 | AI16: =IFERROR(Хронология[[#This Row],[Сутки]]+AI15, Хронология[[#This Row],[Сутки]]) -> 3.1666667 | AJ16: =IF(Хронология[[#This Row],[Этап]]="Доп. работы", "ПВ", IFERROR( IF(AND( MATCH(Хронология[[#This Row],[Ключ]], Планирование[Ключ], 0), Хронология[[#This Row],[Подытог за операцию]] <= INDEX(Планирование[Сутки (план)], MATCH(Хронология[[#This Row],[Ключ]], Планирование[Ключ], 0)) ), "ПВ", "ПНВ"), "НПВ")) -> ПВ | AK16: =IF( OR(Хронология[[#This Row],[Результат]]="ПВ", Хронология[[#This Row],[Результат]]="ПНВ"), Хронология[[#This Row],[Часы]] - IF( Хронология[[#This Row],[Результат]]="ПНВ", MAX(0, MAX(0, SUMIFS(Хронология[Часы], Хронология[Ключ], Хронология[[#This Row],[Ключ]], Хронология[Начало], "<=" & Хронология[[#This Row],[Начало]]) - IFERROR(INDEX(Планирование[Часы (план)], MATCH(Хронология[[#This Row],[Ключ]], Планирование[Ключ], 0)), 0)) - MAX(0, SUMIFS(Хронология[Часы], Хронология[Ключ], Хронология[[#This Row],[Ключ]], Хронология[Начало], "<" & Хронология[[#This Row],[Начало]]) - IFERROR(INDEX(Планирование[Часы (план)], MATCH(Хронология[[#This Row],[Ключ]], Планирование[Ключ], 0)), 0)) ), 0 ), 0 ) -> 0.83 | AL16: =IF( Хронология[[#This Row],[Результат]]="ПНВ", MAX(0, MAX(0, SUMIFS(Хронология[Часы], Хронология[Ключ], Хронология[[#This Row],[Ключ]], Хронология[Начало], "<=" & Хронология[[#This Row],[Начало]]) - IFERROR(INDEX(Планирование[Часы (план)], MATCH(Хронология[[#This Row],[Ключ]], Планирование[Ключ], 0)), 0)) - MAX(0, SUMIFS(Хронология[Часы], Хронология[Ключ], Хронология[[#This Row],[Ключ]], Хронология[Начало], "<" & Хронология[[#This Row],[Начало]]) - IFERROR(INDEX(Планирование[Часы (план)], MATCH(Хронология[[#This Row],[Ключ]], Планирование[Ключ], 0)), 0)) ), 0 ) -> 0 | AM16: =IF(Хронология[[#This Row],[Результат]]="НПВ", Хронология[[#This Row],[Часы]], 0) -> 0 | AN16: =SUMIFS(Хронология[НПВ], Хронология[Скважина], Хронология[[#This Row],[Скважина]], Хронология[Начало], "<=" & Хронология[[#This Row],[Начало]]) -> 9 | AO16: =SUMIFS(Хронология[ПНВ], Хронология[Скважина], Хронология[[#This Row],[Скважина]], Хронология[Начало], "<=" & Хронология[[#This Row],[Начало]]) -> 15.67 | AP16: =INT(ROUND(Хронология[[#This Row],[Начало]], 3)) -> 46147 | AQ16: =Хронология[[#This Row],[Начало]]-INT(Хронология[[#This Row],[Начало]]) -> 0.96541667 | AR16: =INT(ROUND(Хронология[[#This Row],[Окончание]], 3)) -> 46148 | AS16: =Хронология[[#This Row],[Окончание]]-INT(Хронология[[#This Row],[Окончание]]) -> 0 | AT16: =Хронология[[#This Row],[Мастер]] & CHAR(10) & Хронология[[#This Row],[Помощник мастера]] & CHAR(10) & Хронология[[#This Row],[Бурильщик]] -> Жабин П.П. Керимов Н.К. | AU16: =IF(Хронология[[#This Row],[Контекст простоя]]="Штатно", Хронология[[#This Row],[Скважина]] & " " & "ОК–" &Хронология[[#This Row],[ОК]] & " " & Хронология[[#This Row],[Этап]] & " " & Хронология[[#This Row],[Вид работ]] & " " & Хронология[[#This Row],[Объект работ]] & " " & Хронология[[#This Row],[Рейс]], Хронология[[#This Row],[Скважина]] & " " & "ОК–" &Хронология[[#This Row],[ОК]] & " " & Хронология[[#This Row],[Этап]] & " " & Хронология[[#This Row],[Контекст простоя]] & " " & Хронология[[#This Row],[Событие]] & " " & Хронология[[#This Row],[Вид работ]] & " " & Хронология[[#This Row],[Объект работ]] & " " & Хронология[[#This Row],[Рейс]]) -> 6 бис ОК– КРС Демонтаж ГКШ | AV16: =Хронология[[#This Row],[Результат]]&": "&Хронология[[#This Row],[Событие]]& CHAR(10) &Хронология[[#This Row],[Вид работ]]&" "&Хронология[[#This Row],[Объект работ]] -> ПВ: Демонтаж ГКШ | AW16: =SUMIF($AU$2:AU16, Хронология[[#This Row],[Ключ]], $AH$2:AH16) -> 0.034583333 | AX16: =Хронология[[#This Row],[Вид работ]] & " " & Хронология[[#This Row],[Объект работ]] -> Демонтаж ГКШ
A17: ГДТ | B17: КРС | C17: Казанское | D17: 1 | E17: 6 бис | F17: Жабин П.П. | H17: Керимов Н.К. | L17: КРС | M17: Штатно | O17: Контроль_замер | P17: Замер | Q17: Энергетика | R17: Электрооборудование | T17: Контрольный замер сопротивления изоляции совместно с представителем УРиЭ УЭЦН АО "Газпром добыча Томск" R=200МОм. Звезда есть. | U17: 0.5 | W17: Работы окончены | AE17: =IFERROR(IF(Хронология[[#This Row],[Забой, м]]-V16<0, 0, Хронология[[#This Row],[Забой, м]]-V16), 0) -> 0 | AF17: =AG16 -> 46148 | AG17: =Хронология[[#This Row],[Начало]]+Хронология[[#This Row],[Сутки]] -> 46148.021 | AH17: =Хронология[[#This Row],[Часы]]/24 -> 0.020833333 | AI17: =IFERROR(Хронология[[#This Row],[Сутки]]+AI16, Хронология[[#This Row],[Сутки]]) -> 3.1875 | AJ17: =IF(Хронология[[#This Row],[Этап]]="Доп. работы", "ПВ", IFERROR( IF(AND( MATCH(Хронология[[#This Row],[Ключ]], Планирование[Ключ], 0), Хронология[[#This Row],[Подытог за операцию]] <= INDEX(Планирование[Сутки (план)], MATCH(Хронология[[#This Row],[Ключ]], Планирование[Ключ], 0)) ), "ПВ", "ПНВ"), "НПВ")) -> ПВ | AK17: =IF( OR(Хронология[[#This Row],[Результат]]="ПВ", Хронология[[#This Row],[Результат]]="ПНВ"), Хронология[[#This Row],[Часы]] - IF( Хронология[[#This Row],[Результат]]="ПНВ", MAX(0, MAX(0, SUMIFS(Хронология[Часы], Хронология[Ключ], Хронология[[#This Row],[Ключ]], Хронология[Начало], "<=" & Хронология[[#This Row],[Начало]]) - IFERROR(INDEX(Планирование[Часы (план)], MATCH(Хронология[[#This Row],[Ключ]], Планирование[Ключ], 0)), 0)) - MAX(0, SUMIFS(Хронология[Часы], Хронология[Ключ], Хронология[[#This Row],[Ключ]], Хронология[Начало], "<" & Хронология[[#This Row],[Начало]]) - IFERROR(INDEX(Планирование[Часы (план)], MATCH(Хронология[[#This Row],[Ключ]], Планирование[Ключ], 0)), 0)) ), 0 ), 0 ) -> 0.5 | AL17: =IF( Хронология[[#This Row],[Результат]]="ПНВ", MAX(0, MAX(0, SUMIFS(Хронология[Часы], Хронология[Ключ], Хронология[[#This Row],[Ключ]], Хронология[Начало], "<=" & Хронология[[#This Row],[Начало]]) - IFERROR(INDEX(Планирование[Часы (план)], MATCH(Хронология[[#This Row],[Ключ]], Планирование[Ключ], 0)), 0)) - MAX(0, SUMIFS(Хронология[Часы], Хронология[Ключ], Хронология[[#This Row],[Ключ]], Хронология[Начало], "<" & Хронология[[#This Row],[Начало]]) - IFERROR(INDEX(Планирование[Часы (план)], MATCH(Хронология[[#This Row],[Ключ]], Планирование[Ключ], 0)), 0)) ), 0 ) -> 0 | AM17: =IF(Хронология[[#This Row],[Результат]]="НПВ", Хронология[[#This Row],[Часы]], 0) -> 0 | AN17: =SUMIFS(Хронология[НПВ], Хронология[Скважина], Хронология[[#This Row],[Скважина]], Хронология[Начало], "<=" & Хронология[[#This Row],[Начало]]) -> 9 | AO17: =SUMIFS(Хронология[ПНВ], Хронология[Скважина], Хронология[[#This Row],[Скважина]], Хронология[Начало], "<=" & Хронология[[#This Row],[Начало]]) -> 15.67 | AP17: =INT(ROUND(Хронология[[#This Row],[Начало]], 3)) -> 46148 | AQ17: =Хронология[[#This Row],[Начало]]-INT(Хронология[[#This Row],[Начало]]) -> 0 | AR17: =INT(ROUND(Хронология[[#This Row],[Окончание]], 3)) -> 46148 | AS17: =Хронология[[#This Row],[Окончание]]-INT(Хронология[[#This Row],[Окончание]]) -> 0.020833333 | AT17: =Хронология[[#This Row],[Мастер]] & CHAR(10) & Хронология[[#This Row],[Помощник мастера]] & CHAR(10) & Хронология[[#This Row],[Бурильщик]] -> Жабин П.П. Керимов Н.К. | AU17: =IF(Хронология[[#This Row],[Контекст простоя]]="Штатно", Хронология[[#This Row],[Скважина]] & " " & "ОК–" &Хронология[[#This Row],[ОК]] & " " & Хронология[[#This Row],[Этап]] & " " & Хронология[[#This Row],[Вид работ]] & " " & Хронология[[#This Row],[Объект работ]] & " " & Хронология[[#This Row],[Рейс]], Хронология[[#This Row],[Скважина]] & " " & "ОК–" &Хронология[[#This Row],[ОК]] & " " & Хронология[[#This Row],[Этап]] & " " & Хронология[[#This Row],[Контекст простоя]] & " " & Хронология[[#This Row],[Событие]] & " " & Хронология[[#This Row],[Вид работ]] & " " & Хронология[[#This Row],[Объект работ]] & " " & Хронология[[#This Row],[Рейс]]) -> 6 бис ОК– КРС Замер Электрооборудование | AV17: =Хронология[[#This Row],[Результат]]&": "&Хронология[[#This Row],[Событие]]& CHAR(10) &Хронология[[#This Row],[Вид работ]]&" "&Хронология[[#This Row],[Объект работ]] -> ПВ: Замер Электрооборудование | AW17: =SUMIF($AU$2:AU17, Хронология[[#This Row],[Ключ]], $AH$2:AH17) -> 0.020833333 | AX17: =Хронология[[#This Row],[Вид работ]] & " " & Хронология[[#This Row],[Объект работ]] -> Замер Электрооборудование
A18: ГДТ | B18: КРС | C18: Казанское | D18: 1 | E18: 6 бис | F18: Жабин П.П. | H18: Керимов Н.К. | L18: Заканчивание | M18: Штатно | O18: Монтаж_демонтаж_установка | P18: Перемонтаж | Q18: Объекты_устье | R18: Фонтанная арматура | T18: Монтаж ФА с протаскиванием кабеля (≈44м) через кабельный ввод. Монтаж кабельного ввода. Контрольный замер изоляции кабеля с представителем УР и Э УЭЦН АО "Газпром добыча Томск" после посадки планшайбы. R=200МОм. Звезда есть. Монтаж обвязки скважины. | U18: 2 | W18: Работы окончены | X18: Победит Холдинг | AE18: =IFERROR(IF(Хронология[[#This Row],[Забой, м]]-V17<0, 0, Хронология[[#This Row],[Забой, м]]-V17), 0) -> 0 | AF18: =AG17 -> 46148.021 | AG18: =Хронология[[#This Row],[Начало]]+Хронология[[#This Row],[Сутки]] -> 46148.104 | AH18: =Хронология[[#This Row],[Часы]]/24 -> 0.083333333 | AI18: =IFERROR(Хронология[[#This Row],[Сутки]]+AI17, Хронология[[#This Row],[Сутки]]) -> 3.2708333 | AJ18: =IF(Хронология[[#This Row],[Этап]]="Доп. работы", "ПВ", IFERROR( IF(AND( MATCH(Хронология[[#This Row],[Ключ]], Планирование[Ключ], 0), Хронология[[#This Row],[Подытог за операцию]] <= INDEX(Планирование[Сутки (план)], MATCH(Хронология[[#This Row],[Ключ]], Планирование[Ключ], 0)) ), "ПВ", "ПНВ"), "НПВ")) -> ПНВ | AK18: =IF( OR(Хронология[[#This Row],[Результат]]="ПВ", Хронология[[#This Row],[Результат]]="ПНВ"), Хронология[[#This Row],[Часы]] - IF( Хронология[[#This Row],[Результат]]="ПНВ", MAX(0, MAX(0, SUMIFS(Хронология[Часы], Хронология[Ключ], Хронология[[#This Row],[Ключ]], Хронология[Начало], "<=" & Хронология[[#This Row],[Начало]]) - IFERROR(INDEX(Планирование[Часы (план)], MATCH(Хронология[[#This Row],[Ключ]], Планирование[Ключ], 0)), 0)) - MAX(0, SUMIFS(Хронология[Часы], Хронология[Ключ], Хронология[[#This Row],[Ключ]], Хронология[Начало], "<" & Хронология[[#This Row],[Начало]]) - IFERROR(INDEX(Планирование[Часы (план)], MATCH(Хронология[[#This Row],[Ключ]], Планирование[Ключ], 0)), 0)) ), 0 ), 0 ) -> 1.93 | AL18: =IF( Хронология[[#This Row],[Результат]]="ПНВ", MAX(0, MAX(0, SUMIFS(Хронология[Часы], Хронология[Ключ], Хронология[[#This Row],[Ключ]], Хронология[Начало], "<=" & Хронология[[#This Row],[Начало]]) - IFERROR(INDEX(Планирование[Часы (план)], MATCH(Хронология[[#This Row],[Ключ]], Планирование[Ключ], 0)), 0)) - MAX(0, SUMIFS(Хронология[Часы], Хронология[Ключ], Хронология[[#This Row],[Ключ]], Хронология[Начало], "<" & Хронология[[#This Row],[Начало]]) - IFERROR(INDEX(Планирование[Часы (план)], MATCH(Хронология[[#This Row],[Ключ]], Планирование[Ключ], 0)), 0)) ), 0 ) -> 0.07 | AM18: =IF(Хронология[[#This Row],[Результат]]="НПВ", Хронология[[#This Row],[Часы]], 0) -> 0 | AN18: =SUMIFS(Хронология[НПВ], Хронология[Скважина], Хронология[[#This Row],[Скважина]], Хронология[Начало], "<=" & Хронология[[#This Row],[Начало]]) -> 9 | AO18: =SUMIFS(Хронология[ПНВ], Хронология[Скважина], Хронология[[#This Row],[Скважина]], Хронология[Начало], "<=" & Хронология[[#This Row],[Начало]]) -> 15.74 | AP18: =INT(ROUND(Хронология[[#This Row],[Начало]], 3)) -> 46148 | AQ18: =Хронология[[#This Row],[Начало]]-INT(Хронология[[#This Row],[Начало]]) -> 0.020833333 | AR18: =INT(ROUND(Хронология[[#This Row],[Окончание]], 3)) -> 46148 | AS18: =Хронология[[#This Row],[Окончание]]-INT(Хронология[[#This Row],[Окончание]]) -> 0.10416667 | AT18: =Хронология[[#This Row],[Мастер]] & CHAR(10) & Хронология[[#This Row],[Помощник мастера]] & CHAR(10) & Хронология[[#This Row],[Бурильщик]] -> Жабин П.П. Керимов Н.К. | AU18: =IF(Хронология[[#This Row],[Контекст простоя]]="Штатно", Хронология[[#This Row],[Скважина]] & " " & "ОК–" &Хронология[[#This Row],[ОК]] & " " & Хронология[[#This Row],[Этап]] & " " & Хронология[[#This Row],[Вид работ]] & " " & Хронология[[#This Row],[Объект работ]] & " " & Хронология[[#This Row],[Рейс]], Хронология[[#This Row],[Скважина]] & " " & "ОК–" &Хронология[[#This Row],[ОК]] & " " & Хронология[[#This Row],[Этап]] & " " & Хронология[[#This Row],[Контекст простоя]] & " " & Хронология[[#This Row],[Событие]] & " " & Хронология[[#This Row],[Вид работ]] & " " & Хронология[[#This Row],[Объект работ]] & " " & Хронология[[#This Row],[Рейс]]) -> 6 бис ОК– Заканчивание Перемонтаж Фонтанная арматура | AV18: =Хронология[[#This Row],[Результат]]&": "&Хронология[[#This Row],[Событие]]& CHAR(10) &Хронология[[#This Row],[Вид работ]]&" "&Хронология[[#This Row],[Объект работ]] -> ПНВ: Перемонтаж Фонтанная арматура | AW18: =SUMIF($AU$2:AU18, Хронология[[#This Row],[Ключ]], $AH$2:AH18) -> 0.083333333 | AX18: =Хронология[[#This Row],[Вид работ]] & " " & Хронология[[#This Row],[Объект работ]] -> Перемонтаж Фонтанная арматура
A19: ГДТ | B19: КРС | C19: Казанское | D19: 1 | E19: 6 бис | F19: Жабин П.П. | H19: Керимов Н.К. | L19: Заканчивание | M19: Штатно | O19: Испытания | P19: Запуск в работу | Q19: Технологический_инструмент | R19: УЭЦН | T19: Замер сопротивления изоляции кабельной линии перед запуском установки – 100МОм, звезда есть. Запуск 30.1ЭЦНМИК6-1000-370 на НСК в 18:30ч. Iпуск =21,4А; Iраб=19,7А; Частота – 40Гц; Загрузка – 42%; Подача сразу. Дебит составил V = 1040м3 ЗР после запуска. | U19: 1 | W19: Работы окончены | AE19: =IFERROR(IF(Хронология[[#This Row],[Забой, м]]-V18<0, 0, Хронология[[#This Row],[Забой, м]]-V18), 0) -> 0 | AF19: =AG18 -> 46148.104 | AG19: =Хронология[[#This Row],[Начало]]+Хронология[[#This Row],[Сутки]] -> 46148.146 | AH19: =Хронология[[#This Row],[Часы]]/24 -> 0.041666667 | AI19: =IFERROR(Хронология[[#This Row],[Сутки]]+AI18, Хронология[[#This Row],[Сутки]]) -> 3.3125 | AJ19: =IF(Хронология[[#This Row],[Этап]]="Доп. работы", "ПВ", IFERROR( IF(AND( MATCH(Хронология[[#This Row],[Ключ]], Планирование[Ключ], 0), Хронология[[#This Row],[Подытог за операцию]] <= INDEX(Планирование[Сутки (план)], MATCH(Хронология[[#This Row],[Ключ]], Планирование[Ключ], 0)) ), "ПВ", "ПНВ"), "НПВ")) -> ПВ | AK19: =IF( OR(Хронология[[#This Row],[Результат]]="ПВ", Хронология[[#This Row],[Результат]]="ПНВ"), Хронология[[#This Row],[Часы]] - IF( Хронология[[#This Row],[Результат]]="ПНВ", MAX(0, MAX(0, SUMIFS(Хронология[Часы], Хронология[Ключ], Хронология[[#This Row],[Ключ]], Хронология[Начало], "<=" & Хронология[[#This Row],[Начало]]) - IFERROR(INDEX(Планирование[Часы (план)], MATCH(Хронология[[#This Row],[Ключ]], Планирование[Ключ], 0)), 0)) - MAX(0, SUMIFS(Хронология[Часы], Хронология[Ключ], Хронология[[#This Row],[Ключ]], Хронология[Начало], "<" & Хронология[[#This Row],[Начало]]) - IFERROR(INDEX(Планирование[Часы (план)], MATCH(Хронология[[#This Row],[Ключ]], Планирование[Ключ], 0)), 0)) ), 0 ), 0 ) -> 1 | AL19: =IF( Хронология[[#This Row],[Результат]]="ПНВ", MAX(0, MAX(0, SUMIFS(Хронология[Часы], Хронология[Ключ], Хронология[[#This Row],[Ключ]], Хронология[Начало], "<=" & Хронология[[#This Row],[Начало]]) - IFERROR(INDEX(Планирование[Часы (план)], MATCH(Хронология[[#This Row],[Ключ]], Планирование[Ключ], 0)), 0)) - MAX(0, SUMIFS(Хронология[Часы], Хронология[Ключ], Хронология[[#This Row],[Ключ]], Хронология[Начало], "<" & Хронология[[#This Row],[Начало]]) - IFERROR(INDEX(Планирование[Часы (план)], MATCH(Хронология[[#This Row],[Ключ]], Планирование[Ключ], 0)), 0)) ), 0 ) -> 0 | AM19: =IF(Хронология[[#This Row],[Результат]]="НПВ", Хронология[[#This Row],[Часы]], 0) -> 0 | AN19: =SUMIFS(Хронология[НПВ], Хронология[Скважина], Хронология[[#This Row],[Скважина]], Хронология[Начало], "<=" & Хронология[[#This Row],[Начало]]) -> 9 | AO19: =SUMIFS(Хронология[ПНВ], Хронология[Скважина], Хронология[[#This Row],[Скважина]], Хронология[Начало], "<=" & Хронология[[#This Row],[Начало]]) -> 15.74 | AP19: =INT(ROUND(Хронология[[#This Row],[Начало]], 3)) -> 46148 | AQ19: =Хронология[[#This Row],[Начало]]-INT(Хронология[[#This Row],[Начало]]) -> 0.10416667 | AR19: =INT(ROUND(Хронология[[#This Row],[Окончание]], 3)) -> 46148 | AS19: =Хронология[[#This Row],[Окончание]]-INT(Хронология[[#This Row],[Окончание]]) -> 0.14583333 | AT19: =Хронология[[#This Row],[Мастер]] & CHAR(10) & Хронология[[#This Row],[Помощник мастера]] & CHAR(10) & Хронология[[#This Row],[Бурильщик]] -> Жабин П.П. Керимов Н.К. | AU19: =IF(Хронология[[#This Row],[Контекст простоя]]="Штатно", Хронология[[#This Row],[Скважина]] & " " & "ОК–" &Хронология[[#This Row],[ОК]] & " " & Хронология[[#This Row],[Этап]] & " " & Хронология[[#This Row],[Вид работ]] & " " & Хронология[[#This Row],[Объект работ]] & " " & Хронология[[#This Row],[Рейс]], Хронология[[#This Row],[Скважина]] & " " & "ОК–" &Хронология[[#This Row],[ОК]] & " " & Хронология[[#This Row],[Этап]] & " " & Хронология[[#This Row],[Контекст простоя]] & " " & Хронология[[#This Row],[Событие]] & " " & Хронология[[#This Row],[Вид работ]] & " " & Хронология[[#This Row],[Объект работ]] & " " & Хронология[[#This Row],[Рейс]]) -> 6 бис ОК– Заканчивание Запуск в работу УЭЦН | AV19: =Хронология[[#This Row],[Результат]]&": "&Хронология[[#This Row],[Событие]]& CHAR(10) &Хронология[[#This Row],[Вид работ]]&" "&Хронология[[#This Row],[Объект работ]] -> ПВ: Запуск в работу УЭЦН | AW19: =SUMIF($AU$2:AU19, Хронология[[#This Row],[Ключ]], $AH$2:AH19) -> 0.041666667 | AX19: =Хронология[[#This Row],[Вид работ]] & " " & Хронология[[#This Row],[Объект работ]] -> Запуск в работу УЭЦН
A20: ГДТ | B20: КРС | C20: Казанское | D20: 1 | E20: 6 бис | F20: Жабин П.П. | H20: Керимов Н.К. | L20: ДПМ | M20: Штатно | O20: Монтаж_демонтаж_установка | P20: Демонтаж | Q20: Оборудование | R20: УПА | T20: Демонтаж ИВЭ-50, РП, А- 60/80, пригрузов, якорей, ПМ и трёх облегчённых стеллажей, линии долива. Демонтаж пригрузов, якорей.Демонтаж ПМ и трёх облегчённых стеллажей, линии долива. Демонтаж 1-го защитных колпаков. Демонтаж заземления. Отключение оборудования. Демонтаж подставок под кабель. Уборка прилегающей к скважине территории. | U20: 13.5 | W20: Работы окончены | X20: Победит Холдинг | AE20: =IFERROR(IF(Хронология[[#This Row],[Забой, м]]-V19<0, 0, Хронология[[#This Row],[Забой, м]]-V19), 0) -> 0 | AF20: =AG19 -> 46148.146 | AG20: =Хронология[[#This Row],[Начало]]+Хронология[[#This Row],[Сутки]] -> 46148.708 | AH20: =Хронология[[#This Row],[Часы]]/24 -> 0.5625 | AI20: =IFERROR(Хронология[[#This Row],[Сутки]]+AI19, Хронология[[#This Row],[Сутки]]) -> 3.875 | AJ20: =IF(Хронология[[#This Row],[Этап]]="Доп. работы", "ПВ", IFERROR( IF(AND( MATCH(Хронология[[#This Row],[Ключ]], Планирование[Ключ], 0), Хронология[[#This Row],[Подытог за операцию]] <= INDEX(Планирование[Сутки (план)], MATCH(Хронология[[#This Row],[Ключ]], Планирование[Ключ], 0)) ), "ПВ", "ПНВ"), "НПВ")) -> ПНВ | AK20: =IF( OR(Хронология[[#This Row],[Результат]]="ПВ", Хронология[[#This Row],[Результат]]="ПНВ"), Хронология[[#This Row],[Часы]] - IF( Хронология[[#This Row],[Результат]]="ПНВ", MAX(0, MAX(0, SUMIFS(Хронология[Часы], Хронология[Ключ], Хронология[[#This Row],[Ключ]], Хронология[Начало], "<=" & Хронология[[#This Row],[Начало]]) - IFERROR(INDEX(Планирование[Часы (план)], MATCH(Хронология[[#This Row],[Ключ]], Планирование[Ключ], 0)), 0)) - MAX(0, SUMIFS(Хронология[Часы], Хронология[Ключ], Хронология[[#This Row],[Ключ]], Хронология[Начало], "<" & Хронология[[#This Row],[Начало]]) - IFERROR(INDEX(Планирование[Часы (план)], MATCH(Хронология[[#This Row],[Ключ]], Планирование[Ключ], 0)), 0)) ), 0 ), 0 ) -> 7.5 | AL20: =IF( Хронология[[#This Row],[Результат]]="ПНВ", MAX(0, MAX(0, SUMIFS(Хронология[Часы], Хронология[Ключ], Хронология[[#This Row],[Ключ]], Хронология[Начало], "<=" & Хронология[[#This Row],[Начало]]) - IFERROR(INDEX(Планирование[Часы (план)], MATCH(Хронология[[#This Row],[Ключ]], Планирование[Ключ], 0)), 0)) - MAX(0, SUMIFS(Хронология[Часы], Хронология[Ключ], Хронология[[#This Row],[Ключ]], Хронология[Начало], "<" & Хронология[[#This Row],[Начало]]) - IFERROR(INDEX(Планирование[Часы (план)], MATCH(Хронология[[#This Row],[Ключ]], Планирование[Ключ], 0)), 0)) ), 0 ) -> 6 | AM20: =IF(Хронология[[#This Row],[Результат]]="НПВ", Хронология[[#This Row],[Часы]], 0) -> 0 | AN20: =SUMIFS(Хронология[НПВ], Хронология[Скважина], Хронология[[#This Row],[Скважина]], Хронология[Начало], "<=" & Хронология[[#This Row],[Начало]]) -> 9 | AO20: =SUMIFS(Хронология[ПНВ], Хронология[Скважина], Хронология[[#This Row],[Скважина]], Хронология[Начало], "<=" & Хронология[[#This Row],[Начало]]) -> 21.74 | AP20: =INT(ROUND(Хронология[[#This Row],[Начало]], 3)) -> 46148 | AQ20: =Хронология[[#This Row],[Начало]]-INT(Хронология[[#This Row],[Начало]]) -> 0.14583333 | AR20: =INT(ROUND(Хронология[[#This Row],[Окончание]], 3)) -> 46148 | AS20: =Хронология[[#This Row],[Окончание]]-INT(Хронология[[#This Row],[Окончание]]) -> 0.70833333 | AT20: =Хронология[[#This Row],[Мастер]] & CHAR(10) & Хронология[[#This Row],[Помощник мастера]] & CHAR(10) & Хронология[[#This Row],[Бурильщик]] -> Жабин П.П. Керимов Н.К. | AU20: =IF(Хронология[[#This Row],[Контекст простоя]]="Штатно", Хронология[[#This Row],[Скважина]] & " " & "ОК–" &Хронология[[#This Row],[ОК]] & " " & Хронология[[#This Row],[Этап]] & " " & Хронология[[#This Row],[Вид работ]] & " " & Хронология[[#This Row],[Объект работ]] & " " & Хронология[[#This Row],[Рейс]], Хронология[[#This Row],[Скважина]] & " " & "ОК–" &Хронология[[#This Row],[ОК]] & " " & Хронология[[#This Row],[Этап]] & " " & Хронология[[#This Row],[Контекст простоя]] & " " & Хронология[[#This Row],[Событие]] & " " & Хронология[[#This Row],[Вид работ]] & " " & Хронология[[#This Row],[Объект работ]] & " " & Хронология[[#This Row],[Рейс]]) -> 6 бис ОК– ДПМ Демонтаж УПА | AV20: =Хронология[[#This Row],[Результат]]&": "&Хронология[[#This Row],[Событие]]& CHAR(10) &Хронология[[#This Row],[Вид работ]]&" "&Хронология[[#This Row],[Объект работ]] -> ПНВ: Демонтаж УПА | AW20: =SUMIF($AU$2:AU20, Хронология[[#This Row],[Ключ]], $AH$2:AH20) -> 0.5625 | AX20: =Хронология[[#This Row],[Вид работ]] & " " & Хронология[[#This Row],[Объект работ]] -> Демонтаж УПА
A21: ГДТ | B21: КРС | C21: Казанское | D21: 1 | E21: 6 бис | F21: Вдовин И.О. | H21: Жангазиев С.К. | L21: ДПМ | M21: Штатно | O21: Монтаж_демонтаж_установка | P21: Демонтаж | Q21: Оборудование | R21: УПА | T21: Демонтаж БО | U21: 4.5 | W21: Работы окончены | X21: Победит Холдинг | AE21: =IFERROR(IF(Хронология[[#This Row],[Забой, м]]-V20<0, 0, Хронология[[#This Row],[Забой, м]]-V20), 0) -> 0 | AF21: =AG20 -> 46148.708 | AG21: =Хронология[[#This Row],[Начало]]+Хронология[[#This Row],[Сутки]] -> 46148.896 | AH21: =Хронология[[#This Row],[Часы]]/24 -> 0.1875 | AI21: =IFERROR(Хронология[[#This Row],[Сутки]]+AI20, Хронология[[#This Row],[Сутки]]) -> 4.0625 | AJ21: =IF(Хронология[[#This Row],[Этап]]="Доп. работы", "ПВ", IFERROR( IF(AND( MATCH(Хронология[[#This Row],[Ключ]], Планирование[Ключ], 0), Хронология[[#This Row],[Подытог за операцию]] <= INDEX(Планирование[Сутки (план)], MATCH(Хронология[[#This Row],[Ключ]], Планирование[Ключ], 0)) ), "ПВ", "ПНВ"), "НПВ")) -> ПНВ | AK21: =IF( OR(Хронология[[#This Row],[Результат]]="ПВ", Хронология[[#This Row],[Результат]]="ПНВ"), Хронология[[#This Row],[Часы]] - IF( Хронология[[#This Row],[Результат]]="ПНВ", MAX(0, MAX(0, SUMIFS(Хронология[Часы], Хронология[Ключ], Хронология[[#This Row],[Ключ]], Хронология[Начало], "<=" & Хронология[[#This Row],[Начало]]) - IFERROR(INDEX(Планирование[Часы (план)], MATCH(Хронология[[#This Row],[Ключ]], Планирование[Ключ], 0)), 0)) - MAX(0, SUMIFS(Хронология[Часы], Хронология[Ключ], Хронология[[#This Row],[Ключ]], Хронология[Начало], "<" & Хронология[[#This Row],[Начало]]) - IFERROR(INDEX(Планирование[Часы (план)], MATCH(Хронология[[#This Row],[Ключ]], Планирование[Ключ], 0)), 0)) ), 0 ), 0 ) -> 0 | AL21: =IF( Хронология[[#This Row],[Результат]]="ПНВ", MAX(0, MAX(0, SUMIFS(Хронология[Часы], Хронология[Ключ], Хронология[[#This Row],[Ключ]], Хронология[Начало], "<=" & Хронология[[#This Row],[Начало]]) - IFERROR(INDEX(Планирование[Часы (план)], MATCH(Хронология[[#This Row],[Ключ]], Планирование[Ключ], 0)), 0)) - MAX(0, SUMIFS(Хронология[Часы], Хронология[Ключ], Хронология[[#This Row],[Ключ]], Хронология[Начало], "<" & Хронология[[#This Row],[Начало]]) - IFERROR(INDEX(Планирование[Часы (план)], MATCH(Хронология[[#This Row],[Ключ]], Планирование[Ключ], 0)), 0)) ), 0 ) -> 4.5 | AM21: =IF(Хронология[[#This Row],[Результат]]="НПВ", Хронология[[#This Row],[Часы]], 0) -> 0 | AN21: =SUMIFS(Хронология[НПВ], Хронология[Скважина], Хронология[[#This Row],[Скважина]], Хронология[Начало], "<=" & Хронология[[#This Row],[Начало]]) -> 9 | AO21: =SUMIFS(Хронология[ПНВ], Хронология[Скважина], Хронология[[#This Row],[Скважина]], Хронология[Начало], "<=" & Хронология[[#This Row],[Начало]]) -> 26.24 | AP21: =INT(ROUND(Хронология[[#This Row],[Начало]], 3)) -> 46148 | AQ21: =Хронология[[#This Row],[Начало]]-INT(Хронология[[#This Row],[Начало]]) -> 0.70833333 | AR21: =INT(ROUND(Хронология[[#This Row],[Окончание]], 3)) -> 46148 | AS21: =Хронология[[#This Row],[Окончание]]-INT(Хронология[[#This Row],[Окончание]]) -> 0.89583333 | AT21: =Хронология[[#This Row],[Мастер]] & CHAR(10) & Хронология[[#This Row],[Помощник мастера]] & CHAR(10) & Хронология[[#This Row],[Бурильщик]] -> Вдовин И.О. Жангазиев С.К. | AU21: =IF(Хронология[[#This Row],[Контекст простоя]]="Штатно", Хронология[[#This Row],[Скважина]] & " " & "ОК–" &Хронология[[#This Row],[ОК]] & " " & Хронология[[#This Row],[Этап]] & " " & Хронология[[#This Row],[Вид работ]] & " " & Хронология[[#This Row],[Объект работ]] & " " & Хронология[[#This Row],[Рейс]], Хронология[[#This Row],[Скважина]] & " " & "ОК–" &Хронология[[#This Row],[ОК]] & " " & Хронология[[#This Row],[Этап]] & " " & Хронология[[#This Row],[Контекст простоя]] & " " & Хронология[[#This Row],[Событие]] & " " & Хронология[[#This Row],[Вид работ]] & " " & Хронология[[#This Row],[Объект работ]] & " " & Хронология[[#This Row],[Рейс]]) -> 6 бис ОК– ДПМ Демонтаж УПА | AV21: =Хронология[[#This Row],[Результат]]&": "&Хронология[[#This Row],[Событие]]& CHAR(10) &Хронология[[#This Row],[Вид работ]]&" "&Хронология[[#This Row],[Объект работ]] -> ПНВ: Демонтаж УПА | AW21: =SUMIF($AU$2:AU21, Хронология[[#This Row],[Ключ]], $AH$2:AH21) -> 0.75 | AX21: =Хронология[[#This Row],[Вид работ]] & " " & Хронология[[#This Row],[Объект работ]] -> Демонтаж УПА
A22: ГДТ | B22: КРС | C22: Казанское | D22: 1 | E22: 431 | F22: Вдовин И.О. | H22: Жангазиев С.К. | L22: ДПМ | M22: Штатно | O22: ПР | P22: Передвижка | Q22: Оборудование | R22: УПА | T22: ПР к переезду на скв. 431 КП26 Казанского НГКМ. | U22: 2.5 | W22: Работы окончены | X22: Победит Холдинг | AE22: =IFERROR(IF(Хронология[[#This Row],[Забой, м]]-V21<0, 0, Хронология[[#This Row],[Забой, м]]-V21), 0) -> 0 | AF22: =AG21 -> 46148.896 | AG22: =Хронология[[#This Row],[Начало]]+Хронология[[#This Row],[Сутки]] -> 46149 | AH22: =Хронология[[#This Row],[Часы]]/24 -> 0.10416667 | AI22: =IFERROR(Хронология[[#This Row],[Сутки]]+AI21, Хронология[[#This Row],[Сутки]]) -> 4.1666667 | AJ22: =IF(Хронология[[#This Row],[Этап]]="Доп. работы", "ПВ", IFERROR( IF(AND( MATCH(Хронология[[#This Row],[Ключ]], Планирование[Ключ], 0), Хронология[[#This Row],[Подытог за операцию]] <= INDEX(Планирование[Сутки (план)], MATCH(Хронология[[#This Row],[Ключ]], Планирование[Ключ], 0)) ), "ПВ", "ПНВ"), "НПВ")) -> ПВ | AK22: =IF( OR(Хронология[[#This Row],[Результат]]="ПВ", Хронология[[#This Row],[Результат]]="ПНВ"), Хронология[[#This Row],[Часы]] - IF( Хронология[[#This Row],[Результат]]="ПНВ", MAX(0, MAX(0, SUMIFS(Хронология[Часы], Хронология[Ключ], Хронология[[#This Row],[Ключ]], Хронология[Начало], "<=" & Хронология[[#This Row],[Начало]]) - IFERROR(INDEX(Планирование[Часы (план)], MATCH(Хронология[[#This Row],[Ключ]], Планирование[Ключ], 0)), 0)) - MAX(0, SUMIFS(Хронология[Часы], Хронология[Ключ], Хронология[[#This Row],[Ключ]], Хронология[Начало], "<" & Хронология[[#This Row],[Начало]]) - IFERROR(INDEX(Планирование[Часы (план)], MATCH(Хронология[[#This Row],[Ключ]], Планирование[Ключ], 0)), 0)) ), 0 ), 0 ) -> 2.5 | AL22: =IF( Хронология[[#This Row],[Результат]]="ПНВ", MAX(0, MAX(0, SUMIFS(Хронология[Часы], Хронология[Ключ], Хронология[[#This Row],[Ключ]], Хронология[Начало], "<=" & Хронология[[#This Row],[Начало]]) - IFERROR(INDEX(Планирование[Часы (план)], MATCH(Хронология[[#This Row],[Ключ]], Планирование[Ключ], 0)), 0)) - MAX(0, SUMIFS(Хронология[Часы], Хронология[Ключ], Хронология[[#This Row],[Ключ]], Хронология[Начало], "<" & Хронология[[#This Row],[Начало]]) - IFERROR(INDEX(Планирование[Часы (план)], MATCH(Хронология[[#This Row],[Ключ]], Планирование[Ключ], 0)), 0)) ), 0 ) -> 0 | AM22: =IF(Хронология[[#This Row],[Результат]]="НПВ", Хронология[[#This Row],[Часы]], 0) -> 0 | AN22: =SUMIFS(Хронология[НПВ], Хронология[Скважина], Хронология[[#This Row],[Скважина]], Хронология[Начало], "<=" & Хронология[[#This Row],[Начало]]) -> 0 | AO22: =SUMIFS(Хронология[ПНВ], Хронология[Скважина], Хронология[[#This Row],[Скважина]], Хронология[Начало], "<=" & Хронология[[#This Row],[Начало]]) -> 0 | AP22: =INT(ROUND(Хронология[[#This Row],[Начало]], 3)) -> 46148 | AQ22: =Хронология[[#This Row],[Начало]]-INT(Хронология[[#This Row],[Начало]]) -> 0.89583333 | AR22: =INT(ROUND(Хронология[[#This Row],[Окончание]], 3)) -> 46149 | AS22: =Хронология[[#This Row],[Окончание]]-INT(Хронология[[#This Row],[Окончание]]) -> 0 | AT22: =Хронология[[#This Row],[Мастер]] & CHAR(10) & Хронология[[#This Row],[Помощник мастера]] & CHAR(10) & Хронология[[#This Row],[Бурильщик]] -> Вдовин И.О. Жангазиев С.К. | AU22: =IF(Хронология[[#This Row],[Контекст простоя]]="Штатно", Хронология[[#This Row],[Скважина]] & " " & "ОК–" &Хронология[[#This Row],[ОК]] & " " & Хронология[[#This Row],[Этап]] & " " & Хронология[[#This Row],[Вид работ]] & " " & Хронология[[#This Row],[Объект работ]] & " " & Хронология[[#This Row],[Рейс]], Хронология[[#This Row],[Скважина]] & " " & "ОК–" &Хронология[[#This Row],[ОК]] & " " & Хронология[[#This Row],[Этап]] & " " & Хронология[[#This Row],[Контекст простоя]] & " " & Хронология[[#This Row],[Событие]] & " " & Хронология[[#This Row],[Вид работ]] & " " & Хронология[[#This Row],[Объект работ]] & " " & Хронология[[#This Row],[Рейс]]) -> 431 ОК– ДПМ Передвижка УПА | AV22: =Хронология[[#This Row],[Результат]]&": "&Хронология[[#This Row],[Событие]]& CHAR(10) &Хронология[[#This Row],[Вид работ]]&" "&Хронология[[#This Row],[Объект работ]] -> ПВ: Передвижка УПА | AW22: =SUMIF($AU$2:AU22, Хронология[[#This Row],[Ключ]], $AH$2:AH22) -> 0.10416667 | AX22: =Хронология[[#This Row],[Вид работ]] & " " & Хронология[[#This Row],[Объект работ]] -> Передвижка УПА
A23: ГДТ | B23: КРС | C23: Казанское | D23: 1 | E23: 431 | F23: Жабин П.П. | H23: Керимов Н.К. | L23: ДПМ | M23: Штатно | O23: ПР | P23: Передвижка | Q23: Оборудование | R23: УПА | T23: ПР к переезду на скв. 431 КП26 Казанского НГКМ. | U23: 7 | AE23: =IFERROR(IF(Хронология[[#This Row],[Забой, м]]-V22<0, 0, Хронология[[#This Row],[Забой, м]]-V22), 0) -> 0 | AF23: =AG22 -> 46149 | AG23: =Хронология[[#This Row],[Начало]]+Хронология[[#This Row],[Сутки]] -> 46149.292 | AH23: =Хронология[[#This Row],[Часы]]/24 -> 0.29166667 | AI23: =IFERROR(Хронология[[#This Row],[Сутки]]+AI22, Хронология[[#This Row],[Сутки]]) -> 4.4583333 | AJ23: =IF(Хронология[[#This Row],[Этап]]="Доп. работы", "ПВ", IFERROR( IF(AND( MATCH(Хронология[[#This Row],[Ключ]], Планирование[Ключ], 0), Хронология[[#This Row],[Подытог за операцию]] <= INDEX(Планирование[Сутки (план)], MATCH(Хронология[[#This Row],[Ключ]], Планирование[Ключ], 0)) ), "ПВ", "ПНВ"), "НПВ")) -> ПВ | AK23: =IF( OR(Хронология[[#This Row],[Результат]]="ПВ", Хронология[[#This Row],[Результат]]="ПНВ"), Хронология[[#This Row],[Часы]] - IF( Хронология[[#This Row],[Результат]]="ПНВ", MAX(0, MAX(0, SUMIFS(Хронология[Часы], Хронология[Ключ], Хронология[[#This Row],[Ключ]], Хронология[Начало], "<=" & Хронология[[#This Row],[Начало]]) - IFERROR(INDEX(Планирование[Часы (план)], MATCH(Хронология[[#This Row],[Ключ]], Планирование[Ключ], 0)), 0)) - MAX(0, SUMIFS(Хронология[Часы], Хронология[Ключ], Хронология[[#This Row],[Ключ]], Хронология[Начало], "<" & Хронология[[#This Row],[Начало]]) - IFERROR(INDEX(Планирование[Часы (план)], MATCH(Хронология[[#This Row],[Ключ]], Планирование[Ключ], 0)), 0)) ), 0 ), 0 ) -> 7 | AL23: =IF( Хронология[[#This Row],[Результат]]="ПНВ", MAX(0, MAX(0, SUMIFS(Хронология[Часы], Хронология[Ключ], Хронология[[#This Row],[Ключ]], Хронология[Начало], "<=" & Хронология[[#This Row],[Начало]]) - IFERROR(INDEX(Планирование[Часы (план)], MATCH(Хронология[[#This Row],[Ключ]], Планирование[Ключ], 0)), 0)) - MAX(0, SUMIFS(Хронология[Часы], Хронология[Ключ], Хронология[[#This Row],[Ключ]], Хронология[Начало], "<" & Хронология[[#This Row],[Начало]]) - IFERROR(INDEX(Планирование[Часы (план)], MATCH(Хронология[[#This Row],[Ключ]], Планирование[Ключ], 0)), 0)) ), 0 ) -> 0 | AM23: =IF(Хронология[[#This Row],[Результат]]="НПВ", Хронология[[#This Row],[Часы]], 0) -> 0 | AN23: =SUMIFS(Хронология[НПВ], Хронология[Скважина], Хронология[[#This Row],[Скважина]], Хронология[Начало], "<=" & Хронология[[#This Row],[Начало]]) -> 0 | AO23: =SUMIFS(Хронология[ПНВ], Хронология[Скважина], Хронология[[#This Row],[Скважина]], Хронология[Начало], "<=" & Хронология[[#This Row],[Начало]]) -> 0 | AP23: =INT(ROUND(Хронология[[#This Row],[Начало]], 3)) -> 46149 | AQ23: =Хронология[[#This Row],[Начало]]-INT(Хронология[[#This Row],[Начало]]) -> 0 | AR23: =INT(ROUND(Хронология[[#This Row],[Окончание]], 3)) -> 46149 | AS23: =Хронология[[#This Row],[Окончание]]-INT(Хронология[[#This Row],[Окончание]]) -> 0.29166667 | AT23: =Хронология[[#This Row],[Мастер]] & CHAR(10) & Хронология[[#This Row],[Помощник мастера]] & CHAR(10) & Хронология[[#This Row],[Бурильщик]] -> Жабин П.П. Керимов Н.К. | AU23: =IF(Хронология[[#This Row],[Контекст простоя]]="Штатно", Хронология[[#This Row],[Скважина]] & " " & "ОК–" &Хронология[[#This Row],[ОК]] & " " & Хронология[[#This Row],[Этап]] & " " & Хронология[[#This Row],[Вид работ]] & " " & Хронология[[#This Row],[Объект работ]] & " " & Хронология[[#This Row],[Рейс]], Хронология[[#This Row],[Скважина]] & " " & "ОК–" &Хронология[[#This Row],[ОК]] & " " & Хронология[[#This Row],[Этап]] & " " & Хронология[[#This Row],[Контекст простоя]] & " " & Хронология[[#This Row],[Событие]] & " " & Хронология[[#This Row],[Вид работ]] & " " & Хронология[[#This Row],[Объект работ]] & " " & Хронология[[#This Row],[Рейс]]) -> 431 ОК– ДПМ Передвижка УПА | AV23: =Хронология[[#This Row],[Результат]]&": "&Хронология[[#This Row],[Событие]]& CHAR(10) &Хронология[[#This Row],[Вид работ]]&" "&Хронология[[#This Row],[Объект работ]] -> ПВ: Передвижка УПА | AW23: =SUMIF($AU$2:AU23, Хронология[[#This Row],[Ключ]], $AH$2:AH23) -> 0.39583333 | AX23: =Хронология[[#This Row],[Вид работ]] & " " & Хронология[[#This Row],[Объект работ]] -> Передвижка УПА
A24: ГДТ | B24: КРС | C24: Казанское | D24: 1 | E24: 431 | F24: Вдовин И.О. | H24: Жангазиев С.К. | L24: ДПМ | M24: Штатно | O24: ПР | P24: Передвижка | Q24: Оборудование | R24: УПА | T24: ПР и переезд на скв. 431 КП26 Казанского НГКМ — 4 рейса/10. Подключение вагон-городка. | U24: 5 | AE24: =IFERROR(IF(Хронология[[#This Row],[Забой, м]]-V23<0, 0, Хронология[[#This Row],[Забой, м]]-V23), 0) -> 0 | AF24: =AG23 -> 46149.292 | AG24: =Хронология[[#This Row],[Начало]]+Хронология[[#This Row],[Сутки]] -> 46149.5 | AH24: =Хронология[[#This Row],[Часы]]/24 -> 0.20833333 | AI24: =IFERROR(Хронология[[#This Row],[Сутки]]+AI23, Хронология[[#This Row],[Сутки]]) -> 4.6666667 | AJ24: =IF(Хронология[[#This Row],[Этап]]="Доп. работы", "ПВ", IFERROR( IF(AND( MATCH(Хронология[[#This Row],[Ключ]], Планирование[Ключ], 0), Хронология[[#This Row],[Подытог за операцию]] <= INDEX(Планирование[Сутки (план)], MATCH(Хронология[[#This Row],[Ключ]], Планирование[Ключ], 0)) ), "ПВ", "ПНВ"), "НПВ")) -> ПВ | AK24: =IF( OR(Хронология[[#This Row],[Результат]]="ПВ", Хронология[[#This Row],[Результат]]="ПНВ"), Хронология[[#This Row],[Часы]] - IF( Хронология[[#This Row],[Результат]]="ПНВ", MAX(0, MAX(0, SUMIFS(Хронология[Часы], Хронология[Ключ], Хронология[[#This Row],[Ключ]], Хронология[Начало], "<=" & Хронология[[#This Row],[Начало]]) - IFERROR(INDEX(Планирование[Часы (план)], MATCH(Хронология[[#This Row],[Ключ]], Планирование[Ключ], 0)), 0)) - MAX(0, SUMIFS(Хронология[Часы], Хронология[Ключ], Хронология[[#This Row],[Ключ]], Хронология[Начало], "<" & Хронология[[#This Row],[Начало]]) - IFERROR(INDEX(Планирование[Часы (план)], MATCH(Хронология[[#This Row],[Ключ]], Планирование[Ключ], 0)), 0)) ), 0 ), 0 ) -> 5 | AL24: =IF( Хронология[[#This Row],[Результат]]="ПНВ", MAX(0, MAX(0, SUMIFS(Хронология[Часы], Хронология[Ключ], Хронология[[#This Row],[Ключ]], Хронология[Начало], "<=" & Хронология[[#This Row],[Начало]]) - IFERROR(INDEX(Планирование[Часы (план)], MATCH(Хронология[[#This Row],[Ключ]], Планирование[Ключ], 0)), 0)) - MAX(0, SUMIFS(Хронология[Часы], Хронология[Ключ], Хронология[[#This Row],[Ключ]], Хронология[Начало], "<" & Хронология[[#This Row],[Начало]]) - IFERROR(INDEX(Планирование[Часы (план)], MATCH(Хронология[[#This Row],[Ключ]], Планирование[Ключ], 0)), 0)) ), 0 ) -> 0 | AM24: =IF(Хронология[[#This Row],[Результат]]="НПВ", Хронология[[#This Row],[Часы]], 0) -> 0 | AN24: =SUMIFS(Хронология[НПВ], Хронология[Скважина], Хронология[[#This Row],[Скважина]], Хронология[Начало], "<=" & Хронология[[#This Row],[Начало]]) -> 0 | AO24: =SUMIFS(Хронология[ПНВ], Хронология[Скважина], Хронология[[#This Row],[Скважина]], Хронология[Начало], "<=" & Хронология[[#This Row],[Начало]]) -> 0 | AP24: =INT(ROUND(Хронология[[#This Row],[Начало]], 3)) -> 46149 | AQ24: =Хронология[[#This Row],[Начало]]-INT(Хронология[[#This Row],[Начало]]) -> 0.29166667 | AR24: =INT(ROUND(Хронология[[#This Row],[Окончание]], 3)) -> 46149 | AS24: =Хронология[[#This Row],[Окончание]]-INT(Хронология[[#This Row],[Окончание]]) -> 0.5 | AT24: =Хронология[[#This Row],[Мастер]] & CHAR(10) & Хронология[[#This Row],[Помощник мастера]] & CHAR(10) & Хронология[[#This Row],[Бурильщик]] -> Вдовин И.О. Жангазиев С.К. | AU24: =IF(Хронология[[#This Row],[Контекст простоя]]="Штатно", Хронология[[#This Row],[Скважина]] & " " & "ОК–" &Хронология[[#This Row],[ОК]] & " " & Хронология[[#This Row],[Этап]] & " " & Хронология[[#This Row],[Вид работ]] & " " & Хронология[[#This Row],[Объект работ]] & " " & Хронология[[#This Row],[Рейс]], Хронология[[#This Row],[Скважина]] & " " & "ОК–" &Хронология[[#This Row],[ОК]] & " " & Хронология[[#This Row],[Этап]] & " " & Хронология[[#This Row],[Контекст простоя]] & " " & Хронология[[#This Row],[Событие]] & " " & Хронология[[#This Row],[Вид работ]] & " " & Хронология[[#This Row],[Объект работ]] & " " & Хронология[[#This Row],[Рейс]]) -> 431 ОК– ДПМ Передвижка УПА | AV24: =Хронология[[#This Row],[Результат]]&": "&Хронология[[#This Row],[Событие]]& CHAR(10) &Хронология[[#This Row],[Вид работ]]&" "&Хронология[[#This Row],[Объект работ]] -> ПВ: Передвижка УПА | AW24: =SUMIF($AU$2:AU24, Хронология[[#This Row],[Ключ]], $AH$2:AH24) -> 0.60416667 | AX24: =Хронология[[#This Row],[Вид работ]] & " " & Хронология[[#This Row],[Объект работ]] -> Передвижка УПА
A25: ГДТ | B25: КРС | C25: Казанское | D25: 1 | E25: 431 | F25: Вдовин И.О. | H25: Жангазиев С.К. | L25: ДПМ | M25: Штатно | O25: ПР | P25: Передвижка | Q25: Оборудование | R25: УПА | T25: ПР и переезд на скв. 431 КП26 Казанского НГКМ — 5 рейсов/10. Зачистка территории прилегающей к скв. 6 бис, КП 1 бис. Покраска ФА. | U25: 4 | W25: Работы окончены | X25: Победит Холдинг | AE25: =IFERROR(IF(Хронология[[#This Row],[Забой, м]]-V24<0, 0, Хронология[[#This Row],[Забой, м]]-V24), 0) -> 0 | AF25: =AG24 -> 46149.5 | AG25: =Хронология[[#This Row],[Начало]]+Хронология[[#This Row],[Сутки]] -> 46149.667 | AH25: =Хронология[[#This Row],[Часы]]/24 -> 0.16666667 | AI25: =IFERROR(Хронология[[#This Row],[Сутки]]+AI24, Хронология[[#This Row],[Сутки]]) -> 4.8333333 | AJ25: =IF(Хронология[[#This Row],[Этап]]="Доп. работы", "ПВ", IFERROR( IF(AND( MATCH(Хронология[[#This Row],[Ключ]], Планирование[Ключ], 0), Хронология[[#This Row],[Подытог за операцию]] <= INDEX(Планирование[Сутки (план)], MATCH(Хронология[[#This Row],[Ключ]], Планирование[Ключ], 0)) ), "ПВ", "ПНВ"), "НПВ")) -> ПНВ | AK25: =IF( OR(Хронология[[#This Row],[Результат]]="ПВ", Хронология[[#This Row],[Результат]]="ПНВ"), Хронология[[#This Row],[Часы]] - IF( Хронология[[#This Row],[Результат]]="ПНВ", MAX(0, MAX(0, SUMIFS(Хронология[Часы], Хронология[Ключ], Хронология[[#This Row],[Ключ]], Хронология[Начало], "<=" & Хронология[[#This Row],[Начало]]) - IFERROR(INDEX(Планирование[Часы (план)], MATCH(Хронология[[#This Row],[Ключ]], Планирование[Ключ], 0)), 0)) - MAX(0, SUMIFS(Хронология[Часы], Хронология[Ключ], Хронология[[#This Row],[Ключ]], Хронология[Начало], "<" & Хронология[[#This Row],[Начало]]) - IFERROR(INDEX(Планирование[Часы (план)], MATCH(Хронология[[#This Row],[Ключ]], Планирование[Ключ], 0)), 0)) ), 0 ), 0 ) -> 1.97 | AL25: =IF( Хронология[[#This Row],[Результат]]="ПНВ", MAX(0, MAX(0, SUMIFS(Хронология[Часы], Хронология[Ключ], Хронология[[#This Row],[Ключ]], Хронология[Начало], "<=" & Хронология[[#This Row],[Начало]]) - IFERROR(INDEX(Планирование[Часы (план)], MATCH(Хронология[[#This Row],[Ключ]], Планирование[Ключ], 0)), 0)) - MAX(0, SUMIFS(Хронология[Часы], Хронология[Ключ], Хронология[[#This Row],[Ключ]], Хронология[Начало], "<" & Хронология[[#This Row],[Начало]]) - IFERROR(INDEX(Планирование[Часы (план)], MATCH(Хронология[[#This Row],[Ключ]], Планирование[Ключ], 0)), 0)) ), 0 ) -> 2.03 | AM25: =IF(Хронология[[#This Row],[Результат]]="НПВ", Хронология[[#This Row],[Часы]], 0) -> 0 | AN25: =SUMIFS(Хронология[НПВ], Хронология[Скважина], Хронология[[#This Row],[Скважина]], Хронология[Начало], "<=" & Хронология[[#This Row],[Начало]]) -> 0 | AO25: =SUMIFS(Хронология[ПНВ], Хронология[Скважина], Хронология[[#This Row],[Скважина]], Хронология[Начало], "<=" & Хронология[[#This Row],[Начало]]) -> 2.03 | AP25: =INT(ROUND(Хронология[[#This Row],[Начало]], 3)) -> 46149 | AQ25: =Хронология[[#This Row],[Начало]]-INT(Хронология[[#This Row],[Начало]]) -> 0.5 | AR25: =INT(ROUND(Хронология[[#This Row],[Окончание]], 3)) -> 46149 | AS25: =Хронология[[#This Row],[Окончание]]-INT(Хронология[[#This Row],[Окончание]]) -> 0.66666667 | AT25: =Хронология[[#This Row],[Мастер]] & CHAR(10) & Хронология[[#This Row],[Помощник мастера]] & CHAR(10) & Хронология[[#This Row],[Бурильщик]] -> Вдовин И.О. Жангазиев С.К. | AU25: =IF(Хронология[[#This Row],[Контекст простоя]]="Штатно", Хронология[[#This Row],[Скважина]] & " " & "ОК–" &Хронология[[#This Row],[ОК]] & " " & Хронология[[#This Row],[Этап]] & " " & Хронология[[#This Row],[Вид работ]] & " " & Хронология[[#This Row],[Объект работ]] & " " & Хронология[[#This Row],[Рейс]], Хронология[[#This Row],[Скважина]] & " " & "ОК–" &Хронология[[#This Row],[ОК]] & " " & Хронология[[#This Row],[Этап]] & " " & Хронология[[#This Row],[Контекст простоя]] & " " & Хронология[[#This Row],[Событие]] & " " & Хронология[[#This Row],[Вид работ]] & " " & Хронология[[#This Row],[Объект работ]] & " " & Хронология[[#This Row],[Рейс]]) -> 431 ОК– ДПМ Передвижка УПА | AV25: =Хронология[[#This Row],[Результат]]&": "&Хронология[[#This Row],[Событие]]& CHAR(10) &Хронология[[#This Row],[Вид работ]]&" "&Хронология[[#This Row],[Объект работ]] -> ПНВ: Передвижка УПА | AW25: =SUMIF($AU$2:AU25, Хронология[[#This Row],[Ключ]], $AH$2:AH25) -> 0.77083333 | AX25: =Хронология[[#This Row],[Вид работ]] & " " & Хронология[[#This Row],[Объект работ]] -> Передвижка УПА
A26: ГДТ | B26: КРС | C26: Казанское | D26: 1 | E26: 431 | F26: Вдовин И.О. | H26: Жангазиев С.К. | L26: ДПМ | M26: Штатно | O26: ПР | P26: Передвижка | Q26: Оборудование | R26: УПА | T26: Переезд на скв. 431 КП26 Казанского НГКМ — 6 рейсов/10. | U26: 4 | W26: Работы окончены | X26: Победит Холдинг | AE26: =IFERROR(IF(Хронология[[#This Row],[Забой, м]]-V25<0, 0, Хронология[[#This Row],[Забой, м]]-V25), 0) -> 0 | AF26: =AG25 -> 46149.667 | AG26: =Хронология[[#This Row],[Начало]]+Хронология[[#This Row],[Сутки]] -> 46149.833 | AH26: =Хронология[[#This Row],[Часы]]/24 -> 0.16666667 | AI26: =IFERROR(Хронология[[#This Row],[Сутки]]+AI25, Хронология[[#This Row],[Сутки]]) -> 5 | AJ26: =IF(Хронология[[#This Row],[Этап]]="Доп. работы", "ПВ", IFERROR( IF(AND( MATCH(Хронология[[#This Row],[Ключ]], Планирование[Ключ], 0), Хронология[[#This Row],[Подытог за операцию]] <= INDEX(Планирование[Сутки (план)], MATCH(Хронология[[#This Row],[Ключ]], Планирование[Ключ], 0)) ), "ПВ", "ПНВ"), "НПВ")) -> ПНВ | AK26: =IF( OR(Хронология[[#This Row],[Результат]]="ПВ", Хронология[[#This Row],[Результат]]="ПНВ"), Хронология[[#This Row],[Часы]] - IF( Хронология[[#This Row],[Результат]]="ПНВ", MAX(0, MAX(0, SUMIFS(Хронология[Часы], Хронология[Ключ], Хронология[[#This Row],[Ключ]], Хронология[Начало], "<=" & Хронология[[#This Row],[Начало]]) - IFERROR(INDEX(Планирование[Часы (план)], MATCH(Хронология[[#This Row],[Ключ]], Планирование[Ключ], 0)), 0)) - MAX(0, SUMIFS(Хронология[Часы], Хронология[Ключ], Хронология[[#This Row],[Ключ]], Хронология[Начало], "<" & Хронология[[#This Row],[Начало]]) - IFERROR(INDEX(Планирование[Часы (план)], MATCH(Хронология[[#This Row],[Ключ]], Планирование[Ключ], 0)), 0)) ), 0 ), 0 ) -> 0 | AL26: =IF( Хронология[[#This Row],[Результат]]="ПНВ", MAX(0, MAX(0, SUMIFS(Хронология[Часы], Хронология[Ключ], Хронология[[#This Row],[Ключ]], Хронология[Начало], "<=" & Хронология[[#This Row],[Начало]]) - IFERROR(INDEX(Планирование[Часы (план)], MATCH(Хронология[[#This Row],[Ключ]], Планирование[Ключ], 0)), 0)) - MAX(0, SUMIFS(Хронология[Часы], Хронология[Ключ], Хронология[[#This Row],[Ключ]], Хронология[Начало], "<" & Хронология[[#This Row],[Начало]]) - IFERROR(INDEX(Планирование[Часы (план)], MATCH(Хронология[[#This Row],[Ключ]], Планирование[Ключ], 0)), 0)) ), 0 ) -> 4 | AM26: =IF(Хронология[[#This Row],[Результат]]="НПВ", Хронология[[#This Row],[Часы]], 0) -> 0 | AN26: =SUMIFS(Хронология[НПВ], Хронология[Скважина], Хронология[[#This Row],[Скважина]], Хронология[Начало], "<=" & Хронология[[#This Row],[Начало]]) -> 0 | AO26: =SUMIFS(Хронология[ПНВ], Хронология[Скважина], Хронология[[#This Row],[Скважина]], Хронология[Начало], "<=" & Хронология[[#This Row],[Начало]]) -> 6.03 | AP26: =INT(ROUND(Хронология[[#This Row],[Начало]], 3)) -> 46149 | AQ26: =Хронология[[#This Row],[Начало]]-INT(Хронология[[#This Row],[Начало]]) -> 0.66666667 | AR26: =INT(ROUND(Хронология[[#This Row],[Окончание]], 3)) -> 46149 | AS26: =Хронология[[#This Row],[Окончание]]-INT(Хронология[[#This Row],[Окончание]]) -> 0.83333333 | AT26: =Хронология[[#This Row],[Мастер]] & CHAR(10) & Хронология[[#This Row],[Помощник мастера]] & CHAR(10) & Хронология[[#This Row],[Бурильщик]] -> Вдовин И.О. Жангазиев С.К. | AU26: =IF(Хронология[[#This Row],[Контекст простоя]]="Штатно", Хронология[[#This Row],[Скважина]] & " " & "ОК–" &Хронология[[#This Row],[ОК]] & " " & Хронология[[#This Row],[Этап]] & " " & Хронология[[#This Row],[Вид работ]] & " " & Хронология[[#This Row],[Объект работ]] & " " & Хронология[[#This Row],[Рейс]], Хронология[[#This Row],[Скважина]] & " " & "ОК–" &Хронология[[#This Row],[ОК]] & " " & Хронология[[#This Row],[Этап]] & " " & Хронология[[#This Row],[Контекст простоя]] & " " & Хронология[[#This Row],[Событие]] & " " & Хронология[[#This Row],[Вид работ]] & " " & Хронология[[#This Row],[Объект работ]] & " " & Хронология[[#This Row],[Рейс]]) -> 431 ОК– ДПМ Передвижка УПА | AV26: =Хронология[[#This Row],[Результат]]&": "&Хронология[[#This Row],[Событие]]& CHAR(10) &Хронология[[#This Row],[Вид работ]]&" "&Хронология[[#This Row],[Объект работ]] -> ПНВ: Передвижка УПА | AW26: =SUMIF($AU$2:AU26, Хронология[[#This Row],[Ключ]], $AH$2:AH26) -> 0.9375 | AX26: =Хронология[[#This Row],[Вид работ]] & " " & Хронология[[#This Row],[Объект работ]] -> Передвижка УПА
A27: ГДТ | B27: КРС | C27: Казанское | D27: 1 | E27: 431 | F27: Вдовин И.О. | H27: Жангазиев С.К. | L27: ДПМ | M27: Штатно | O27: ПР | P27: Передвижка | Q27: Оборудование | R27: УПА | T27: Переезд на скв. 431 КП26 Казанского НГКМ — 7 рейсов/10. | U27: 4 | W27: Работы окончены | X27: Победит Холдинг | AE27: =IFERROR(IF(Хронология[[#This Row],[Забой, м]]-V26<0, 0, Хронология[[#This Row],[Забой, м]]-V26), 0) -> 0 | AF27: =AG26 -> 46149.833 | AG27: =Хронология[[#This Row],[Начало]]+Хронология[[#This Row],[Сутки]] -> 46150 | AH27: =Хронология[[#This Row],[Часы]]/24 -> 0.16666667 | AI27: =IFERROR(Хронология[[#This Row],[Сутки]]+AI26, Хронология[[#This Row],[Сутки]]) -> 5.1666667 | AJ27: =IF(Хронология[[#This Row],[Этап]]="Доп. работы", "ПВ", IFERROR( IF(AND( MATCH(Хронология[[#This Row],[Ключ]], Планирование[Ключ], 0), Хронология[[#This Row],[Подытог за операцию]] <= INDEX(Планирование[Сутки (план)], MATCH(Хронология[[#This Row],[Ключ]], Планирование[Ключ], 0)) ), "ПВ", "ПНВ"), "НПВ")) -> ПНВ | AK27: =IF( OR(Хронология[[#This Row],[Результат]]="ПВ", Хронология[[#This Row],[Результат]]="ПНВ"), Хронология[[#This Row],[Часы]] - IF( Хронология[[#This Row],[Результат]]="ПНВ", MAX(0, MAX(0, SUMIFS(Хронология[Часы], Хронология[Ключ], Хронология[[#This Row],[Ключ]], Хронология[Начало], "<=" & Хронология[[#This Row],[Начало]]) - IFERROR(INDEX(Планирование[Часы (план)], MATCH(Хронология[[#This Row],[Ключ]], Планирование[Ключ], 0)), 0)) - MAX(0, SUMIFS(Хронология[Часы], Хронология[Ключ], Хронология[[#This Row],[Ключ]], Хронология[Начало], "<" & Хронология[[#This Row],[Начало]]) - IFERROR(INDEX(Планирование[Часы (план)], MATCH(Хронология[[#This Row],[Ключ]], Планирование[Ключ], 0)), 0)) ), 0 ), 0 ) -> 0 | AL27: =IF( Хронология[[#This Row],[Результат]]="ПНВ", MAX(0, MAX(0, SUMIFS(Хронология[Часы], Хронология[Ключ], Хронология[[#This Row],[Ключ]], Хронология[Начало], "<=" & Хронология[[#This Row],[Начало]]) - IFERROR(INDEX(Планирование[Часы (план)], MATCH(Хронология[[#This Row],[Ключ]], Планирование[Ключ], 0)), 0)) - MAX(0, SUMIFS(Хронология[Часы], Хронология[Ключ], Хронология[[#This Row],[Ключ]], Хронология[Начало], "<" & Хронология[[#This Row],[Начало]]) - IFERROR(INDEX(Планирование[Часы (план)], MATCH(Хронология[[#This Row],[Ключ]], Планирование[Ключ], 0)), 0)) ), 0 ) -> 4 | AM27: =IF(Хронология[[#This Row],[Результат]]="НПВ", Хронология[[#This Row],[Часы]], 0) -> 0 | AN27: =SUMIFS(Хронология[НПВ], Хронология[Скважина], Хронология[[#This Row],[Скважина]], Хронология[Начало], "<=" & Хронология[[#This Row],[Начало]]) -> 0 | AO27: =SUMIFS(Хронология[ПНВ], Хронология[Скважина], Хронология[[#This Row],[Скважина]], Хронология[Начало], "<=" & Хронология[[#This Row],[Начало]]) -> 10.03 | AP27: =INT(ROUND(Хронология[[#This Row],[Начало]], 3)) -> 46149 | AQ27: =Хронология[[#This Row],[Начало]]-INT(Хронология[[#This Row],[Начало]]) -> 0.83333333 | AR27: =INT(ROUND(Хронология[[#This Row],[Окончание]], 3)) -> 46150 | AS27: =Хронология[[#This Row],[Окончание]]-INT(Хронология[[#This Row],[Окончание]]) -> 0 | AT27: =Хронология[[#This Row],[Мастер]] & CHAR(10) & Хронология[[#This Row],[Помощник мастера]] & CHAR(10) & Хронология[[#This Row],[Бурильщик]] -> Вдовин И.О. Жангазиев С.К. | AU27: =IF(Хронология[[#This Row],[Контекст простоя]]="Штатно", Хронология[[#This Row],[Скважина]] & " " & "ОК–" &Хронология[[#This Row],[ОК]] & " " & Хронология[[#This Row],[Этап]] & " " & Хронология[[#This Row],[Вид работ]] & " " & Хронология[[#This Row],[Объект работ]] & " " & Хронология[[#This Row],[Рейс]], Хронология[[#This Row],[Скважина]] & " " & "ОК–" &Хронология[[#This Row],[ОК]] & " " & Хронология[[#This Row],[Этап]] & " " & Хронология[[#This Row],[Контекст простоя]] & " " & Хронология[[#This Row],[Событие]] & " " & Хронология[[#This Row],[Вид работ]] & " " & Хронология[[#This Row],[Объект работ]] & " " & Хронология[[#This Row],[Рейс]]) -> 431 ОК– ДПМ Передвижка УПА | AV27: =Хронология[[#This Row],[Результат]]&": "&Хронология[[#This Row],[Событие]]& CHAR(10) &Хронология[[#This Row],[Вид работ]]&" "&Хронология[[#This Row],[Объект работ]] -> ПНВ: Передвижка УПА | AW27: =SUMIF($AU$2:AU27, Хронология[[#This Row],[Ключ]], $AH$2:AH27) -> 1.1041667 | AX27: =Хронология[[#This Row],[Вид работ]] & " " & Хронология[[#This Row],[Объект работ]] -> Передвижка УПА
A28: ГДТ | B28: КРС | C28: Казанское | D28: 1 | E28: 431 | F28: Жабин П.П. | H28: Керимов Н.К. | L28: ДПМ | M28: Штатно | O28: ПР | P28: Передвижка | Q28: Оборудование | R28: УПА | T28: Переезд на скв. 431 КП26 Казанского НГКМ — 7 рейсов/10 (вагон-дом, мостки, стеллажи, ПВО, пригрузы, автовымотка, емкость 25м³, УПРСБ-80). | U28: 7 | W28: Работы окончены | X28: Победит Холдинг | AE28: =IFERROR(IF(Хронология[[#This Row],[Забой, м]]-V27<0, 0, Хронология[[#This Row],[Забой, м]]-V27), 0) -> 0 | AF28: =AG27 -> 46150 | AG28: =Хронология[[#This Row],[Начало]]+Хронология[[#This Row],[Сутки]] -> 46150.292 | AH28: =Хронология[[#This Row],[Часы]]/24 -> 0.29166667 | AI28: =IFERROR(Хронология[[#This Row],[Сутки]]+AI27, Хронология[[#This Row],[Сутки]]) -> 5.4583333 | AJ28: =IF(Хронология[[#This Row],[Этап]]="Доп. работы", "ПВ", IFERROR( IF(AND( MATCH(Хронология[[#This Row],[Ключ]], Планирование[Ключ], 0), Хронология[[#This Row],[Подытог за операцию]] <= INDEX(Планирование[Сутки (план)], MATCH(Хронология[[#This Row],[Ключ]], Планирование[Ключ], 0)) ), "ПВ", "ПНВ"), "НПВ")) -> ПНВ | AK28: =IF( OR(Хронология[[#This Row],[Результат]]="ПВ", Хронология[[#This Row],[Результат]]="ПНВ"), Хронология[[#This Row],[Часы]] - IF( Хронология[[#This Row],[Результат]]="ПНВ", MAX(0, MAX(0, SUMIFS(Хронология[Часы], Хронология[Ключ], Хронология[[#This Row],[Ключ]], Хронология[Начало], "<=" & Хронология[[#This Row],[Начало]]) - IFERROR(INDEX(Планирование[Часы (план)], MATCH(Хронология[[#This Row],[Ключ]], Планирование[Ключ], 0)), 0)) - MAX(0, SUMIFS(Хронология[Часы], Хронология[Ключ], Хронология[[#This Row],[Ключ]], Хронология[Начало], "<" & Хронология[[#This Row],[Начало]]) - IFERROR(INDEX(Планирование[Часы (план)], MATCH(Хронология[[#This Row],[Ключ]], Планирование[Ключ], 0)), 0)) ), 0 ), 0 ) -> 0 | AL28: =IF( Хронология[[#This Row],[Результат]]="ПНВ", MAX(0, MAX(0, SUMIFS(Хронология[Часы], Хронология[Ключ], Хронология[[#This Row],[Ключ]], Хронология[Начало], "<=" & Хронология[[#This Row],[Начало]]) - IFERROR(INDEX(Планирование[Часы (план)], MATCH(Хронология[[#This Row],[Ключ]], Планирование[Ключ], 0)), 0)) - MAX(0, SUMIFS(Хронология[Часы], Хронология[Ключ], Хронология[[#This Row],[Ключ]], Хронология[Начало], "<" & Хронология[[#This Row],[Начало]]) - IFERROR(INDEX(Планирование[Часы (план)], MATCH(Хронология[[#This Row],[Ключ]], Планирование[Ключ], 0)), 0)) ), 0 ) -> 7 | AM28: =IF(Хронология[[#This Row],[Результат]]="НПВ", Хронология[[#This Row],[Часы]], 0) -> 0 | AN28: =SUMIFS(Хронология[НПВ], Хронология[Скважина], Хронология[[#This Row],[Скважина]], Хронология[Начало], "<=" & Хронология[[#This Row],[Начало]]) -> 0 | AO28: =SUMIFS(Хронология[ПНВ], Хронология[Скважина], Хронология[[#This Row],[Скважина]], Хронология[Начало], "<=" & Хронология[[#This Row],[Начало]]) -> 17.03 | AP28: =INT(ROUND(Хронология[[#This Row],[Начало]], 3)) -> 46150 | AQ28: =Хронология[[#This Row],[Начало]]-INT(Хронология[[#This Row],[Начало]]) -> 0 | AR28: =INT(ROUND(Хронология[[#This Row],[Окончание]], 3)) -> 46150 | AS28: =Хронология[[#This Row],[Окончание]]-INT(Хронология[[#This Row],[Окончание]]) -> 0.29166667 | AT28: =Хронология[[#This Row],[Мастер]] & CHAR(10) & Хронология[[#This Row],[Помощник мастера]] & CHAR(10) & Хронология[[#This Row],[Бурильщик]] -> Жабин П.П. Керимов Н.К. | AU28: =IF(Хронология[[#This Row],[Контекст простоя]]="Штатно", Хронология[[#This Row],[Скважина]] & " " & "ОК–" &Хронология[[#This Row],[ОК]] & " " & Хронология[[#This Row],[Этап]] & " " & Хронология[[#This Row],[Вид работ]] & " " & Хронология[[#This Row],[Объект работ]] & " " & Хронология[[#This Row],[Рейс]], Хронология[[#This Row],[Скважина]] & " " & "ОК–" &Хронология[[#This Row],[ОК]] & " " & Хронология[[#This Row],[Этап]] & " " & Хронология[[#This Row],[Контекст простоя]] & " " & Хронология[[#This Row],[Событие]] & " " & Хронология[[#This Row],[Вид работ]] & " " & Хронология[[#This Row],[Объект работ]] & " " & Хронология[[#This Row],[Рейс]]) -> 431 ОК– ДПМ Передвижка УПА | AV28: =Хронология[[#This Row],[Результат]]&": "&Хронология[[#This Row],[Событие]]& CHAR(10) &Хронология[[#This Row],[Вид работ]]&" "&Хронология[[#This Row],[Объект работ]] -> ПНВ: Передвижка УПА | AW28: =SUMIF($AU$2:AU28, Хронология[[#This Row],[Ключ]], $AH$2:AH28) -> 1.3958333 | AX28: =Хронология[[#This Row],[Вид работ]] & " " & Хронология[[#This Row],[Объект работ]] -> Передвижка УПА
A29: ГДТ | B29: КРС | C29: Казанское | D29: 1 | E29: 431 | F29: Вдовин И.О. | H29: Жангазиев С.К. | L29: ДПМ | M29: Штатно | O29: ПР | P29: Передвижка | Q29: Оборудование | R29: УПА | T29: Мобилизация 70%. Получение наряд-допуска на одновременные работы по скв. 431 КП26 Казанского НГКМ. | U29: 5 | W29: Работы окончены | X29: Победит Холдинг | AE29: =IFERROR(IF(Хронология[[#This Row],[Забой, м]]-V28<0, 0, Хронология[[#This Row],[Забой, м]]-V28), 0) -> 0 | AF29: =AG28 -> 46150.292 | AG29: =Хронология[[#This Row],[Начало]]+Хронология[[#This Row],[Сутки]] -> 46150.5 | AH29: =Хронология[[#This Row],[Часы]]/24 -> 0.20833333 | AI29: =IFERROR(Хронология[[#This Row],[Сутки]]+AI28, Хронология[[#This Row],[Сутки]]) -> 5.6666667 | AJ29: =IF(Хронология[[#This Row],[Этап]]="Доп. работы", "ПВ", IFERROR( IF(AND( MATCH(Хронология[[#This Row],[Ключ]], Планирование[Ключ], 0), Хронология[[#This Row],[Подытог за операцию]] <= INDEX(Планирование[Сутки (план)], MATCH(Хронология[[#This Row],[Ключ]], Планирование[Ключ], 0)) ), "ПВ", "ПНВ"), "НПВ")) -> ПНВ | AK29: =IF( OR(Хронология[[#This Row],[Результат]]="ПВ", Хронология[[#This Row],[Результат]]="ПНВ"), Хронология[[#This Row],[Часы]] - IF( Хронология[[#This Row],[Результат]]="ПНВ", MAX(0, MAX(0, SUMIFS(Хронология[Часы], Хронология[Ключ], Хронология[[#This Row],[Ключ]], Хронология[Начало], "<=" & Хронология[[#This Row],[Начало]]) - IFERROR(INDEX(Планирование[Часы (план)], MATCH(Хронология[[#This Row],[Ключ]], Планирование[Ключ], 0)), 0)) - MAX(0, SUMIFS(Хронология[Часы], Хронология[Ключ], Хронология[[#This Row],[Ключ]], Хронология[Начало], "<" & Хронология[[#This Row],[Начало]]) - IFERROR(INDEX(Планирование[Часы (план)], MATCH(Хронология[[#This Row],[Ключ]], Планирование[Ключ], 0)), 0)) ), 0 ), 0 ) -> 0 | AL29: =IF( Хронология[[#This Row],[Результат]]="ПНВ", MAX(0, MAX(0, SUMIFS(Хронология[Часы], Хронология[Ключ], Хронология[[#This Row],[Ключ]], Хронология[Начало], "<=" & Хронология[[#This Row],[Начало]]) - IFERROR(INDEX(Планирование[Часы (план)], MATCH(Хронология[[#This Row],[Ключ]], Планирование[Ключ], 0)), 0)) - MAX(0, SUMIFS(Хронология[Часы], Хронология[Ключ], Хронология[[#This Row],[Ключ]], Хронология[Начало], "<" & Хронология[[#This Row],[Начало]]) - IFERROR(INDEX(Планирование[Часы (план)], MATCH(Хронология[[#This Row],[Ключ]], Планирование[Ключ], 0)), 0)) ), 0 ) -> 5 | AM29: =IF(Хронология[[#This Row],[Результат]]="НПВ", Хронология[[#This Row],[Часы]], 0) -> 0 | AN29: =SUMIFS(Хронология[НПВ], Хронология[Скважина], Хронология[[#This Row],[Скважина]], Хронология[Начало], "<=" & Хронология[[#This Row],[Начало]]) -> 0 | AO29: =SUMIFS(Хронология[ПНВ], Хронология[Скважина], Хронология[[#This Row],[Скважина]], Хронология[Начало], "<=" & Хронология[[#This Row],[Начало]]) -> 22.03 | AP29: =INT(ROUND(Хронология[[#This Row],[Начало]], 3)) -> 46150 | AQ29: =Хронология[[#This Row],[Начало]]-INT(Хронология[[#This Row],[Начало]]) -> 0.29166667 | AR29: =INT(ROUND(Хронология[[#This Row],[Окончание]], 3)) -> 46150 | AS29: =Хронология[[#This Row],[Окончание]]-INT(Хронология[[#This Row],[Окончание]]) -> 0.5 | AT29: =Хронология[[#This Row],[Мастер]] & CHAR(10) & Хронология[[#This Row],[Помощник мастера]] & CHAR(10) & Хронология[[#This Row],[Бурильщик]] -> Вдовин И.О. Жангазиев С.К. | AU29: =IF(Хронология[[#This Row],[Контекст простоя]]="Штатно", Хронология[[#This Row],[Скважина]] & " " & "ОК–" &Хронология[[#This Row],[ОК]] & " " & Хронология[[#This Row],[Этап]] & " " & Хронология[[#This Row],[Вид работ]] & " " & Хронология[[#This Row],[Объект работ]] & " " & Хронология[[#This Row],[Рейс]], Хронология[[#This Row],[Скважина]] & " " & "ОК–" &Хронология[[#This Row],[ОК]] & " " & Хронология[[#This Row],[Этап]] & " " & Хронология[[#This Row],[Контекст простоя]] & " " & Хронология[[#This Row],[Событие]] & " " & Хронология[[#This Row],[Вид работ]] & " " & Хронология[[#This Row],[Объект работ]] & " " & Хронология[[#This Row],[Рейс]]) -> 431 ОК– ДПМ Передвижка УПА | AV29: =Хронология[[#This Row],[Результат]]&": "&Хронология[[#This Row],[Событие]]& CHAR(10) &Хронология[[#This Row],[Вид работ]]&" "&Хронология[[#This Row],[Объект работ]] -> ПНВ: Передвижка УПА | AW29: =SUMIF($AU$2:AU29, Хронология[[#This Row],[Ключ]], $AH$2:AH29) -> 1.6041667 | AX29: =Хронология[[#This Row],[Вид работ]] & " " & Хронология[[#This Row],[Объект работ]] -> Передвижка УПА
A30: ГДТ | B30: КРС | C30: Казанское | D30: 1 | E30: 431 | F30: Вдовин И.О. | H30: Жангазиев С.К. | L30: ДПМ | M30: Штатно | O30: ПР | P30: Передвижка | Q30: Оборудование | R30: УПА | T30: Получение наряд-допуска. Планировка площадки. Мобилизация на скв. 431 КП26 — 1 рейс (емкость 40м³). | U30: 4 | W30: Работы окончены | X30: Победит Холдинг | AE30: =IFERROR(IF(Хронология[[#This Row],[Забой, м]]-V29<0, 0, Хронология[[#This Row],[Забой, м]]-V29), 0) -> 0 | AF30: =AG29 -> 46150.5 | AG30: =Хронология[[#This Row],[Начало]]+Хронология[[#This Row],[Сутки]] -> 46150.667 | AH30: =Хронология[[#This Row],[Часы]]/24 -> 0.16666667 | AI30: =IFERROR(Хронология[[#This Row],[Сутки]]+AI29, Хронология[[#This Row],[Сутки]]) -> 5.8333333 | AJ30: =IF(Хронология[[#This Row],[Этап]]="Доп. работы", "ПВ", IFERROR( IF(AND( MATCH(Хронология[[#This Row],[Ключ]], Планирование[Ключ], 0), Хронология[[#This Row],[Подытог за операцию]] <= INDEX(Планирование[Сутки (план)], MATCH(Хронология[[#This Row],[Ключ]], Планирование[Ключ], 0)) ), "ПВ", "ПНВ"), "НПВ")) -> ПНВ | AK30: =IF( OR(Хронология[[#This Row],[Результат]]="ПВ", Хронология[[#This Row],[Результат]]="ПНВ"), Хронология[[#This Row],[Часы]] - IF( Хронология[[#This Row],[Результат]]="ПНВ", MAX(0, MAX(0, SUMIFS(Хронология[Часы], Хронология[Ключ], Хронология[[#This Row],[Ключ]], Хронология[Начало], "<=" & Хронология[[#This Row],[Начало]]) - IFERROR(INDEX(Планирование[Часы (план)], MATCH(Хронология[[#This Row],[Ключ]], Планирование[Ключ], 0)), 0)) - MAX(0, SUMIFS(Хронология[Часы], Хронология[Ключ], Хронология[[#This Row],[Ключ]], Хронология[Начало], "<" & Хронология[[#This Row],[Начало]]) - IFERROR(INDEX(Планирование[Часы (план)], MATCH(Хронология[[#This Row],[Ключ]], Планирование[Ключ], 0)), 0)) ), 0 ), 0 ) -> 0 | AL30: =IF( Хронология[[#This Row],[Результат]]="ПНВ", MAX(0, MAX(0, SUMIFS(Хронология[Часы], Хронология[Ключ], Хронология[[#This Row],[Ключ]], Хронология[Начало], "<=" & Хронология[[#This Row],[Начало]]) - IFERROR(INDEX(Планирование[Часы (план)], MATCH(Хронология[[#This Row],[Ключ]], Планирование[Ключ], 0)), 0)) - MAX(0, SUMIFS(Хронология[Часы], Хронология[Ключ], Хронология[[#This Row],[Ключ]], Хронология[Начало], "<" & Хронология[[#This Row],[Начало]]) - IFERROR(INDEX(Планирование[Часы (план)], MATCH(Хронология[[#This Row],[Ключ]], Планирование[Ключ], 0)), 0)) ), 0 ) -> 4 | AM30: =IF(Хронология[[#This Row],[Результат]]="НПВ", Хронология[[#This Row],[Часы]], 0) -> 0 | AN30: =SUMIFS(Хронология[НПВ], Хронология[Скважина], Хронология[[#This Row],[Скважина]], Хронология[Начало], "<=" & Хронология[[#This Row],[Начало]]) -> 0 | AO30: =SUMIFS(Хронология[ПНВ], Хронология[Скважина], Хронология[[#This Row],[Скважина]], Хронология[Начало], "<=" & Хронология[[#This Row],[Начало]]) -> 26.03 | AP30: =INT(ROUND(Хронология[[#This Row],[Начало]], 3)) -> 46150 | AQ30: =Хронология[[#This Row],[Начало]]-INT(Хронология[[#This Row],[Начало]]) -> 0.5 | AR30: =INT(ROUND(Хронология[[#This Row],[Окончание]], 3)) -> 46150 | AS30: =Хронология[[#This Row],[Окончание]]-INT(Хронология[[#This Row],[Окончание]]) -> 0.66666667 | AT30: =Хронология[[#This Row],[Мастер]] & CHAR(10) & Хронология[[#This Row],[Помощник мастера]] & CHAR(10) & Хронология[[#This Row],[Бурильщик]] -> Вдовин И.О. Жангазиев С.К. | AU30: =IF(Хронология[[#This Row],[Контекст простоя]]="Штатно", Хронология[[#This Row],[Скважина]] & " " & "ОК–" &Хронология[[#This Row],[ОК]] & " " & Хронология[[#This Row],[Этап]] & " " & Хронология[[#This Row],[Вид работ]] & " " & Хронология[[#This Row],[Объект работ]] & " " & Хронология[[#This Row],[Рейс]], Хронология[[#This Row],[Скважина]] & " " & "ОК–" &Хронология[[#This Row],[ОК]] & " " & Хронология[[#This Row],[Этап]] & " " & Хронология[[#This Row],[Контекст простоя]] & " " & Хронология[[#This Row],[Событие]] & " " & Хронология[[#This Row],[Вид работ]] & " " & Хронология[[#This Row],[Объект работ]] & " " & Хронология[[#This Row],[Рейс]]) -> 431 ОК– ДПМ Передвижка УПА | AV30: =Хронология[[#This Row],[Результат]]&": "&Хронология[[#This Row],[Событие]]& CHAR(10) &Хронология[[#This Row],[Вид работ]]&" "&Хронология[[#This Row],[Объект работ]] -> ПНВ: Передвижка УПА | AW30: =SUMIF($AU$2:AU30, Хронология[[#This Row],[Ключ]], $AH$2:AH30) -> 1.7708333 | AX30: =Хронология[[#This Row],[Вид работ]] & " " & Хронология[[#This Row],[Объект работ]] -> Передвижка УПА
A31: ГДТ | B31: КРС | C31: Казанское | D31: 1 | E31: 431 | F31: Вдовин И.О. | H31: Жангазиев С.К. | L31: ДПМ | M31: Штатно | O31: ПР | P31: Передвижка | Q31: Оборудование | R31: УПА | T31: Мобилизация на скв. 431 КП26 — 2 рейса (вагон-дом, стеллажи, доп. стеллажи, автонаматыватель, подключение). Растаскивание кабеля СИП 150м. | U31: 4 | W31: Работы окончены | X31: Победит Холдинг | AE31: =IFERROR(IF(Хронология[[#This Row],[Забой, м]]-V30<0, 0, Хронология[[#This Row],[Забой, м]]-V30), 0) -> 0 | AF31: =AG30 -> 46150.667 | AG31: =Хронология[[#This Row],[Начало]]+Хронология[[#This Row],[Сутки]] -> 46150.833 | AH31: =Хронология[[#This Row],[Часы]]/24 -> 0.16666667 | AI31: =IFERROR(Хронология[[#This Row],[Сутки]]+AI30, Хронология[[#This Row],[Сутки]]) -> 6 | AJ31: =IF(Хронология[[#This Row],[Этап]]="Доп. работы", "ПВ", IFERROR( IF(AND( MATCH(Хронология[[#This Row],[Ключ]], Планирование[Ключ], 0), Хронология[[#This Row],[Подытог за операцию]] <= INDEX(Планирование[Сутки (план)], MATCH(Хронология[[#This Row],[Ключ]], Планирование[Ключ], 0)) ), "ПВ", "ПНВ"), "НПВ")) -> ПНВ | AK31: =IF( OR(Хронология[[#This Row],[Результат]]="ПВ", Хронология[[#This Row],[Результат]]="ПНВ"), Хронология[[#This Row],[Часы]] - IF( Хронология[[#This Row],[Результат]]="ПНВ", MAX(0, MAX(0, SUMIFS(Хронология[Часы], Хронология[Ключ], Хронология[[#This Row],[Ключ]], Хронология[Начало], "<=" & Хронология[[#This Row],[Начало]]) - IFERROR(INDEX(Планирование[Часы (план)], MATCH(Хронология[[#This Row],[Ключ]], Планирование[Ключ], 0)), 0)) - MAX(0, SUMIFS(Хронология[Часы], Хронология[Ключ], Хронология[[#This Row],[Ключ]], Хронология[Начало], "<" & Хронология[[#This Row],[Начало]]) - IFERROR(INDEX(Планирование[Часы (план)], MATCH(Хронология[[#This Row],[Ключ]], Планирование[Ключ], 0)), 0)) ), 0 ), 0 ) -> 0 | AL31: =IF( Хронология[[#This Row],[Результат]]="ПНВ", MAX(0, MAX(0, SUMIFS(Хронология[Часы], Хронология[Ключ], Хронология[[#This Row],[Ключ]], Хронология[Начало], "<=" & Хронология[[#This Row],[Начало]]) - IFERROR(INDEX(Планирование[Часы (план)], MATCH(Хронология[[#This Row],[Ключ]], Планирование[Ключ], 0)), 0)) - MAX(0, SUMIFS(Хронология[Часы], Хронология[Ключ], Хронология[[#This Row],[Ключ]], Хронология[Начало], "<" & Хронология[[#This Row],[Начало]]) - IFERROR(INDEX(Планирование[Часы (план)], MATCH(Хронология[[#This Row],[Ключ]], Планирование[Ключ], 0)), 0)) ), 0 ) -> 4 | AM31: =IF(Хронология[[#This Row],[Результат]]="НПВ", Хронология[[#This Row],[Часы]], 0) -> 0 | AN31: =SUMIFS(Хронология[НПВ], Хронология[Скважина], Хронология[[#This Row],[Скважина]], Хронология[Начало], "<=" & Хронология[[#This Row],[Начало]]) -> 0 | AO31: =SUMIFS(Хронология[ПНВ], Хронология[Скважина], Хронология[[#This Row],[Скважина]], Хронология[Начало], "<=" & Хронология[[#This Row],[Начало]]) -> 30.03 | AP31: =INT(ROUND(Хронология[[#This Row],[Начало]], 3)) -> 46150 | AQ31: =Хронология[[#This Row],[Начало]]-INT(Хронология[[#This Row],[Начало]]) -> 0.66666667 | AR31: =INT(ROUND(Хронология[[#This Row],[Окончание]], 3)) -> 46150 | AS31: =Хронология[[#This Row],[Окончание]]-INT(Хронология[[#This Row],[Окончание]]) -> 0.83333333 | AT31: =Хронология[[#This Row],[Мастер]] & CHAR(10) & Хронология[[#This Row],[Помощник мастера]] & CHAR(10) & Хронология[[#This Row],[Бурильщик]] -> Вдовин И.О. Жангазиев С.К. | AU31: =IF(Хронология[[#This Row],[Контекст простоя]]="Штатно", Хронология[[#This Row],[Скважина]] & " " & "ОК–" &Хронология[[#This Row],[ОК]] & " " & Хронология[[#This Row],[Этап]] & " " & Хронология[[#This Row],[Вид работ]] & " " & Хронология[[#This Row],[Объект работ]] & " " & Хронология[[#This Row],[Рейс]], Хронология[[#This Row],[Скважина]] & " " & "ОК–" &Хронология[[#This Row],[ОК]] & " " & Хронология[[#This Row],[Этап]] & " " & Хронология[[#This Row],[Контекст простоя]] & " " & Хронология[[#This Row],[Событие]] & " " & Хронология[[#This Row],[Вид работ]] & " " & Хронология[[#This Row],[Объект работ]] & " " & Хронология[[#This Row],[Рейс]]) -> 431 ОК– ДПМ Передвижка УПА | AV31: =Хронология[[#This Row],[Результат]]&": "&Хронология[[#This Row],[Событие]]& CHAR(10) &Хронология[[#This Row],[Вид работ]]&" "&Хронология[[#This Row],[Объект работ]] -> ПНВ: Передвижка УПА | AW31: =SUMIF($AU$2:AU31, Хронология[[#This Row],[Ключ]], $AH$2:AH31) -> 1.9375 | AX31: =Хронология[[#This Row],[Вид работ]] & " " & Хронология[[#This Row],[Объект работ]] -> Передвижка УПА
